Workbook
Name ChampsData: WatchList!$A$6:$B$20
Name ChampsData: #REF!
Name ContendersData: #REF!
Name CzallengersData: #REF!
Name DataAll: Challengers!#REF!
Name DataAll: Champions!$A$7:$BC$152
Name DataAll: Contenders!$A$7:$BC$221
Name DataAll: Historical!$A$7:$BG$411
Name DataAll: 'All CCC'!$A$7:$BC$367
Name Deletions: Changes!$A$162:$I$1098
Name FrozenAngels: Notes!$A$181:$J$197
Name NearChallengers: Notes!#REF!
Name WatchList: WatchList!$A$6:$B$20

Sheet Title
M6: The Dividend Champions List
M8: A Resource For Dividend Growth Investors
M18: A monthly publication tracking companies with a history of consistently increasing their dividends
M20: To be included on the list, a company must be consistently increasing its calendar year dividend payout for at least the past 5 years
M34: Created by David Fish
M36: Updated by Justin Law
M38: ©2026 All Rights Reserved. This listing is intended for personal, non-commercial use only.

Sheet Champions
A1: U.S. Dividend Champions | C1: Sign up for free updates at: | J1: Dividend Information | Z1: Fundamental Data | AC1: Numbers in Blue directly from Finviz | AO1: Special | AR1: Dividend Growth Model | AY1: Technical Data | BD1: Other
A2: (and American Depository Receipts) | C2: https://www.ireitinvestor.com/dividend-champions/ | J2: DEG=Dividend to Earnings Growth; A/D=Acceleration/Deceleration; DGR=Dividend Growth Rate | Z2: EPS=Earnings Per Share; P/E=Price/Earnings Per Share; TTM=Trailing Twelve Months; FYE=Fiscal Year End; MRQ=Most Recent Quarter; ROE = Return on Equity | AO2: (see Notes tab) | AR2: (based on Earnings Estimates, if available) | AY2: MMA=Moving Market Average
A3: 46142 | J3: Dates in Red (right-aligned) indicate last increase more than a year ago (Ex-Div Date) | Q3: Dates in Green (centered) indicate increase (by Ex-Div. Date) expected in next 2 months | AR3: Past Performance is No Guarantee of Future Results
J4: Numbers in Gray last updated 12/31/2025 | Z4: Disclaimer: Although all figures are thought to be correct, no guarantee is expressed or implied. | AR4: Last updated 12/31/2025 | AW4: 5-year Total | AZ4: Current Price as % from:
A5: Company | B5: Ticker | E5: No. | F5: CCC | G5: DRIP Fees | I5: 46142 | J5: Div. | K5: Current | L5: Payouts/ | N5: Qtly | O5: Previous | P5: Last Increased on: | R5: MR% | S5: DGR | T5: DGR | U5: DGR | V5: DGR | W5: 5/10 | X5: Past 5yr | Y5: &=MultiIncThisYr | Z5: EPS% | AA5: TTM | AB5: FYE | AC5: TTM | AE5: TTM | AF5: MRQ | AG5: TTM | AH5: TTM | AI5: NY | AJ5: Past 5yr | AK5: Est-5yr | AL5: MktCap | AM5: Inside | AN5: Debt/ | AO5: Tweed | AP5: Chowder | AQ5: +/-% vs. | AR5: Estimated Dividends to be Paid in Year: | AW5: Est. Payback | AY5: 5-yr | AZ5: 52-wk | BA5: 52-wk | BB5: 50-day | BC5: 200-day | BE5: Streak | BF5: Recessions | BG5: TTM | BH5: Dividend
A6: Name | B6: Symbol | C6: Sector | D6: Industry | E6: Yrs | F6: Seq | G6: DR | H6: SP | I6: Price | J6: Yield | K6: Dividend | L6: Year | M6: Annualized | N6: Sch | O6: Payout | P6: Ex-Div | Q6: Pay | R6: Inc. | S6: 1-yr | T6: 3-yr | U6: 5-yr | V6: 10-yr | W6: A/D* | X6: DEG | Y6: Notes | Z6: Payout | AA6: P/E | AB6: Month | AC6: EPS | AD6: PEG | AE6: P/Sales | AF6: P/Book | AG6: ROE | AH6: Growth | AI6: Growth | AJ6: Growth | AK6: Growth | AL6: ($Mil) | AM6: Own. | AN6: Equity | AO6: Factor | AP6: Rule | AQ6: Graham | AR6: 2024 | AS6: 2025 | AT6: 2026 | AU6: 2027 | AV6: 2028 | AW6: $ | AX6: % | AY6: Beta | AZ6: Low | BA6: High | BB6: MMA | BC6: MMA | BD6: OTC | BE6: Began | BF6: Survived | BG6: ROA | BH6: Currency | BI6: Tax
A7: ABM Industries Incorporated | B7: ABM | C7: Industrials | D7: Commercial Services & Supplies | E7: 59 | F7: 18 | G7: Y | H7: N | I7: 40.8 | J7: =(M7/I7)*100 -> 2.8431373 | K7: 0.29 | L7: 4 | M7: =K7*L7 -> 1.16 | N7: B05 | O7: 0.265 | P7: 46038 | Q7: 46055 | R7: =(K7-O7)/O7*100 -> 9.4339623 | S7: =IF(INDEX(Historical!$D$7:$D1047,MATCH(B7,Historical!$B$7:$B$1044,0))=0,"n/a",(INDEX(Historical!$C$7:$C$1044,MATCH(B7,Historical!$B$7:$B$1044,0))/INDEX(Historical!$D$7:$D$1044,MATCH(B7,Historical!$B$7:$B$1044,0))-1)*100) -> 17.777778 | T7: =IF(INDEX(Historical!$F$7:$F$1044,MATCH(B7,Historical!$B$7:$B$1044,0))=0,"n/a",((INDEX(Historical!$C$7:$C$1044,MATCH(B7,Historical!$B$7:$B$1044,0))/INDEX(Historical!$F$7:$F$1044,MATCH(B7,Historical!$B$7:$B$1044,0)))^(1/3)-1)*100) -> 10.765307 | U7: =IF(INDEX(Historical!$H$7:$H$1044,MATCH(B7,Historical!$B$7:$B$1044,0))=0,"n/a",((INDEX(Historical!$C$7:$C$1044,MATCH(B7,Historical!$B$7:$B$1044,0))/INDEX(Historical!$H$7:$H$1044,MATCH(B7,Historical!$B$7:$B$1044,0)))^(1/5)-1)*100) -> 7.4520806 | V7: =IF(INDEX(Historical!$M$7:$M$1044,MATCH(B7,Historical!$B$7:$B$1044,0))=0,"n/a",((INDEX(Historical!$C$7:$C$1044,MATCH(B7,Historical!$B$7:$B$1044,0))/INDEX(Historical!$M$7:$M$1044,MATCH(B7,Historical!$B$7:$B$1044,0)))^(1/10)-1)*100) -> 5.1750166 | W7: =IF(OR(U7<=0,U7="n/a",V7<=0,V7="n/a"),"n/a",U7/V7) -> 1.440011 | X7: =IF(OR(AJ7<=0,AJ7="n/a",U7<=0,U7="n/a"),"n/a",U7/AJ7) -> 0.029056344 | Z7: =IF(OR(AC7<0.01,AC7="n/a"),"n/a",M7/AC7*100) -> 45.669291 | AA7: =IF(OR(AC7<0.01,AC7="n/a"),"n/a",I7/AC7) -> 16.062992 | AB7: 10 | AC7: 2.54 | AD7: 0.92 | AE7: 0.27 | AF7: 1.39 | AG7: 9 | AH7: 15.09 | AI7: 9.5 | AJ7: 256.47 | AK7: 10.25 | AL7: 2390 | AM7: 1.68 | AN7: 1.01 | AO7: =IF(U7="n/a","n/a",IF(AA7<0,"n/a",IF(AA7="n/a","n/a",J7+U7-AA7))) -> -5.7677743 | AP7: =IF(U7="n/a","n/a",J7+U7) -> 10.295218 | AQ7: =IF(OR(AC7<0.01,AC7="n/a",AF7="n/a"),"n/a",(I7/SQRT(22.5*AC7*(I7/AF7))-1)*100) -> -0.38393915 | AR7: =INDEX(Historical!$C$7:$C$1045,MATCH(B7,Historical!$B$7:$B$1045,0))*IF(AH7="n/a",1.03,IF(AH7<0,1.01,IF(AH7>10,1.1,(1+AH7/100)))) -> 1.166 | AS7: =IF($AI7="n/a",1.03*AR7,IF($AI7<0,1.01*AR7,IF($AI7>10,1.1*AR7,(1+$AI7/100)*AR7))) -> 1.27677 | AT7: =IF($AK7="n/a",1.03*AS7,IF($AK7<0,1.01*AS7,IF($AK7>10,1.1*AS7,(1+$AK7/100)*AS7))) -> 1.404447 | AU7: =IF($AK7="n/a",1.03*AT7,IF($AK7<0,1.01*AT7,IF($AK7>10,1.1*AT7,(1+$AK7/100)*AT7))) -> 1.5448917 | AV7: =IF($AK7="n/a",1.03*AU7,IF($AK7<0,1.01*AU7,IF($AK7>10,1.1*AU7,(1+$AK7/100)*AU7))) -> 1.6993809 | AW7: =SUM(AR7:AV7) -> 7.0914896 | AX7: =AW7/I7*100 -> 17.381102 | AY7: 0.72 | AZ7: 10.38 | BA7: -22.93 | BB7: 0.72 | BC7: -7.65 | BE7: 1968 | BF7: =IF(BE7>2020,0,IF(BE7>2008,1,IF(BE7>2001,2,IF(BE7>1990,3,IF(BE7>1980,4,IF(BE7>1973,5,IF(BE7>1970,6,IF(BE7>1960,7,IF(BE7>1958,8,IF(BE7>1953,9,10)))))))))) -> 7 | BG7: 3 | BH7: USD | BI7: Corp
A8: Archer-Daniels-Midland Company | B8: ADM | C8: Consumer Staples | D8: Food Products | E8: 51 | F8: 47 | G8: N | H8: Y | I8: 74.54 | J8: =(M8/I8)*100 -> 2.7904481 | K8: 0.52 | L8: 4 | M8: =K8*L8 -> 2.08 | N8: C13 | O8: 0.51 | P8: 46070 | Q8: 46091 | R8: =(K8-O8)/O8*100 -> 1.9607843 | S8: =IF(INDEX(Historical!$D$7:$D1054,MATCH(B8,Historical!$B$7:$B$1044,0))=0,"n/a",(INDEX(Historical!$C$7:$C$1044,MATCH(B8,Historical!$B$7:$B$1044,0))/INDEX(Historical!$D$7:$D$1044,MATCH(B8,Historical!$B$7:$B$1044,0))-1)*100) -> 2 | T8: =IF(INDEX(Historical!$F$7:$F$1044,MATCH(B8,Historical!$B$7:$B$1044,0))=0,"n/a",((INDEX(Historical!$C$7:$C$1044,MATCH(B8,Historical!$B$7:$B$1044,0))/INDEX(Historical!$F$7:$F$1044,MATCH(B8,Historical!$B$7:$B$1044,0)))^(1/3)-1)*100) -> 8.4351443 | U8: =IF(INDEX(Historical!$H$7:$H$1044,MATCH(B8,Historical!$B$7:$B$1044,0))=0,"n/a",((INDEX(Historical!$C$7:$C$1044,MATCH(B8,Historical!$B$7:$B$1044,0))/INDEX(Historical!$H$7:$H$1044,MATCH(B8,Historical!$B$7:$B$1044,0)))^(1/5)-1)*100) -> 7.2145026 | V8: =IF(INDEX(Historical!$M$7:$M$1044,MATCH(B8,Historical!$B$7:$B$1044,0))=0,"n/a",((INDEX(Historical!$C$7:$C$1044,MATCH(B8,Historical!$B$7:$B$1044,0))/INDEX(Historical!$M$7:$M$1044,MATCH(B8,Historical!$B$7:$B$1044,0)))^(1/10)-1)*100) -> 6.1796317 | W8: =IF(OR(U8<=0,U8="n/a",V8<=0,V8="n/a"),"n/a",U8/V8) -> 1.1674648 | X8: =IF(OR(AJ8<=0,AJ8="n/a",U8<=0,U8="n/a"),"n/a",U8/AJ8) -> n/a | Z8: =IF(OR(AC8<0.01,AC8="n/a"),"n/a",M8/AC8*100) -> 93.273543 | AA8: =IF(OR(AC8<0.01,AC8="n/a"),"n/a",I8/AC8) -> 33.426009 | AB8: 6 | AC8: 2.23 | AD8: 0.99 | AE8: 0.45 | AF8: 1.57 | AG8: 4.8 | AH8: 21.35 | AI8: 16.27 | AJ8: -6.68 | AK8: 15.62 | AL8: 35920 | AM8: 0.68 | AN8: 0.43 | AO8: =IF(U8="n/a","n/a",IF(AA8<0,"n/a",IF(AA8="n/a","n/a",J8+U8-AA8))) -> -23.421058 | AP8: =IF(U8="n/a","n/a",J8+U8) -> 10.004951 | AQ8: =IF(OR(AC8<0.01,AC8="n/a",AF8="n/a"),"n/a",(I8/SQRT(22.5*AC8*(I8/AF8))-1)*100) -> 52.721728 | AR8: =INDEX(Historical!$C$7:$C$1045,MATCH(B8,Historical!$B$7:$B$1045,0))*IF(AH8="n/a",1.03,IF(AH8<0,1.01,IF(AH8>10,1.1,(1+AH8/100)))) -> 2.244 | AS8: =IF($AI8="n/a",1.03*AR8,IF($AI8<0,1.01*AR8,IF($AI8>10,1.1*AR8,(1+$AI8/100)*AR8))) -> 2.4684 | AT8: =IF($AK8="n/a",1.03*AS8,IF($AK8<0,1.01*AS8,IF($AK8>10,1.1*AS8,(1+$AK8/100)*AS8))) -> 2.71524 | AU8: =IF($AK8="n/a",1.03*AT8,IF($AK8<0,1.01*AT8,IF($AK8>10,1.1*AT8,(1+$AK8/100)*AT8))) -> 2.986764 | AV8: =IF($AK8="n/a",1.03*AU8,IF($AK8<0,1.01*AU8,IF($AK8>10,1.1*AU8,(1+$AK8/100)*AU8))) -> 3.2854404 | AW8: =SUM(AR8:AV8) -> 13.699844 | AX8: =AW8/I8*100 -> 18.379185 | AY8: 0.58 | AZ8: 59.24 | BA8: -0.47 | BB8: 6.48 | BC8: 18.08 | BE8: 1976 | BF8: =IF(BE8>2020,0,IF(BE8>2008,1,IF(BE8>2001,2,IF(BE8>1990,3,IF(BE8>1980,4,IF(BE8>1973,5,IF(BE8>1970,6,IF(BE8>1960,7,IF(BE8>1958,8,IF(BE8>1953,9,10)))))))))) -> 5 | BG8: 2.04 | BH8: USD | BI8: Corp
A9: Automatic Data Processing, Inc. | B9: ADP | C9: Industrials | D9: Professional Services | E9: 50 | F9: 51 | G9: N | H9: Y | I9: 211.91 | J9: =(M9/I9)*100 -> 3.2089094 | K9: 1.7 | L9: 4 | M9: =K9*L9 -> 6.8 | N9: A01 | O9: 1.54 | P9: 46003 | Q9: 46023 | R9: =(K9-O9)/O9*100 -> 10.38961 | S9: =IF(INDEX(Historical!$D$7:$D1055,MATCH(B9,Historical!$B$7:$B$1044,0))=0,"n/a",(INDEX(Historical!$C$7:$C$1044,MATCH(B9,Historical!$B$7:$B$1044,0))/INDEX(Historical!$D$7:$D$1044,MATCH(B9,Historical!$B$7:$B$1044,0))-1)*100) -> 10 | T9: =IF(INDEX(Historical!$F$7:$F$1044,MATCH(B9,Historical!$B$7:$B$1044,0))=0,"n/a",((INDEX(Historical!$C$7:$C$1044,MATCH(B9,Historical!$B$7:$B$1044,0))/INDEX(Historical!$F$7:$F$1044,MATCH(B9,Historical!$B$7:$B$1044,0)))^(1/3)-1)*100) -> 13.980125 | U9: =IF(INDEX(Historical!$H$7:$H$1044,MATCH(B9,Historical!$B$7:$B$1044,0))=0,"n/a",((INDEX(Historical!$C$7:$C$1044,MATCH(B9,Historical!$B$7:$B$1044,0))/INDEX(Historical!$H$7:$H$1044,MATCH(B9,Historical!$B$7:$B$1044,0)))^(1/5)-1)*100) -> 11.095346 | V9: =IF(INDEX(Historical!$M$7:$M$1044,MATCH(B9,Historical!$B$7:$B$1044,0))=0,"n/a",((INDEX(Historical!$C$7:$C$1044,MATCH(B9,Historical!$B$7:$B$1044,0))/INDEX(Historical!$M$7:$M$1044,MATCH(B9,Historical!$B$7:$B$1044,0)))^(1/10)-1)*100) -> 12.132748 | W9: =IF(OR(U9<=0,U9="n/a",V9<=0,V9="n/a"),"n/a",U9/V9) -> 0.91449573 | X9: =IF(OR(AJ9<=0,AJ9="n/a",U9<=0,U9="n/a"),"n/a",U9/AJ9) -> 0.93552664 | Z9: =IF(OR(AC9<0.01,AC9="n/a"),"n/a",M9/AC9*100) -> 63.373719 | AA9: =IF(OR(AC9<0.01,AC9="n/a"),"n/a",I9/AC9) -> 19.749301 | AB9: 6 | AC9: 10.73 | AD9: 1.78 | AE9: 3.95 | AF9: 13.37 | AG9: 71.2 | AH9: 10.32 | AI9: 9.91 | AJ9: 11.86 | AK9: 9.79 | AL9: 85320 | AM9: 0.15 | AN9: 0.68 | AO9: =IF(U9="n/a","n/a",IF(AA9<0,"n/a",IF(AA9="n/a","n/a",J9+U9-AA9))) -> -5.4450456 | AP9: =IF(U9="n/a","n/a",J9+U9) -> 14.304255 | AQ9: =IF(OR(AC9<0.01,AC9="n/a",AF9="n/a"),"n/a",(I9/SQRT(22.5*AC9*(I9/AF9))-1)*100) -> 242.57077 | AR9: =INDEX(Historical!$C$7:$C$1045,MATCH(B9,Historical!$B$7:$B$1045,0))*IF(AH9="n/a",1.03,IF(AH9<0,1.01,IF(AH9>10,1.1,(1+AH9/100)))) -> 6.776 | AS9: =IF($AI9="n/a",1.03*AR9,IF($AI9<0,1.01*AR9,IF($AI9>10,1.1*AR9,(1+$AI9/100)*AR9))) -> 7.4475016 | AT9: =IF($AK9="n/a",1.03*AS9,IF($AK9<0,1.01*AS9,IF($AK9>10,1.1*AS9,(1+$AK9/100)*AS9))) -> 8.176612 | AU9: =IF($AK9="n/a",1.03*AT9,IF($AK9<0,1.01*AT9,IF($AK9>10,1.1*AT9,(1+$AK9/100)*AT9))) -> 8.9771023 | AV9: =IF($AK9="n/a",1.03*AU9,IF($AK9<0,1.01*AU9,IF($AK9>10,1.1*AU9,(1+$AK9/100)*AU9))) -> 9.8559606 | AW9: =SUM(AR9:AV9) -> 41.233177 | AX9: =AW9/I9*100 -> 19.457872 | AY9: 0.86 | AZ9: 12.62 | BA9: -35.77 | BB9: 2.42 | BC9: -17.61 | BE9: 1976 | BF9: =IF(BE9>2020,0,IF(BE9>2008,1,IF(BE9>2001,2,IF(BE9>1990,3,IF(BE9>1980,4,IF(BE9>1973,5,IF(BE9>1970,6,IF(BE9>1960,7,IF(BE9>1958,8,IF(BE9>1953,9,10)))))))))) -> 5 | BG9: 7.19 | BH9: USD | BI9: Corp
A10: Aflac Incorporated | B10: AFL | C10: Financials | D10: Insurance | E10: 44 | F10: 61 | G10: N | H10: N | I10: 113.67 | J10: =(M10/I10)*100 -> 2.1465646 | K10: 0.61 | L10: 4 | M10: =K10*L10 -> 2.44 | N10: C01 | O10: 0.58 | P10: 46071 | Q10: 46083 | R10: =(K10-O10)/O10*100 -> 5.1724138 | S10: =IF(INDEX(Historical!$D$7:$D1060,MATCH(B10,Historical!$B$7:$B$1044,0))=0,"n/a",(INDEX(Historical!$C$7:$C$1044,MATCH(B10,Historical!$B$7:$B$1044,0))/INDEX(Historical!$D$7:$D$1044,MATCH(B10,Historical!$B$7:$B$1044,0))-1)*100) -> 16 | T10: =IF(INDEX(Historical!$F$7:$F$1044,MATCH(B10,Historical!$B$7:$B$1044,0))=0,"n/a",((INDEX(Historical!$C$7:$C$1044,MATCH(B10,Historical!$B$7:$B$1044,0))/INDEX(Historical!$F$7:$F$1044,MATCH(B10,Historical!$B$7:$B$1044,0)))^(1/3)-1)*100) -> 13.18512 | U10: =IF(INDEX(Historical!$H$7:$H$1044,MATCH(B10,Historical!$B$7:$B$1044,0))=0,"n/a",((INDEX(Historical!$C$7:$C$1044,MATCH(B10,Historical!$B$7:$B$1044,0))/INDEX(Historical!$H$7:$H$1044,MATCH(B10,Historical!$B$7:$B$1044,0)))^(1/5)-1)*100) -> 15.678858 | V10: =IF(INDEX(Historical!$M$7:$M$1044,MATCH(B10,Historical!$B$7:$B$1044,0))=0,"n/a",((INDEX(Historical!$C$7:$C$1044,MATCH(B10,Historical!$B$7:$B$1044,0))/INDEX(Historical!$M$7:$M$1044,MATCH(B10,Historical!$B$7:$B$1044,0)))^(1/10)-1)*100) -> 11.374583 | W10: =IF(OR(U10<=0,U10="n/a",V10<=0,V10="n/a"),"n/a",U10/V10) -> 1.3784117 | X10: =IF(OR(AJ10<=0,AJ10="n/a",U10<=0,U10="n/a"),"n/a",U10/AJ10) -> 36.46246 | Z10: =IF(OR(AC10<0.01,AC10="n/a"),"n/a",M10/AC10*100) -> 27.6958 | AA10: =IF(OR(AC10<0.01,AC10="n/a"),"n/a",I10/AC10) -> 12.902384 | AB10: 12 | AC10: 8.81 | AD10: 5.53 | AE10: 3.24 | AF10: 2.59 | AG10: 19.01 | AH10: -3.78 | AI10: 7.22 | AJ10: 0.43 | AK10: 2.66 | AL10: 58560 | AM10: 10.82 | AN10: 0.35 | AO10: =IF(U10="n/a","n/a",IF(AA10<0,"n/a",IF(AA10="n/a","n/a",J10+U10-AA10))) -> 4.9230389 | AP10: =IF(U10="n/a","n/a",J10+U10) -> 17.825423 | AQ10: =IF(OR(AC10<0.01,AC10="n/a",AF10="n/a"),"n/a",(I10/SQRT(22.5*AC10*(I10/AF10))-1)*100) -> 21.869099 | AR10: =INDEX(Historical!$C$7:$C$1045,MATCH(B10,Historical!$B$7:$B$1045,0))*IF(AH10="n/a",1.03,IF(AH10<0,1.01,IF(AH10>10,1.1,(1+AH10/100)))) -> 2.3432 | AS10: =IF($AI10="n/a",1.03*AR10,IF($AI10<0,1.01*AR10,IF($AI10>10,1.1*AR10,(1+$AI10/100)*AR10))) -> 2.512379 | AT10: =IF($AK10="n/a",1.03*AS10,IF($AK10<0,1.01*AS10,IF($AK10>10,1.1*AS10,(1+$AK10/100)*AS10))) -> 2.5792083 | AU10: =IF($AK10="n/a",1.03*AT10,IF($AK10<0,1.01*AT10,IF($AK10>10,1.1*AT10,(1+$AK10/100)*AT10))) -> 2.6478153 | AV10: =IF($AK10="n/a",1.03*AU10,IF($AK10<0,1.01*AU10,IF($AK10>10,1.1*AU10,(1+$AK10/100)*AU10))) -> 2.7182471 | AW10: =SUM(AR10:AV10) -> 12.80085 | AX10: =AW10/I10*100 -> 11.261414 | AY10: 0.64 | AZ10: 17.25 | BA10: -4.74 | BB10: 2.02 | BC10: 3.89 | BE10: 1983 | BF10: =IF(BE10>2020,0,IF(BE10>2008,1,IF(BE10>2001,2,IF(BE10>1990,3,IF(BE10>1980,4,IF(BE10>1973,5,IF(BE10>1970,6,IF(BE10>1960,7,IF(BE10>1958,8,IF(BE10>1953,9,10)))))))))) -> 4 | BG10: 3.86 | BH10: USD | BI10: Corp
A11: Albemarle Corporation | B11: ALB | C11: Materials | D11: Chemicals | E11: 31 | F11: 114 | G11: N | H11: N | I11: 196.7 | J11: =(M11/I11)*100 -> 0.82358922 | K11: 0.405 | L11: 4 | M11: =K11*L11 -> 1.62 | N11: A02 | O11: 0.4 | P11: 45548 | Q11: 45566 | R11: =(K11-O11)/O11*100 -> 1.25 | S11: =IF(INDEX(Historical!$D$7:$D1068,MATCH(B11,Historical!$B$7:$B$1044,0))=0,"n/a",(INDEX(Historical!$C$7:$C$1044,MATCH(B11,Historical!$B$7:$B$1044,0))/INDEX(Historical!$D$7:$D$1044,MATCH(B11,Historical!$B$7:$B$1044,0))-1)*100) -> 0.93457944 | T11: =IF(INDEX(Historical!$F$7:$F$1044,MATCH(B11,Historical!$B$7:$B$1044,0))=0,"n/a",((INDEX(Historical!$C$7:$C$1044,MATCH(B11,Historical!$B$7:$B$1044,0))/INDEX(Historical!$F$7:$F$1044,MATCH(B11,Historical!$B$7:$B$1044,0)))^(1/3)-1)*100) -> 0.94345194 | U11: =IF(INDEX(Historical!$H$7:$H$1044,MATCH(B11,Historical!$B$7:$B$1044,0))=0,"n/a",((INDEX(Historical!$C$7:$C$1044,MATCH(B11,Historical!$B$7:$B$1044,0))/INDEX(Historical!$H$7:$H$1044,MATCH(B11,Historical!$B$7:$B$1044,0)))^(1/5)-1)*100) -> 1.2491865 | V11: =IF(INDEX(Historical!$M$7:$M$1044,MATCH(B11,Historical!$B$7:$B$1044,0))=0,"n/a",((INDEX(Historical!$C$7:$C$1044,MATCH(B11,Historical!$B$7:$B$1044,0))/INDEX(Historical!$M$7:$M$1044,MATCH(B11,Historical!$B$7:$B$1044,0)))^(1/10)-1)*100) -> 3.5311297 | W11: =IF(OR(U11<=0,U11="n/a",V11<=0,V11="n/a"),"n/a",U11/V11) -> 0.35376399 | X11: =IF(OR(AJ11<=0,AJ11="n/a",U11<=0,U11="n/a"),"n/a",U11/AJ11) -> n/a | Y11: 2025 = Year 31 | Z11: =IF(OR(AC11<0.01,AC11="n/a"),"n/a",M11/AC11*100) -> n/a | AA11: =IF(OR(AC11<0.01,AC11="n/a"),"n/a",I11/AC11) -> n/a | AB11: 12 | AC11: -5.76 | AD11: n/a | AE11: 4.51 | AF11: 3.17 | AG11: -5.24 | AH11: 1222.73 | AI11: 6.72 | AJ11: n/a | AK11: n/a | AL11: 23180 | AM11: 0.29 | AN11: 0.35 | AO11: =IF(U11="n/a","n/a",IF(AA11<0,"n/a",IF(AA11="n/a","n/a",J11+U11-AA11))) -> n/a | AP11: =IF(U11="n/a","n/a",J11+U11) -> 2.0727758 | AQ11: =IF(OR(AC11<0.01,AC11="n/a",AF11="n/a"),"n/a",(I11/SQRT(22.5*AC11*(I11/AF11))-1)*100) -> n/a | AR11: =INDEX(Historical!$C$7:$C$1045,MATCH(B11,Historical!$B$7:$B$1045,0))*IF(AH11="n/a",1.03,IF(AH11<0,1.01,IF(AH11>10,1.1,(1+AH11/100)))) -> 1.782 | AS11: =IF($AI11="n/a",1.03*AR11,IF($AI11<0,1.01*AR11,IF($AI11>10,1.1*AR11,(1+$AI11/100)*AR11))) -> 1.9017504 | AT11: =IF($AK11="n/a",1.03*AS11,IF($AK11<0,1.01*AS11,IF($AK11>10,1.1*AS11,(1+$AK11/100)*AS11))) -> 1.9588029 | AU11: =IF($AK11="n/a",1.03*AT11,IF($AK11<0,1.01*AT11,IF($AK11>10,1.1*AT11,(1+$AK11/100)*AT11))) -> 2.017567 | AV11: =IF($AK11="n/a",1.03*AU11,IF($AK11<0,1.01*AU11,IF($AK11>10,1.1*AU11,(1+$AK11/100)*AU11))) -> 2.078094 | AW11: =SUM(AR11:AV11) -> 9.7382143 | AX11: =AW11/I11*100 -> 4.9507953 | AY11: 1.36 | AZ11: 266.29 | BA11: -8.81 | BB11: 10.27 | BC11: 52.08 | BE11: 1995 | BF11: =IF(BE11>2020,0,IF(BE11>2008,1,IF(BE11>2001,2,IF(BE11>1990,3,IF(BE11>1980,4,IF(BE11>1973,5,IF(BE11>1970,6,IF(BE11>1960,7,IF(BE11>1958,8,IF(BE11>1953,9,10)))))))))) -> 3 | BG11: -3.1 | BH11: USD | BI11: Corp
A12: Alerus Financial Corporation | B12: ALRS | C12: Financials | D12: Diversified Financial Services | E12: 27 | F12: 137 | G12: - | H12: - | I12: 26.94 | J12: =(M12/I12)*100 -> 3.1180401 | K12: 0.21 | L12: 4 | M12: =K12*L12 -> 0.84 | N12: A10 | O12: 0.2 | P12: 45835 | Q12: 45849 | R12: =(K12-O12)/O12*100 -> 5 | S12: =IF(INDEX(Historical!$D$7:$D1072,MATCH(B12,Historical!$B$7:$B$1044,0))=0,"n/a",(INDEX(Historical!$C$7:$C$1044,MATCH(B12,Historical!$B$7:$B$1044,0))/INDEX(Historical!$D$7:$D$1044,MATCH(B12,Historical!$B$7:$B$1044,0))-1)*100) -> 5.1282051 | T12: =IF(INDEX(Historical!$F$7:$F$1044,MATCH(B12,Historical!$B$7:$B$1044,0))=0,"n/a",((INDEX(Historical!$C$7:$C$1044,MATCH(B12,Historical!$B$7:$B$1044,0))/INDEX(Historical!$F$7:$F$1044,MATCH(B12,Historical!$B$7:$B$1044,0)))^(1/3)-1)*100) -> 6.439211 | U12: =IF(INDEX(Historical!$H$7:$H$1044,MATCH(B12,Historical!$B$7:$B$1044,0))=0,"n/a",((INDEX(Historical!$C$7:$C$1044,MATCH(B12,Historical!$B$7:$B$1044,0))/INDEX(Historical!$H$7:$H$1044,MATCH(B12,Historical!$B$7:$B$1044,0)))^(1/5)-1)*100) -> 6.446778 | V12: =IF(INDEX(Historical!$M$7:$M$1044,MATCH(B12,Historical!$B$7:$B$1044,0))=0,"n/a",((INDEX(Historical!$C$7:$C$1044,MATCH(B12,Historical!$B$7:$B$1044,0))/INDEX(Historical!$M$7:$M$1044,MATCH(B12,Historical!$B$7:$B$1044,0)))^(1/10)-1)*100) -> 7.1773463 | W12: =IF(OR(U12<=0,U12="n/a",V12<=0,V12="n/a"),"n/a",U12/V12) -> 0.89821192 | X12: =IF(OR(AJ12<=0,AJ12="n/a",U12<=0,U12="n/a"),"n/a",U12/AJ12) -> n/a | Z12: =IF(OR(AC12<0.01,AC12="n/a"),"n/a",M12/AC12*100) -> 80.769231 | AA12: =IF(OR(AC12<0.01,AC12="n/a"),"n/a",I12/AC12) -> 25.903846 | AB12: 12 | AC12: 1.04 | AD12: n/a | AE12: 2.06 | AF12: 1.18 | AG12: 5 | AH12: -7.37 | AI12: 6.12 | AJ12: -23.04 | AK12: n/a | AL12: 688.6 | AM12: 9.39 | AN12: 0.53 | AO12: =IF(U12="n/a","n/a",IF(AA12<0,"n/a",IF(AA12="n/a","n/a",J12+U12-AA12))) -> -16.339028 | AP12: =IF(U12="n/a","n/a",J12+U12) -> 9.5648181 | AQ12: =IF(OR(AC12<0.01,AC12="n/a",AF12="n/a"),"n/a",(I12/SQRT(22.5*AC12*(I12/AF12))-1)*100) -> 16.555258 | AR12: =INDEX(Historical!$C$7:$C$1045,MATCH(B12,Historical!$B$7:$B$1045,0))*IF(AH12="n/a",1.03,IF(AH12<0,1.01,IF(AH12>10,1.1,(1+AH12/100)))) -> 0.8282 | AS12: =IF($AI12="n/a",1.03*AR12,IF($AI12<0,1.01*AR12,IF($AI12>10,1.1*AR12,(1+$AI12/100)*AR12))) -> 0.87888584 | AT12: =IF($AK12="n/a",1.03*AS12,IF($AK12<0,1.01*AS12,IF($AK12>10,1.1*AS12,(1+$AK12/100)*AS12))) -> 0.90525242 | AU12: =IF($AK12="n/a",1.03*AT12,IF($AK12<0,1.01*AT12,IF($AK12>10,1.1*AT12,(1+$AK12/100)*AT12))) -> 0.93240999 | AV12: =IF($AK12="n/a",1.03*AU12,IF($AK12<0,1.01*AU12,IF($AK12>10,1.1*AU12,(1+$AK12/100)*AU12))) -> 0.96038229 | AW12: =SUM(AR12:AV12) -> 4.5051305 | AX12: =AW12/I12*100 -> 16.72283 | AY12: 0.65 | AZ12: 38.48 | BA12: 2.36 | BB12: 9.76 | BC12: 17.18 | BE12: 1999 | BF12: =IF(BE12>2020,0,IF(BE12>2008,1,IF(BE12>2001,2,IF(BE12>1990,3,IF(BE12>1980,4,IF(BE12>1973,5,IF(BE12>1970,6,IF(BE12>1960,7,IF(BE12>1958,8,IF(BE12>1953,9,10)))))))))) -> 3 | BG12: 0.51 | BH12: USD | BI12: Corp
A13: A. O. Smith Corporation | B13: AOS | C13: Industrials | D13: Building Products | E13: 32 | F13: 110 | G13: N | H13: N | I13: 61.84 | J13: =(M13/I13)*100 -> 2.3285899 | K13: 0.36 | L13: 4 | M13: =K13*L13 -> 1.44 | N13: B15 | O13: 0.34 | P13: 45961 | Q13: 45978 | R13: =(K13-O13)/O13*100 -> 5.8823529 | S13: =IF(INDEX(Historical!$D$7:$D1082,MATCH(B13,Historical!$B$7:$B$1044,0))=0,"n/a",(INDEX(Historical!$C$7:$C$1044,MATCH(B13,Historical!$B$7:$B$1044,0))/INDEX(Historical!$D$7:$D$1044,MATCH(B13,Historical!$B$7:$B$1044,0))-1)*100) -> 6.1538462 | T13: =IF(INDEX(Historical!$F$7:$F$1044,MATCH(B13,Historical!$B$7:$B$1044,0))=0,"n/a",((INDEX(Historical!$C$7:$C$1044,MATCH(B13,Historical!$B$7:$B$1044,0))/INDEX(Historical!$F$7:$F$1044,MATCH(B13,Historical!$B$7:$B$1044,0)))^(1/3)-1)*100) -> 6.5756717 | U13: =IF(INDEX(Historical!$H$7:$H$1044,MATCH(B13,Historical!$B$7:$B$1044,0))=0,"n/a",((INDEX(Historical!$C$7:$C$1044,MATCH(B13,Historical!$B$7:$B$1044,0))/INDEX(Historical!$H$7:$H$1044,MATCH(B13,Historical!$B$7:$B$1044,0)))^(1/5)-1)*100) -> 7.0854836 | V13: =IF(INDEX(Historical!$M$7:$M$1044,MATCH(B13,Historical!$B$7:$B$1044,0))=0,"n/a",((INDEX(Historical!$C$7:$C$1044,MATCH(B13,Historical!$B$7:$B$1044,0))/INDEX(Historical!$M$7:$M$1044,MATCH(B13,Historical!$B$7:$B$1044,0)))^(1/10)-1)*100) -> 13.76523 | W13: =IF(OR(U13<=0,U13="n/a",V13<=0,V13="n/a"),"n/a",U13/V13) -> 0.51473775 | X13: =IF(OR(AJ13<=0,AJ13="n/a",U13<=0,U13="n/a"),"n/a",U13/AJ13) -> 0.55967485 | Z13: =IF(OR(AC13<0.01,AC13="n/a"),"n/a",M13/AC13*100) -> 37.402597 | AA13: =IF(OR(AC13<0.01,AC13="n/a"),"n/a",I13/AC13) -> 16.062338 | AB13: 12 | AC13: 3.85 | AD13: 2.21 | AE13: 2.23 | AF13: 4.61 | AG13: 29.2 | AH13: 3.11 | AI13: 8.65 | AJ13: 12.66 | AK13: 6.5 | AL13: 8550 | AM13: 19.85 | AN13: 0.11 | AO13: =IF(U13="n/a","n/a",IF(AA13<0,"n/a",IF(AA13="n/a","n/a",J13+U13-AA13))) -> -6.6482642 | AP13: =IF(U13="n/a","n/a",J13+U13) -> 9.4140735 | AQ13: =IF(OR(AC13<0.01,AC13="n/a",AF13="n/a"),"n/a",(I13/SQRT(22.5*AC13*(I13/AF13))-1)*100) -> 81.410984 | AR13: =INDEX(Historical!$C$7:$C$1045,MATCH(B13,Historical!$B$7:$B$1045,0))*IF(AH13="n/a",1.03,IF(AH13<0,1.01,IF(AH13>10,1.1,(1+AH13/100)))) -> 1.422918 | AS13: =IF($AI13="n/a",1.03*AR13,IF($AI13<0,1.01*AR13,IF($AI13>10,1.1*AR13,(1+$AI13/100)*AR13))) -> 1.5460004 | AT13: =IF($AK13="n/a",1.03*AS13,IF($AK13<0,1.01*AS13,IF($AK13>10,1.1*AS13,(1+$AK13/100)*AS13))) -> 1.6464904 | AU13: =IF($AK13="n/a",1.03*AT13,IF($AK13<0,1.01*AT13,IF($AK13>10,1.1*AT13,(1+$AK13/100)*AT13))) -> 1.7535123 | AV13: =IF($AK13="n/a",1.03*AU13,IF($AK13<0,1.01*AU13,IF($AK13>10,1.1*AU13,(1+$AK13/100)*AU13))) -> 1.8674906 | AW13: =SUM(AR13:AV13) -> 8.2364118 | AX13: =AW13/I13*100 -> 13.318906 | AY13: 1.26 | AZ13: -0.48 | BA13: -24.46 | BB13: -8.99 | BC13: -11.44 | BE13: 1994 | BF13: =IF(BE13>2020,0,IF(BE13>2008,1,IF(BE13>2001,2,IF(BE13>1990,3,IF(BE13>1980,4,IF(BE13>1973,5,IF(BE13>1970,6,IF(BE13>1960,7,IF(BE13>1958,8,IF(BE13>1953,9,10)))))))))) -> 3 | BG13: 17.11 | BH13: USD | BI13: Corp
A14: Air Products and Chemicals, Inc. | B14: APD | C14: Materials | D14: Chemicals | E14: 44 | F14: 62 | G14: Y | H14: Y | I14: 300.05 | J14: =(M14/I14)*100 -> 2.4129312 | K14: 1.81 | L14: 4 | M14: =K14*L14 -> 7.24 | N14: B14 | O14: 1.79 | P14: 46113 | Q14: 46153 | R14: =(K14-O14)/O14*100 -> 1.1173184 | S14: =IF(INDEX(Historical!$D$7:$D1083,MATCH(B14,Historical!$B$7:$B$1044,0))=0,"n/a",(INDEX(Historical!$C$7:$C$1044,MATCH(B14,Historical!$B$7:$B$1044,0))/INDEX(Historical!$D$7:$D$1044,MATCH(B14,Historical!$B$7:$B$1044,0))-1)*100) -> 1.1331445 | T14: =IF(INDEX(Historical!$F$7:$F$1044,MATCH(B14,Historical!$B$7:$B$1044,0))=0,"n/a",((INDEX(Historical!$C$7:$C$1044,MATCH(B14,Historical!$B$7:$B$1044,0))/INDEX(Historical!$F$7:$F$1044,MATCH(B14,Historical!$B$7:$B$1044,0)))^(1/3)-1)*100) -> 3.9314609 | U14: =IF(INDEX(Historical!$H$7:$H$1044,MATCH(B14,Historical!$B$7:$B$1044,0))=0,"n/a",((INDEX(Historical!$C$7:$C$1044,MATCH(B14,Historical!$B$7:$B$1044,0))/INDEX(Historical!$H$7:$H$1044,MATCH(B14,Historical!$B$7:$B$1044,0)))^(1/5)-1)*100) -> 6.6285959 | V14: =IF(INDEX(Historical!$M$7:$M$1044,MATCH(B14,Historical!$B$7:$B$1044,0))=0,"n/a",((INDEX(Historical!$C$7:$C$1044,MATCH(B14,Historical!$B$7:$B$1044,0))/INDEX(Historical!$M$7:$M$1044,MATCH(B14,Historical!$B$7:$B$1044,0)))^(1/10)-1)*100) -> 8.3564638 | W14: =IF(OR(U14<=0,U14="n/a",V14<=0,V14="n/a"),"n/a",U14/V14) -> 0.79322978 | X14: =IF(OR(AJ14<=0,AJ14="n/a",U14<=0,U14="n/a"),"n/a",U14/AJ14) -> n/a | Z14: =IF(OR(AC14<0.01,AC14="n/a"),"n/a",M14/AC14*100) -> n/a | AA14: =IF(OR(AC14<0.01,AC14="n/a"),"n/a",I14/AC14) -> n/a | AB14: 9 | AC14: -1.5 | AD14: 2.46 | AE14: 5.47 | AF14: 4.33 | AG14: -2.03 | AH14: 9.24 | AI14: 7.89 | AJ14: n/a | AK14: 8.62 | AL14: 66810 | AM14: 0.42 | AN14: 1.18 | AO14: =IF(U14="n/a","n/a",IF(AA14<0,"n/a",IF(AA14="n/a","n/a",J14+U14-AA14))) -> n/a | AP14: =IF(U14="n/a","n/a",J14+U14) -> 9.0415271 | AQ14: =IF(OR(AC14<0.01,AC14="n/a",AF14="n/a"),"n/a",(I14/SQRT(22.5*AC14*(I14/AF14))-1)*100) -> n/a | AR14: =INDEX(Historical!$C$7:$C$1045,MATCH(B14,Historical!$B$7:$B$1045,0))*IF(AH14="n/a",1.03,IF(AH14<0,1.01,IF(AH14>10,1.1,(1+AH14/100)))) -> 7.799736 | AS14: =IF($AI14="n/a",1.03*AR14,IF($AI14<0,1.01*AR14,IF($AI14>10,1.1*AR14,(1+$AI14/100)*AR14))) -> 8.4151352 | AT14: =IF($AK14="n/a",1.03*AS14,IF($AK14<0,1.01*AS14,IF($AK14>10,1.1*AS14,(1+$AK14/100)*AS14))) -> 9.1405198 | AU14: =IF($AK14="n/a",1.03*AT14,IF($AK14<0,1.01*AT14,IF($AK14>10,1.1*AT14,(1+$AK14/100)*AT14))) -> 9.9284326 | AV14: =IF($AK14="n/a",1.03*AU14,IF($AK14<0,1.01*AU14,IF($AK14>10,1.1*AU14,(1+$AK14/100)*AU14))) -> 10.784264 | AW14: =SUM(AR14:AV14) -> 46.068087 | AX14: =AW14/I14*100 -> 15.35347 | AY14: 0.79 | AZ14: 30.96 | BA14: -2.36 | BB14: 4.02 | BC14: 9.3 | BE14: 1983 | BF14: =IF(BE14>2020,0,IF(BE14>2008,1,IF(BE14>2001,2,IF(BE14>1990,3,IF(BE14>1980,4,IF(BE14>1973,5,IF(BE14>1970,6,IF(BE14>1960,7,IF(BE14>1958,8,IF(BE14>1953,9,10)))))))))) -> 4 | BG14: -0.8 | BH14: USD | BI14: Corp
A15: Arrow Financial Corporation | B15: AROW | C15: Financials | D15: Banks | E15: 33 | F15: 99 | G15: N | H15: N | I15: 36.85 | J15: =(M15/I15)*100 -> 3.256445 | K15: 0.3 | L15: 4 | M15: =K15*L15 -> 1.2 | N15: C15 | O15: 0.29 | P15: 46064 | Q15: 46078 | R15: =(K15-O15)/O15*100 -> 3.4482759 | S15: =IF(INDEX(Historical!$D$7:$D1088,MATCH(B15,Historical!$B$7:$B$1044,0))=0,"n/a",(INDEX(Historical!$C$7:$C$1044,MATCH(B15,Historical!$B$7:$B$1044,0))/INDEX(Historical!$D$7:$D$1044,MATCH(B15,Historical!$B$7:$B$1044,0))-1)*100) -> 4.587156 | T15: =IF(INDEX(Historical!$F$7:$F$1044,MATCH(B15,Historical!$B$7:$B$1044,0))=0,"n/a",((INDEX(Historical!$C$7:$C$1044,MATCH(B15,Historical!$B$7:$B$1044,0))/INDEX(Historical!$F$7:$F$1044,MATCH(B15,Historical!$B$7:$B$1044,0)))^(1/3)-1)*100) -> 3.5868344 | U15: =IF(INDEX(Historical!$H$7:$H$1044,MATCH(B15,Historical!$B$7:$B$1044,0))=0,"n/a",((INDEX(Historical!$C$7:$C$1044,MATCH(B15,Historical!$B$7:$B$1044,0))/INDEX(Historical!$H$7:$H$1044,MATCH(B15,Historical!$B$7:$B$1044,0)))^(1/5)-1)*100) -> 4.1346043 | V15: =IF(INDEX(Historical!$M$7:$M$1044,MATCH(B15,Historical!$B$7:$B$1044,0))=0,"n/a",((INDEX(Historical!$C$7:$C$1044,MATCH(B15,Historical!$B$7:$B$1044,0))/INDEX(Historical!$M$7:$M$1044,MATCH(B15,Historical!$B$7:$B$1044,0)))^(1/10)-1)*100) -> 3.8971599 | W15: =IF(OR(U15<=0,U15="n/a",V15<=0,V15="n/a"),"n/a",U15/V15) -> 1.0609276 | X15: =IF(OR(AJ15<=0,AJ15="n/a",U15<=0,U15="n/a"),"n/a",U15/AJ15) -> 2.1534398 | Y15: Adj Stock dividend | Z15: =IF(OR(AC15<0.01,AC15="n/a"),"n/a",M15/AC15*100) -> 45.112782 | AA15: =IF(OR(AC15<0.01,AC15="n/a"),"n/a",I15/AC15) -> 13.853383 | AB15: 12 | AC15: 2.66 | AD15: n/a | AE15: 2.51 | AF15: 1.4 | AG15: 10.55 | AH15: 37.74 | AI15: 18.63 | AJ15: 1.92 | AK15: n/a | AL15: 608.45 | AM15: 2.95 | AN15: 0.08 | AO15: =IF(U15="n/a","n/a",IF(AA15<0,"n/a",IF(AA15="n/a","n/a",J15+U15-AA15))) -> -6.4623341 | AP15: =IF(U15="n/a","n/a",J15+U15) -> 7.3910494 | AQ15: =IF(OR(AC15<0.01,AC15="n/a",AF15="n/a"),"n/a",(I15/SQRT(22.5*AC15*(I15/AF15))-1)*100) -> -7.1566748 | AR15: =INDEX(Historical!$C$7:$C$1045,MATCH(B15,Historical!$B$7:$B$1045,0))*IF(AH15="n/a",1.03,IF(AH15<0,1.01,IF(AH15>10,1.1,(1+AH15/100)))) -> 1.254 | AS15: =IF($AI15="n/a",1.03*AR15,IF($AI15<0,1.01*AR15,IF($AI15>10,1.1*AR15,(1+$AI15/100)*AR15))) -> 1.3794 | AT15: =IF($AK15="n/a",1.03*AS15,IF($AK15<0,1.01*AS15,IF($AK15>10,1.1*AS15,(1+$AK15/100)*AS15))) -> 1.420782 | AU15: =IF($AK15="n/a",1.03*AT15,IF($AK15<0,1.01*AT15,IF($AK15>10,1.1*AT15,(1+$AK15/100)*AT15))) -> 1.4634055 | AV15: =IF($AK15="n/a",1.03*AU15,IF($AK15<0,1.01*AU15,IF($AK15>10,1.1*AU15,(1+$AK15/100)*AU15))) -> 1.5073076 | AW15: =SUM(AR15:AV15) -> 7.0248951 | AX15: =AW15/I15*100 -> 19.063487 | AY15: 0.76 | AZ15: 57.75 | BA15: -3.26 | BB15: 7.02 | BC15: 18.61 | BE15: 1994 | BF15: =IF(BE15>2020,0,IF(BE15>2008,1,IF(BE15>2001,2,IF(BE15>1990,3,IF(BE15>1980,4,IF(BE15>1973,5,IF(BE15>1970,6,IF(BE15>1960,7,IF(BE15>1958,8,IF(BE15>1953,9,10)))))))))) -> 3 | BG15: 1 | BH15: USD | BI15: Corp
A16: Artesian Resources Corporation | B16: ARTNA | C16: Utilities | D16: Water Utilities | E16: 33 | F16: 95 | G16: N | H16: N | I16: 31.31 | J16: =(M16/I16)*100 -> 4.0063877 | K16: 0.3136 | L16: 4 | M16: =K16*L16 -> 1.2544 | N16: B22 | O16: 0.3074 | P16: 45975 | Q16: 45985 | R16: =(K16-O16)/O16*100 -> 2.0169161 | S16: =IF(INDEX(Historical!$D$7:$D1089,MATCH(B16,Historical!$B$7:$B$1044,0))=0,"n/a",(INDEX(Historical!$C$7:$C$1044,MATCH(B16,Historical!$B$7:$B$1044,0))/INDEX(Historical!$D$7:$D$1044,MATCH(B16,Historical!$B$7:$B$1044,0))-1)*100) -> 4.0351916 | T16: =IF(INDEX(Historical!$F$7:$F$1044,MATCH(B16,Historical!$B$7:$B$1044,0))=0,"n/a",((INDEX(Historical!$C$7:$C$1044,MATCH(B16,Historical!$B$7:$B$1044,0))/INDEX(Historical!$F$7:$F$1044,MATCH(B16,Historical!$B$7:$B$1044,0)))^(1/3)-1)*100) -> 4.0503933 | U16: =IF(INDEX(Historical!$H$7:$H$1044,MATCH(B16,Historical!$B$7:$B$1044,0))=0,"n/a",((INDEX(Historical!$C$7:$C$1044,MATCH(B16,Historical!$B$7:$B$1044,0))/INDEX(Historical!$H$7:$H$1044,MATCH(B16,Historical!$B$7:$B$1044,0)))^(1/5)-1)*100) -> 4.101248 | V16: =IF(INDEX(Historical!$M$7:$M$1044,MATCH(B16,Historical!$B$7:$B$1044,0))=0,"n/a",((INDEX(Historical!$C$7:$C$1044,MATCH(B16,Historical!$B$7:$B$1044,0))/INDEX(Historical!$M$7:$M$1044,MATCH(B16,Historical!$B$7:$B$1044,0)))^(1/10)-1)*100) -> 3.4837305 | W16: =IF(OR(U16<=0,U16="n/a",V16<=0,V16="n/a"),"n/a",U16/V16) -> 1.1772576 | X16: =IF(OR(AJ16<=0,AJ16="n/a",U16<=0,U16="n/a"),"n/a",U16/AJ16) -> 0.95823552 | Z16: =IF(OR(AC16<0.01,AC16="n/a"),"n/a",M16/AC16*100) -> 56.760181 | AA16: =IF(OR(AC16<0.01,AC16="n/a"),"n/a",I16/AC16) -> 14.167421 | AB16: 12 | AC16: 2.21 | AD16: n/a | AE16: 2.88 | AF16: 1.29 | AG16: 9.33 | AH16: n/a | AI16: n/a | AJ16: 4.28 | AK16: n/a | AL16: 324.91 | AM16: 12 | AN16: 0.73 | AO16: =IF(U16="n/a","n/a",IF(AA16<0,"n/a",IF(AA16="n/a","n/a",J16+U16-AA16))) -> -6.0597851 | AP16: =IF(U16="n/a","n/a",J16+U16) -> 8.1076358 | AQ16: =IF(OR(AC16<0.01,AC16="n/a",AF16="n/a"),"n/a",(I16/SQRT(22.5*AC16*(I16/AF16))-1)*100) -> -9.874229 | AR16: =INDEX(Historical!$C$7:$C$1045,MATCH(B16,Historical!$B$7:$B$1045,0))*IF(AH16="n/a",1.03,IF(AH16<0,1.01,IF(AH16>10,1.1,(1+AH16/100)))) -> 1.266694 | AS16: =IF($AI16="n/a",1.03*AR16,IF($AI16<0,1.01*AR16,IF($AI16>10,1.1*AR16,(1+$AI16/100)*AR16))) -> 1.3046948 | AT16: =IF($AK16="n/a",1.03*AS16,IF($AK16<0,1.01*AS16,IF($AK16>10,1.1*AS16,(1+$AK16/100)*AS16))) -> 1.3438357 | AU16: =IF($AK16="n/a",1.03*AT16,IF($AK16<0,1.01*AT16,IF($AK16>10,1.1*AT16,(1+$AK16/100)*AT16))) -> 1.3841507 | AV16: =IF($AK16="n/a",1.03*AU16,IF($AK16<0,1.01*AU16,IF($AK16>10,1.1*AU16,(1+$AK16/100)*AU16))) -> 1.4256753 | AW16: =SUM(AR16:AV16) -> 6.7250505 | AX16: =AW16/I16*100 -> 21.478922 | AY16: 0.33 | AZ16: 2.66 | BA16: -13.48 | BB16: -3.67 | BC16: -3.98 | BE16: 1993 | BF16: =IF(BE16>2020,0,IF(BE16>2008,1,IF(BE16>2001,2,IF(BE16>1990,3,IF(BE16>1980,4,IF(BE16>1973,5,IF(BE16>1970,6,IF(BE16>1960,7,IF(BE16>1958,8,IF(BE16>1953,9,10)))))))))) -> 3 | BG16: 2.74 | BH16: USD | BI16: Corp
A17: Atmos Energy Corporation | B17: ATO | C17: Utilities | D17: Gas Utilities | E17: 42 | F17: 66 | G17: N | H17: N | I17: 189.98 | J17: =(M17/I17)*100 -> 2.1054848 | K17: 1 | L17: 4 | M17: =K17*L17 -> 4 | N17: C11 | O17: 0.87 | P17: 45985 | Q17: 45999 | R17: =(K17-O17)/O17*100 -> 14.942529 | S17: =IF(INDEX(Historical!$D$7:$D1092,MATCH(B17,Historical!$B$7:$B$1044,0))=0,"n/a",(INDEX(Historical!$C$7:$C$1044,MATCH(B17,Historical!$B$7:$B$1044,0))/INDEX(Historical!$D$7:$D$1044,MATCH(B17,Historical!$B$7:$B$1044,0))-1)*100) -> 9.8934551 | T17: =IF(INDEX(Historical!$F$7:$F$1044,MATCH(B17,Historical!$B$7:$B$1044,0))=0,"n/a",((INDEX(Historical!$C$7:$C$1044,MATCH(B17,Historical!$B$7:$B$1044,0))/INDEX(Historical!$F$7:$F$1044,MATCH(B17,Historical!$B$7:$B$1044,0)))^(1/3)-1)*100) -> 9.0990081 | U17: =IF(INDEX(Historical!$H$7:$H$1044,MATCH(B17,Historical!$B$7:$B$1044,0))=0,"n/a",((INDEX(Historical!$C$7:$C$1044,MATCH(B17,Historical!$B$7:$B$1044,0))/INDEX(Historical!$H$7:$H$1044,MATCH(B17,Historical!$B$7:$B$1044,0)))^(1/5)-1)*100) -> 8.9652119 | V17: =IF(INDEX(Historical!$M$7:$M$1044,MATCH(B17,Historical!$B$7:$B$1044,0))=0,"n/a",((INDEX(Historical!$C$7:$C$1044,MATCH(B17,Historical!$B$7:$B$1044,0))/INDEX(Historical!$M$7:$M$1044,MATCH(B17,Historical!$B$7:$B$1044,0)))^(1/10)-1)*100) -> 8.5452961 | W17: =IF(OR(U17<=0,U17="n/a",V17<=0,V17="n/a"),"n/a",U17/V17) -> 1.04914 | X17: =IF(OR(AJ17<=0,AJ17="n/a",U17<=0,U17="n/a"),"n/a",U17/AJ17) -> 1.0164639 | Z17: =IF(OR(AC17<0.01,AC17="n/a"),"n/a",M17/AC17*100) -> 52.083333 | AA17: =IF(OR(AC17<0.01,AC17="n/a"),"n/a",I17/AC17) -> 24.736979 | AB17: 9 | AC17: 7.68 | AD17: 2.44 | AE17: 6.45 | AF17: 2.2 | AG17: 9.23 | AH17: 11.43 | AI17: 6.78 | AJ17: 8.82 | AK17: 8.77 | AL17: 31430 | AM17: 0.45 | AN17: 0.67 | AO17: =IF(U17="n/a","n/a",IF(AA17<0,"n/a",IF(AA17="n/a","n/a",J17+U17-AA17))) -> -13.666282 | AP17: =IF(U17="n/a","n/a",J17+U17) -> 11.070697 | AQ17: =IF(OR(AC17<0.01,AC17="n/a",AF17="n/a"),"n/a",(I17/SQRT(22.5*AC17*(I17/AF17))-1)*100) -> 55.522566 | AR17: =INDEX(Historical!$C$7:$C$1045,MATCH(B17,Historical!$B$7:$B$1045,0))*IF(AH17="n/a",1.03,IF(AH17<0,1.01,IF(AH17>10,1.1,(1+AH17/100)))) -> 3.971 | AS17: =IF($AI17="n/a",1.03*AR17,IF($AI17<0,1.01*AR17,IF($AI17>10,1.1*AR17,(1+$AI17/100)*AR17))) -> 4.2402338 | AT17: =IF($AK17="n/a",1.03*AS17,IF($AK17<0,1.01*AS17,IF($AK17>10,1.1*AS17,(1+$AK17/100)*AS17))) -> 4.6121023 | AU17: =IF($AK17="n/a",1.03*AT17,IF($AK17<0,1.01*AT17,IF($AK17>10,1.1*AT17,(1+$AK17/100)*AT17))) -> 5.0165837 | AV17: =IF($AK17="n/a",1.03*AU17,IF($AK17<0,1.01*AU17,IF($AK17>10,1.1*AU17,(1+$AK17/100)*AU17))) -> 5.4565381 | AW17: =SUM(AR17:AV17) -> 23.296458 | AX17: =AW17/I17*100 -> 12.262584 | AY17: 0.64 | AZ17: 26.67 | BA17: -1.31 | BB17: 2.43 | BC17: 9.88 | BE17: 1985 | BF17: =IF(BE17>2020,0,IF(BE17>2008,1,IF(BE17>2001,2,IF(BE17>1990,3,IF(BE17>1980,4,IF(BE17>1973,5,IF(BE17>1970,6,IF(BE17>1960,7,IF(BE17>1958,8,IF(BE17>1953,9,10)))))))))) -> 4 | BG17: 4.44 | BH17: USD | BI17: Corp
A18: AptarGroup, Inc. | B18: ATR | C18: Materials | D18: Containers & Packaging | E18: 32 | F18: 109 | G18: - | H18: - | I18: 123.68 | J18: =(M18/I18)*100 -> 1.5523933 | K18: 0.48 | L18: 4 | M18: =K18*L18 -> 1.92 | N18: B23 | O18: 0.45 | P18: 45953 | Q18: 45974 | R18: =(K18-O18)/O18*100 -> 6.6666667 | S18: =IF(INDEX(Historical!$D$7:$D1093,MATCH(B18,Historical!$B$7:$B$1044,0))=0,"n/a",(INDEX(Historical!$C$7:$C$1044,MATCH(B18,Historical!$B$7:$B$1044,0))/INDEX(Historical!$D$7:$D$1044,MATCH(B18,Historical!$B$7:$B$1044,0))-1)*100) -> 6.3953488 | T18: =IF(INDEX(Historical!$F$7:$F$1044,MATCH(B18,Historical!$B$7:$B$1044,0))=0,"n/a",((INDEX(Historical!$C$7:$C$1044,MATCH(B18,Historical!$B$7:$B$1044,0))/INDEX(Historical!$F$7:$F$1044,MATCH(B18,Historical!$B$7:$B$1044,0)))^(1/3)-1)*100) -> 6.382249 | U18: =IF(INDEX(Historical!$H$7:$H$1044,MATCH(B18,Historical!$B$7:$B$1044,0))=0,"n/a",((INDEX(Historical!$C$7:$C$1044,MATCH(B18,Historical!$B$7:$B$1044,0))/INDEX(Historical!$H$7:$H$1044,MATCH(B18,Historical!$B$7:$B$1044,0)))^(1/5)-1)*100) -> 4.9102011 | V18: =IF(INDEX(Historical!$M$7:$M$1044,MATCH(B18,Historical!$B$7:$B$1044,0))=0,"n/a",((INDEX(Historical!$C$7:$C$1044,MATCH(B18,Historical!$B$7:$B$1044,0))/INDEX(Historical!$M$7:$M$1044,MATCH(B18,Historical!$B$7:$B$1044,0)))^(1/10)-1)*100) -> 4.8466657 | W18: =IF(OR(U18<=0,U18="n/a",V18<=0,V18="n/a"),"n/a",U18/V18) -> 1.0131091 | X18: =IF(OR(AJ18<=0,AJ18="n/a",U18<=0,U18="n/a"),"n/a",U18/AJ18) -> 0.38152301 | Z18: =IF(OR(AC18<0.01,AC18="n/a"),"n/a",M18/AC18*100) -> 32.653061 | AA18: =IF(OR(AC18<0.01,AC18="n/a"),"n/a",I18/AC18) -> 21.034014 | AB18: 12 | AC18: 5.88 | AD18: 2.4 | AE18: 2.09 | AF18: 2.98 | AG18: 15.28 | AH18: -2.99 | AI18: 16.06 | AJ18: 12.87 | AK18: 7.97 | AL18: 7890 | AM18: 0.72 | AN18: 0.58 | AO18: =IF(U18="n/a","n/a",IF(AA18<0,"n/a",IF(AA18="n/a","n/a",J18+U18-AA18))) -> -14.571419 | AP18: =IF(U18="n/a","n/a",J18+U18) -> 6.4625944 | AQ18: =IF(OR(AC18<0.01,AC18="n/a",AF18="n/a"),"n/a",(I18/SQRT(22.5*AC18*(I18/AF18))-1)*100) -> 66.908306 | AR18: =INDEX(Historical!$C$7:$C$1045,MATCH(B18,Historical!$B$7:$B$1045,0))*IF(AH18="n/a",1.03,IF(AH18<0,1.01,IF(AH18>10,1.1,(1+AH18/100)))) -> 1.8483 | AS18: =IF($AI18="n/a",1.03*AR18,IF($AI18<0,1.01*AR18,IF($AI18>10,1.1*AR18,(1+$AI18/100)*AR18))) -> 2.03313 | AT18: =IF($AK18="n/a",1.03*AS18,IF($AK18<0,1.01*AS18,IF($AK18>10,1.1*AS18,(1+$AK18/100)*AS18))) -> 2.1951705 | AU18: =IF($AK18="n/a",1.03*AT18,IF($AK18<0,1.01*AT18,IF($AK18>10,1.1*AT18,(1+$AK18/100)*AT18))) -> 2.3701255 | AV18: =IF($AK18="n/a",1.03*AU18,IF($AK18<0,1.01*AU18,IF($AK18>10,1.1*AU18,(1+$AK18/100)*AU18))) -> 2.5590246 | AW18: =SUM(AR18:AV18) -> 11.005751 | AX18: =AW18/I18*100 -> 8.8985693 | AY18: 0.43 | AZ18: 19.81 | BA18: -24.71 | BB18: -5.23 | BC18: -5.59 | BE18: 1994 | BF18: =IF(BE18>2020,0,IF(BE18>2008,1,IF(BE18>2001,2,IF(BE18>1990,3,IF(BE18>1980,4,IF(BE18>1973,5,IF(BE18>1970,6,IF(BE18>1960,7,IF(BE18>1958,8,IF(BE18>1953,9,10)))))))))) -> 3 | BG18: 8.11 | BH18: USD | BI18: Corp
A19: American States Water Company | B19: AWR | C19: Utilities | D19: Water Utilities | E19: 71 | F19: 1 | G19: N | H19: N | I19: 75.29 | J19: =(M19/I19)*100 -> 2.6776464 | K19: 0.504 | L19: 4 | M19: =K19*L19 -> 2.016 | N19: C01 | O19: 0.4655 | P19: 45884 | Q19: 45903 | R19: =(K19-O19)/O19*100 -> 8.2706767 | S19: =IF(INDEX(Historical!$D$7:$D1102,MATCH(B19,Historical!$B$7:$B$1044,0))=0,"n/a",(INDEX(Historical!$C$7:$C$1044,MATCH(B19,Historical!$B$7:$B$1044,0))/INDEX(Historical!$D$7:$D$1044,MATCH(B19,Historical!$B$7:$B$1044,0))-1)*100) -> 8.2635399 | T19: =IF(INDEX(Historical!$F$7:$F$1044,MATCH(B19,Historical!$B$7:$B$1044,0))=0,"n/a",((INDEX(Historical!$C$7:$C$1044,MATCH(B19,Historical!$B$7:$B$1044,0))/INDEX(Historical!$F$7:$F$1044,MATCH(B19,Historical!$B$7:$B$1044,0)))^(1/3)-1)*100) -> 8.3351332 | U19: =IF(INDEX(Historical!$H$7:$H$1044,MATCH(B19,Historical!$B$7:$B$1044,0))=0,"n/a",((INDEX(Historical!$C$7:$C$1044,MATCH(B19,Historical!$B$7:$B$1044,0))/INDEX(Historical!$H$7:$H$1044,MATCH(B19,Historical!$B$7:$B$1044,0)))^(1/5)-1)*100) -> 8.6609676 | V19: =IF(INDEX(Historical!$M$7:$M$1044,MATCH(B19,Historical!$B$7:$B$1044,0))=0,"n/a",((INDEX(Historical!$C$7:$C$1044,MATCH(B19,Historical!$B$7:$B$1044,0))/INDEX(Historical!$M$7:$M$1044,MATCH(B19,Historical!$B$7:$B$1044,0)))^(1/10)-1)*100) -> 8.2945591 | W19: =IF(OR(U19<=0,U19="n/a",V19<=0,V19="n/a"),"n/a",U19/V19) -> 1.0441746 | X19: =IF(OR(AJ19<=0,AJ19="n/a",U19<=0,U19="n/a"),"n/a",U19/AJ19) -> 1.1366099 | Z19: =IF(OR(AC19<0.01,AC19="n/a"),"n/a",M19/AC19*100) -> 59.821958 | AA19: =IF(OR(AC19<0.01,AC19="n/a"),"n/a",I19/AC19) -> 22.341246 | AB19: 12 | AC19: 3.37 | AD19: 2.62 | AE19: 4.48 | AF19: 2.81 | AG19: 13.22 | AH19: 10.09 | AI19: 2.83 | AJ19: 7.62 | AK19: 7.53 | AL19: 2950 | AM19: 0.97 | AN19: 0.9 | AO19: =IF(U19="n/a","n/a",IF(AA19<0,"n/a",IF(AA19="n/a","n/a",J19+U19-AA19))) -> -11.002632 | AP19: =IF(U19="n/a","n/a",J19+U19) -> 11.338614 | AQ19: =IF(OR(AC19<0.01,AC19="n/a",AF19="n/a"),"n/a",(I19/SQRT(22.5*AC19*(I19/AF19))-1)*100) -> 67.038122 | AR19: =INDEX(Historical!$C$7:$C$1045,MATCH(B19,Historical!$B$7:$B$1045,0))*IF(AH19="n/a",1.03,IF(AH19<0,1.01,IF(AH19>10,1.1,(1+AH19/100)))) -> 2.1329 | AS19: =IF($AI19="n/a",1.03*AR19,IF($AI19<0,1.01*AR19,IF($AI19>10,1.1*AR19,(1+$AI19/100)*AR19))) -> 2.1932611 | AT19: =IF($AK19="n/a",1.03*AS19,IF($AK19<0,1.01*AS19,IF($AK19>10,1.1*AS19,(1+$AK19/100)*AS19))) -> 2.3584136 | AU19: =IF($AK19="n/a",1.03*AT19,IF($AK19<0,1.01*AT19,IF($AK19>10,1.1*AT19,(1+$AK19/100)*AT19))) -> 2.5360022 | AV19: =IF($AK19="n/a",1.03*AU19,IF($AK19<0,1.01*AU19,IF($AK19>10,1.1*AU19,(1+$AK19/100)*AU19))) -> 2.7269631 | AW19: =SUM(AR19:AV19) -> 11.94754 | AX19: =AW19/I19*100 -> 15.868694 | AY19: 0.63 | AZ19: 8.41 | BA19: -9.22 | BB19: -0.57 | BC19: 1.52 | BE19: 1955 | BF19: =IF(BE19>2020,0,IF(BE19>2008,1,IF(BE19>2001,2,IF(BE19>1990,3,IF(BE19>1980,4,IF(BE19>1973,5,IF(BE19>1970,6,IF(BE19>1960,7,IF(BE19>1958,8,IF(BE19>1953,9,10)))))))))) -> 9 | BG19: 4.98 | BH19: USD | BI19: Corp
A20: BancFirst Corporation | B20: BANF | C20: Financials | D20: Banks | E20: 32 | F20: 108 | G20: - | H20: - | I20: 111.61 | J20: =(M20/I20)*100 -> 1.756115 | K20: 0.49 | L20: 4 | M20: =K20*L20 -> 1.96 | N20: A13 | O20: 0.46 | P20: 45930 | Q20: 45945 | R20: =(K20-O20)/O20*100 -> 6.5217391 | S20: =IF(INDEX(Historical!$D$7:$D1105,MATCH(B20,Historical!$B$7:$B$1044,0))=0,"n/a",(INDEX(Historical!$C$7:$C$1044,MATCH(B20,Historical!$B$7:$B$1044,0))/INDEX(Historical!$D$7:$D$1044,MATCH(B20,Historical!$B$7:$B$1044,0))-1)*100) -> 6.8571429 | T20: =IF(INDEX(Historical!$F$7:$F$1044,MATCH(B20,Historical!$B$7:$B$1044,0))=0,"n/a",((INDEX(Historical!$C$7:$C$1044,MATCH(B20,Historical!$B$7:$B$1044,0))/INDEX(Historical!$F$7:$F$1044,MATCH(B20,Historical!$B$7:$B$1044,0)))^(1/3)-1)*100) -> 8.1085304 | U20: =IF(INDEX(Historical!$H$7:$H$1044,MATCH(B20,Historical!$B$7:$B$1044,0))=0,"n/a",((INDEX(Historical!$C$7:$C$1044,MATCH(B20,Historical!$B$7:$B$1044,0))/INDEX(Historical!$H$7:$H$1044,MATCH(B20,Historical!$B$7:$B$1044,0)))^(1/5)-1)*100) -> 7.5423818 | V20: =IF(INDEX(Historical!$M$7:$M$1044,MATCH(B20,Historical!$B$7:$B$1044,0))=0,"n/a",((INDEX(Historical!$C$7:$C$1044,MATCH(B20,Historical!$B$7:$B$1044,0))/INDEX(Historical!$M$7:$M$1044,MATCH(B20,Historical!$B$7:$B$1044,0)))^(1/10)-1)*100) -> 10.483965 | W20: =IF(OR(U20<=0,U20="n/a",V20<=0,V20="n/a"),"n/a",U20/V20) -> 0.71942074 | X20: =IF(OR(AJ20<=0,AJ20="n/a",U20<=0,U20="n/a"),"n/a",U20/AJ20) -> 0.40012636 | Z20: =IF(OR(AC20<0.01,AC20="n/a"),"n/a",M20/AC20*100) -> 26.849315 | AA20: =IF(OR(AC20<0.01,AC20="n/a"),"n/a",I20/AC20) -> 15.289041 | AB20: 12 | AC20: 7.3 | AD20: n/a | AE20: 4.23 | AF20: 1.97 | AG20: 13.85 | AH20: 2.86 | AI20: 0.05 | AJ20: 18.85 | AK20: n/a | AL20: 3750 | AM20: 37.13 | AN20: 0.07 | AO20: =IF(U20="n/a","n/a",IF(AA20<0,"n/a",IF(AA20="n/a","n/a",J20+U20-AA20))) -> -5.9905442 | AP20: =IF(U20="n/a","n/a",J20+U20) -> 9.2984969 | AQ20: =IF(OR(AC20<0.01,AC20="n/a",AF20="n/a"),"n/a",(I20/SQRT(22.5*AC20*(I20/AF20))-1)*100) -> 15.699632 | AR20: =INDEX(Historical!$C$7:$C$1045,MATCH(B20,Historical!$B$7:$B$1045,0))*IF(AH20="n/a",1.03,IF(AH20<0,1.01,IF(AH20>10,1.1,(1+AH20/100)))) -> 1.923482 | AS20: =IF($AI20="n/a",1.03*AR20,IF($AI20<0,1.01*AR20,IF($AI20>10,1.1*AR20,(1+$AI20/100)*AR20))) -> 1.9244437 | AT20: =IF($AK20="n/a",1.03*AS20,IF($AK20<0,1.01*AS20,IF($AK20>10,1.1*AS20,(1+$AK20/100)*AS20))) -> 1.9821771 | AU20: =IF($AK20="n/a",1.03*AT20,IF($AK20<0,1.01*AT20,IF($AK20>10,1.1*AT20,(1+$AK20/100)*AT20))) -> 2.0416424 | AV20: =IF($AK20="n/a",1.03*AU20,IF($AK20<0,1.01*AU20,IF($AK20>10,1.1*AU20,(1+$AK20/100)*AU20))) -> 2.1028916 | AW20: =SUM(AR20:AV20) -> 9.9746368 | AX20: =AW20/I20*100 -> 8.9370458 | AY20: 0.62 | AZ20: 9.98 | BA20: -19.57 | BB20: 0.65 | BC20: -4.47 | BE20: 1994 | BF20: =IF(BE20>2020,0,IF(BE20>2008,1,IF(BE20>2001,2,IF(BE20>1990,3,IF(BE20>1980,4,IF(BE20>1973,5,IF(BE20>1970,6,IF(BE20>1960,7,IF(BE20>1958,8,IF(BE20>1953,9,10)))))))))) -> 3 | BG20: 1.7 | BH20: USD | BI20: Corp
A21: Becton, Dickinson and Company | B21: BDX | C21: Health Care | D21: Health Care Equipment & Supplies | E21: 54 | F21: 36 | G21: N | H21: N | I21: 149.04 | J21: =(M21/I21)*100 -> 2.8180354 | K21: 1.05 | L21: 4 | M21: =K21*L21 -> 4.2 | N21: C29 | O21: 1.04 | P21: 45999 | Q21: 46022 | R21: =(K21-O21)/O21*100 -> 0.96153846 | S21: =IF(INDEX(Historical!$D$7:$D1111,MATCH(B21,Historical!$B$7:$B$1044,0))=0,"n/a",(INDEX(Historical!$C$7:$C$1044,MATCH(B21,Historical!$B$7:$B$1044,0))/INDEX(Historical!$D$7:$D$1044,MATCH(B21,Historical!$B$7:$B$1044,0))-1)*100) -> 7.1979434 | T21: =IF(INDEX(Historical!$F$7:$F$1044,MATCH(B21,Historical!$B$7:$B$1044,0))=0,"n/a",((INDEX(Historical!$C$7:$C$1044,MATCH(B21,Historical!$B$7:$B$1044,0))/INDEX(Historical!$F$7:$F$1044,MATCH(B21,Historical!$B$7:$B$1044,0)))^(1/3)-1)*100) -> 5.8110759 | U21: =IF(INDEX(Historical!$H$7:$H$1044,MATCH(B21,Historical!$B$7:$B$1044,0))=0,"n/a",((INDEX(Historical!$C$7:$C$1044,MATCH(B21,Historical!$B$7:$B$1044,0))/INDEX(Historical!$H$7:$H$1044,MATCH(B21,Historical!$B$7:$B$1044,0)))^(1/5)-1)*100) -> 5.4380136 | V21: =IF(INDEX(Historical!$M$7:$M$1044,MATCH(B21,Historical!$B$7:$B$1044,0))=0,"n/a",((INDEX(Historical!$C$7:$C$1044,MATCH(B21,Historical!$B$7:$B$1044,0))/INDEX(Historical!$M$7:$M$1044,MATCH(B21,Historical!$B$7:$B$1044,0)))^(1/10)-1)*100) -> 5.4192919 | W21: =IF(OR(U21<=0,U21="n/a",V21<=0,V21="n/a"),"n/a",U21/V21) -> 1.0034546 | X21: =IF(OR(AJ21<=0,AJ21="n/a",U21<=0,U21="n/a"),"n/a",U21/AJ21) -> 0.33057833 | Y21: FY Streak | Z21: =IF(OR(AC21<0.01,AC21="n/a"),"n/a",M21/AC21*100) -> 68.627451 | AA21: =IF(OR(AC21<0.01,AC21="n/a"),"n/a",I21/AC21) -> 24.352941 | AB21: 9 | AC21: 6.12 | AD21: 1.37 | AE21: 1.94 | AF21: 1.68 | AG21: 6.96 | AH21: 10.36 | AI21: 7.68 | AJ21: 16.45 | AK21: 8.07 | AL21: 42440 | AM21: 0.19 | AN21: 0.77 | AO21: =IF(U21="n/a","n/a",IF(AA21<0,"n/a",IF(AA21="n/a","n/a",J21+U21-AA21))) -> -16.096892 | AP21: =IF(U21="n/a","n/a",J21+U21) -> 8.256049 | AQ21: =IF(OR(AC21<0.01,AC21="n/a",AF21="n/a"),"n/a",(I21/SQRT(22.5*AC21*(I21/AF21))-1)*100) -> 34.846318 | AR21: =INDEX(Historical!$C$7:$C$1045,MATCH(B21,Historical!$B$7:$B$1045,0))*IF(AH21="n/a",1.03,IF(AH21<0,1.01,IF(AH21>10,1.1,(1+AH21/100)))) -> 4.587 | AS21: =IF($AI21="n/a",1.03*AR21,IF($AI21<0,1.01*AR21,IF($AI21>10,1.1*AR21,(1+$AI21/100)*AR21))) -> 4.9392816 | AT21: =IF($AK21="n/a",1.03*AS21,IF($AK21<0,1.01*AS21,IF($AK21>10,1.1*AS21,(1+$AK21/100)*AS21))) -> 5.3378816 | AU21: =IF($AK21="n/a",1.03*AT21,IF($AK21<0,1.01*AT21,IF($AK21>10,1.1*AT21,(1+$AK21/100)*AT21))) -> 5.7686487 | AV21: =IF($AK21="n/a",1.03*AU21,IF($AK21<0,1.01*AU21,IF($AK21>10,1.1*AU21,(1+$AK21/100)*AU21))) -> 6.2341786 | AW21: =SUM(AR21:AV21) -> 26.866991 | AX21: =AW21/I21*100 -> 18.026698 | AY21: 0.22 | AZ21: 16.86 | BA21: -20.45 | BB21: -7.59 | BC21: -3.32 | BE21: 1973 | BF21: =IF(BE21>2020,0,IF(BE21>2008,1,IF(BE21>2001,2,IF(BE21>1990,3,IF(BE21>1980,4,IF(BE21>1973,5,IF(BE21>1970,6,IF(BE21>1960,7,IF(BE21>1958,8,IF(BE21>1953,9,10)))))))))) -> 6 | BG21: 3.21 | BH21: USD | BI21: Corp
A22: Franklin Resources, Inc. | B22: BEN | C22: Financials | D22: Capital Markets | E22: 46 | F22: 58 | G22: N | H22: Y | I22: 29.97 | J22: =(M22/I22)*100 -> 4.4044044 | K22: 0.33 | L22: 4 | M22: =K22*L22 -> 1.32 | N22: A10 | O22: 0.32 | P22: 46021 | Q22: 46031 | R22: =(K22-O22)/O22*100 -> 3.125 | S22: =IF(INDEX(Historical!$D$7:$D1112,MATCH(B22,Historical!$B$7:$B$1044,0))=0,"n/a",(INDEX(Historical!$C$7:$C$1044,MATCH(B22,Historical!$B$7:$B$1044,0))/INDEX(Historical!$D$7:$D$1044,MATCH(B22,Historical!$B$7:$B$1044,0))-1)*100) -> 3.2258065 | T22: =IF(INDEX(Historical!$F$7:$F$1044,MATCH(B22,Historical!$B$7:$B$1044,0))=0,"n/a",((INDEX(Historical!$C$7:$C$1044,MATCH(B22,Historical!$B$7:$B$1044,0))/INDEX(Historical!$F$7:$F$1044,MATCH(B22,Historical!$B$7:$B$1044,0)))^(1/3)-1)*100) -> 3.3357653 | U22: =IF(INDEX(Historical!$H$7:$H$1044,MATCH(B22,Historical!$B$7:$B$1044,0))=0,"n/a",((INDEX(Historical!$C$7:$C$1044,MATCH(B22,Historical!$B$7:$B$1044,0))/INDEX(Historical!$H$7:$H$1044,MATCH(B22,Historical!$B$7:$B$1044,0)))^(1/5)-1)*100) -> 3.4563716 | V22: =IF(INDEX(Historical!$M$7:$M$1044,MATCH(B22,Historical!$B$7:$B$1044,0))=0,"n/a",((INDEX(Historical!$C$7:$C$1044,MATCH(B22,Historical!$B$7:$B$1044,0))/INDEX(Historical!$M$7:$M$1044,MATCH(B22,Historical!$B$7:$B$1044,0)))^(1/10)-1)*100) -> 7.8712899 | W22: =IF(OR(U22<=0,U22="n/a",V22<=0,V22="n/a"),"n/a",U22/V22) -> 0.43911121 | X22: =IF(OR(AJ22<=0,AJ22="n/a",U22<=0,U22="n/a"),"n/a",U22/AJ22) -> n/a | Z22: =IF(OR(AC22<0.01,AC22="n/a"),"n/a",M22/AC22*100) -> 100.76336 | AA22: =IF(OR(AC22<0.01,AC22="n/a"),"n/a",I22/AC22) -> 22.877863 | AB22: 9 | AC22: 1.31 | AD22: 0.86 | AE22: 1.74 | AF22: 1.28 | AG22: 5.54 | AH22: 22.64 | AI22: 7.18 | AJ22: -10.54 | AK22: 11.89 | AL22: 15570 | AM22: 47.04 | AN22: 1.27 | AO22: =IF(U22="n/a","n/a",IF(AA22<0,"n/a",IF(AA22="n/a","n/a",J22+U22-AA22))) -> -15.017087 | AP22: =IF(U22="n/a","n/a",J22+U22) -> 7.860776 | AQ22: =IF(OR(AC22<0.01,AC22="n/a",AF22="n/a"),"n/a",(I22/SQRT(22.5*AC22*(I22/AF22))-1)*100) -> 14.083136 | AR22: =INDEX(Historical!$C$7:$C$1045,MATCH(B22,Historical!$B$7:$B$1045,0))*IF(AH22="n/a",1.03,IF(AH22<0,1.01,IF(AH22>10,1.1,(1+AH22/100)))) -> 1.408 | AS22: =IF($AI22="n/a",1.03*AR22,IF($AI22<0,1.01*AR22,IF($AI22>10,1.1*AR22,(1+$AI22/100)*AR22))) -> 1.5090944 | AT22: =IF($AK22="n/a",1.03*AS22,IF($AK22<0,1.01*AS22,IF($AK22>10,1.1*AS22,(1+$AK22/100)*AS22))) -> 1.6600038 | AU22: =IF($AK22="n/a",1.03*AT22,IF($AK22<0,1.01*AT22,IF($AK22>10,1.1*AT22,(1+$AK22/100)*AT22))) -> 1.8260042 | AV22: =IF($AK22="n/a",1.03*AU22,IF($AK22<0,1.01*AU22,IF($AK22>10,1.1*AU22,(1+$AK22/100)*AU22))) -> 2.0086046 | AW22: =SUM(AR22:AV22) -> 8.4117071 | AX22: =AW22/I22*100 -> 28.067091 | AY22: 1.58 | AZ22: 64.99 | BA22: -1.02 | BB22: 16.51 | BC22: 21.62 | BE22: 1981 | BF22: =IF(BE22>2020,0,IF(BE22>2008,1,IF(BE22>2001,2,IF(BE22>1990,3,IF(BE22>1980,4,IF(BE22>1973,5,IF(BE22>1970,6,IF(BE22>1960,7,IF(BE22>1958,8,IF(BE22>1953,9,10)))))))))) -> 4 | BG22: 2.05 | BH22: USD | BI22: Corp
A23: Brown-Forman Corporation | B23: BF-B | C23: Consumer Staples | D23: Beverages | E23: 41 | F23: 67 | G23: Y | H23: Y | I23: 25.77 | J23: =(M23/I23)*100 -> 3.5855646 | K23: 0.231 | L23: 4 | M23: =K23*L23 -> 0.924 | N23: A02 | O23: 0.2265 | P23: 45996 | Q23: 46024 | R23: =(K23-O23)/O23*100 -> 1.986755 | S23: =IF(INDEX(Historical!$D$7:$D1114,MATCH(B23,Historical!$B$7:$B$1044,0))=0,"n/a",(INDEX(Historical!$C$7:$C$1044,MATCH(B23,Historical!$B$7:$B$1044,0))/INDEX(Historical!$D$7:$D$1044,MATCH(B23,Historical!$B$7:$B$1044,0))-1)*100) -> 3.9944904 | T23: =IF(INDEX(Historical!$F$7:$F$1044,MATCH(B23,Historical!$B$7:$B$1044,0))=0,"n/a",((INDEX(Historical!$C$7:$C$1044,MATCH(B23,Historical!$B$7:$B$1044,0))/INDEX(Historical!$F$7:$F$1044,MATCH(B23,Historical!$B$7:$B$1044,0)))^(1/3)-1)*100) -> 6.3128149 | U23: =IF(INDEX(Historical!$H$7:$H$1044,MATCH(B23,Historical!$B$7:$B$1044,0))=0,"n/a",((INDEX(Historical!$C$7:$C$1044,MATCH(B23,Historical!$B$7:$B$1044,0))/INDEX(Historical!$H$7:$H$1044,MATCH(B23,Historical!$B$7:$B$1044,0)))^(1/5)-1)*100) -> 5.379022 | V23: =IF(INDEX(Historical!$M$7:$M$1044,MATCH(B23,Historical!$B$7:$B$1044,0))=0,"n/a",((INDEX(Historical!$C$7:$C$1044,MATCH(B23,Historical!$B$7:$B$1044,0))/INDEX(Historical!$M$7:$M$1044,MATCH(B23,Historical!$B$7:$B$1044,0)))^(1/10)-1)*100) -> 5.8318792 | W23: =IF(OR(U23<=0,U23="n/a",V23<=0,V23="n/a"),"n/a",U23/V23) -> 0.92234798 | X23: =IF(OR(AJ23<=0,AJ23="n/a",U23<=0,U23="n/a"),"n/a",U23/AJ23) -> 4.1061237 | Z23: =IF(OR(AC23<0.01,AC23="n/a"),"n/a",M23/AC23*100) -> 53.72093 | AA23: =IF(OR(AC23<0.01,AC23="n/a"),"n/a",I23/AC23) -> 14.982558 | AB23: 4 | AC23: 1.72 | AD23: n/a | AE23: 3.04 | AF23: 2.9 | AG23: 20.42 | AH23: -4.74 | AI23: -3.22 | AJ23: 1.31 | AK23: -2.18 | AL23: 11910 | AM23: 39.03 | AN23: 0.67 | AO23: =IF(U23="n/a","n/a",IF(AA23<0,"n/a",IF(AA23="n/a","n/a",J23+U23-AA23))) -> -6.0179715 | AP23: =IF(U23="n/a","n/a",J23+U23) -> 8.9645867 | AQ23: =IF(OR(AC23<0.01,AC23="n/a",AF23="n/a"),"n/a",(I23/SQRT(22.5*AC23*(I23/AF23))-1)*100) -> 38.963494 | AR23: =INDEX(Historical!$C$7:$C$1045,MATCH(B23,Historical!$B$7:$B$1045,0))*IF(AH23="n/a",1.03,IF(AH23<0,1.01,IF(AH23>10,1.1,(1+AH23/100)))) -> 0.91506 | AS23: =IF($AI23="n/a",1.03*AR23,IF($AI23<0,1.01*AR23,IF($AI23>10,1.1*AR23,(1+$AI23/100)*AR23))) -> 0.9242106 | AT23: =IF($AK23="n/a",1.03*AS23,IF($AK23<0,1.01*AS23,IF($AK23>10,1.1*AS23,(1+$AK23/100)*AS23))) -> 0.93345271 | AU23: =IF($AK23="n/a",1.03*AT23,IF($AK23<0,1.01*AT23,IF($AK23>10,1.1*AT23,(1+$AK23/100)*AT23))) -> 0.94278723 | AV23: =IF($AK23="n/a",1.03*AU23,IF($AK23<0,1.01*AU23,IF($AK23>10,1.1*AU23,(1+$AK23/100)*AU23))) -> 0.95221511 | AW23: =SUM(AR23:AV23) -> 4.6677256 | AX23: =AW23/I23*100 -> 18.113022 | AY23: 0.33 | AZ23: 13.98 | BA23: -28.77 | BB23: -3.9 | BC23: -7.96 | BE23: 1985 | BF23: =IF(BE23>2020,0,IF(BE23>2008,1,IF(BE23>2001,2,IF(BE23>1990,3,IF(BE23>1980,4,IF(BE23>1973,5,IF(BE23>1970,6,IF(BE23>1960,7,IF(BE23>1958,8,IF(BE23>1953,9,10)))))))))) -> 4 | BG23: 9.86 | BH23: USD | BI23: Corp
A24: Black Hills Corporation | B24: BKH | C24: Utilities | D24: Multi-Utilities | E24: 56 | F24: 28 | G24: N | H24: N | I24: 75.29 | J24: =(M24/I24)*100 -> 3.7348918 | K24: 0.703 | L24: 4 | M24: =K24*L24 -> 2.812 | N24: C01 | O24: 0.676 | P24: 46070 | Q24: 46082 | R24: =(K24-O24)/O24*100 -> 3.9940828 | S24: =IF(INDEX(Historical!$D$7:$D1120,MATCH(B24,Historical!$B$7:$B$1044,0))=0,"n/a",(INDEX(Historical!$C$7:$C$1044,MATCH(B24,Historical!$B$7:$B$1044,0))/INDEX(Historical!$D$7:$D$1044,MATCH(B24,Historical!$B$7:$B$1044,0))-1)*100) -> 4 | T24: =IF(INDEX(Historical!$F$7:$F$1044,MATCH(B24,Historical!$B$7:$B$1044,0))=0,"n/a",((INDEX(Historical!$C$7:$C$1044,MATCH(B24,Historical!$B$7:$B$1044,0))/INDEX(Historical!$F$7:$F$1044,MATCH(B24,Historical!$B$7:$B$1044,0)))^(1/3)-1)*100) -> 3.9114045 | U24: =IF(INDEX(Historical!$H$7:$H$1044,MATCH(B24,Historical!$B$7:$B$1044,0))=0,"n/a",((INDEX(Historical!$C$7:$C$1044,MATCH(B24,Historical!$B$7:$B$1044,0))/INDEX(Historical!$H$7:$H$1044,MATCH(B24,Historical!$B$7:$B$1044,0)))^(1/5)-1)*100) -> 4.4983398 | V24: =IF(INDEX(Historical!$M$7:$M$1044,MATCH(B24,Historical!$B$7:$B$1044,0))=0,"n/a",((INDEX(Historical!$C$7:$C$1044,MATCH(B24,Historical!$B$7:$B$1044,0))/INDEX(Historical!$M$7:$M$1044,MATCH(B24,Historical!$B$7:$B$1044,0)))^(1/10)-1)*100) -> 5.2565588 | W24: =IF(OR(U24<=0,U24="n/a",V24<=0,V24="n/a"),"n/a",U24/V24) -> 0.85575754 | X24: =IF(OR(AJ24<=0,AJ24="n/a",U24<=0,U24="n/a"),"n/a",U24/AJ24) -> 2.513039 | Z24: =IF(OR(AC24<0.01,AC24="n/a"),"n/a",M24/AC24*100) -> 70.653266 | AA24: =IF(OR(AC24<0.01,AC24="n/a"),"n/a",I24/AC24) -> 18.917085 | AB24: 12 | AC24: 3.98 | AD24: 2.45 | AE24: 2.48 | AF24: 1.49 | AG24: 7.96 | AH24: 6.16 | AI24: 6.09 | AJ24: 1.79 | AK24: 6.65 | AL24: 5730 | AM24: 0.46 | AN24: 1.23 | AO24: =IF(U24="n/a","n/a",IF(AA24<0,"n/a",IF(AA24="n/a","n/a",J24+U24-AA24))) -> -10.683854 | AP24: =IF(U24="n/a","n/a",J24+U24) -> 8.2332315 | AQ24: =IF(OR(AC24<0.01,AC24="n/a",AF24="n/a"),"n/a",(I24/SQRT(22.5*AC24*(I24/AF24))-1)*100) -> 11.925486 | AR24: =INDEX(Historical!$C$7:$C$1045,MATCH(B24,Historical!$B$7:$B$1045,0))*IF(AH24="n/a",1.03,IF(AH24<0,1.01,IF(AH24>10,1.1,(1+AH24/100)))) -> 2.8705664 | AS24: =IF($AI24="n/a",1.03*AR24,IF($AI24<0,1.01*AR24,IF($AI24>10,1.1*AR24,(1+$AI24/100)*AR24))) -> 3.0453839 | AT24: =IF($AK24="n/a",1.03*AS24,IF($AK24<0,1.01*AS24,IF($AK24>10,1.1*AS24,(1+$AK24/100)*AS24))) -> 3.2479019 | AU24: =IF($AK24="n/a",1.03*AT24,IF($AK24<0,1.01*AT24,IF($AK24>10,1.1*AT24,(1+$AK24/100)*AT24))) -> 3.4638874 | AV24: =IF($AK24="n/a",1.03*AU24,IF($AK24<0,1.01*AU24,IF($AK24>10,1.1*AU24,(1+$AK24/100)*AU24))) -> 3.6942359 | AW24: =SUM(AR24:AV24) -> 16.321976 | AX24: =AW24/I24*100 -> 21.678809 | AY24: 0.72 | AZ24: 35.69 | BA24: -4.32 | BB24: 3.62 | BC24: 11.88 | BE24: 1972 | BF24: =IF(BE24>2020,0,IF(BE24>2008,1,IF(BE24>2001,2,IF(BE24>1990,3,IF(BE24>1980,4,IF(BE24>1973,5,IF(BE24>1970,6,IF(BE24>1960,7,IF(BE24>1958,8,IF(BE24>1953,9,10)))))))))) -> 6 | BG24: 2.7 | BH24: USD | BI24: Corp
A25: Bank of Utica | B25: BKUTK | C25: Financials | D25: Banks | E25: 26 | F25: 142 | G25: - | H25: - | I25: 659 | J25: =(M25/I25)*100 -> 2.9590288 | K25: 9.75 | L25: 2 | M25: =K25*L25 -> 19.5 | N25: JaJl | O25: 9.5 | P25: 46022 | Q25: 46042 | R25: =(K25-O25)/O25*100 -> 2.6315789 | S25: =IF(INDEX(Historical!$D$7:$D1122,MATCH(B25,Historical!$B$7:$B$1044,0))=0,"n/a",(INDEX(Historical!$C$7:$C$1044,MATCH(B25,Historical!$B$7:$B$1044,0))/INDEX(Historical!$D$7:$D$1044,MATCH(B25,Historical!$B$7:$B$1044,0))-1)*100) -> 2.7027027 | T25: =IF(INDEX(Historical!$F$7:$F$1044,MATCH(B25,Historical!$B$7:$B$1044,0))=0,"n/a",((INDEX(Historical!$C$7:$C$1044,MATCH(B25,Historical!$B$7:$B$1044,0))/INDEX(Historical!$F$7:$F$1044,MATCH(B25,Historical!$B$7:$B$1044,0)))^(1/3)-1)*100) -> 2.7791884 | U25: =IF(INDEX(Historical!$H$7:$H$1044,MATCH(B25,Historical!$B$7:$B$1044,0))=0,"n/a",((INDEX(Historical!$C$7:$C$1044,MATCH(B25,Historical!$B$7:$B$1044,0))/INDEX(Historical!$H$7:$H$1044,MATCH(B25,Historical!$B$7:$B$1044,0)))^(1/5)-1)*100) -> 4.156021 | V25: =IF(INDEX(Historical!$M$7:$M$1044,MATCH(B25,Historical!$B$7:$B$1044,0))=0,"n/a",((INDEX(Historical!$C$7:$C$1044,MATCH(B25,Historical!$B$7:$B$1044,0))/INDEX(Historical!$M$7:$M$1044,MATCH(B25,Historical!$B$7:$B$1044,0)))^(1/10)-1)*100) -> 4.5296213 | W25: =IF(OR(U25<=0,U25="n/a",V25<=0,V25="n/a"),"n/a",U25/V25) -> 0.91752063 | X25: =IF(OR(AJ25<=0,AJ25="n/a",U25<=0,U25="n/a"),"n/a",U25/AJ25) -> n/a | Z25: =IF(OR(AC25<0.01,AC25="n/a"),"n/a",M25/AC25*100) -> n/a | AA25: =IF(OR(AC25<0.01,AC25="n/a"),"n/a",I25/AC25) -> n/a | AB25: 12 | AC25: n/a | AD25: n/a | AE25: n/a | AF25: n/a | AG25: n/a | AH25: n/a | AI25: n/a | AJ25: n/a | AK25: n/a | AL25: n/a | AM25: n/a | AN25: n/a | AO25: =IF(U25="n/a","n/a",IF(AA25<0,"n/a",IF(AA25="n/a","n/a",J25+U25-AA25))) -> n/a | AP25: =IF(U25="n/a","n/a",J25+U25) -> 7.1150498 | AQ25: =IF(OR(AC25<0.01,AC25="n/a",AF25="n/a"),"n/a",(I25/SQRT(22.5*AC25*(I25/AF25))-1)*100) -> n/a | AR25: =INDEX(Historical!$C$7:$C$1045,MATCH(B25,Historical!$B$7:$B$1045,0))*IF(AH25="n/a",1.03,IF(AH25<0,1.01,IF(AH25>10,1.1,(1+AH25/100)))) -> 19.57 | AS25: =IF($AI25="n/a",1.03*AR25,IF($AI25<0,1.01*AR25,IF($AI25>10,1.1*AR25,(1+$AI25/100)*AR25))) -> 20.1571 | AT25: =IF($AK25="n/a",1.03*AS25,IF($AK25<0,1.01*AS25,IF($AK25>10,1.1*AS25,(1+$AK25/100)*AS25))) -> 20.761813 | AU25: =IF($AK25="n/a",1.03*AT25,IF($AK25<0,1.01*AT25,IF($AK25>10,1.1*AT25,(1+$AK25/100)*AT25))) -> 21.384667 | AV25: =IF($AK25="n/a",1.03*AU25,IF($AK25<0,1.01*AU25,IF($AK25>10,1.1*AU25,(1+$AK25/100)*AU25))) -> 22.026207 | AW25: =SUM(AR25:AV25) -> 103.89979 | AX25: =AW25/I25*100 -> 15.76628 | AY25: n/a | AZ25: n/a | BA25: n/a | BB25: n/a | BC25: n/a | BD25: OTC | BE25: 2001 | BF25: =IF(BE25>2020,0,IF(BE25>2008,1,IF(BE25>2001,2,IF(BE25>1990,3,IF(BE25>1980,4,IF(BE25>1973,5,IF(BE25>1970,6,IF(BE25>1960,7,IF(BE25>1958,8,IF(BE25>1953,9,10)))))))))) -> 3 | BG25: n/a | BH25: USD | BI25: Corp
A26: Badger Meter, Inc. | B26: BMI | C26: Information Technology | D26: Electronic Equipment, Instruments & Components | E26: 33 | F26: 93 | G26: N | H26: Y | I26: 120.91 | J26: =(M26/I26)*100 -> 1.3232983 | K26: 0.4 | L26: 4 | M26: =K26*L26 -> 1.6 | N26: C15 | O26: 0.34 | P26: 45891 | Q26: 45905 | R26: =(K26-O26)/O26*100 -> 17.647059 | S26: =IF(INDEX(Historical!$D$7:$D1124,MATCH(B26,Historical!$B$7:$B$1044,0))=0,"n/a",(INDEX(Historical!$C$7:$C$1044,MATCH(B26,Historical!$B$7:$B$1044,0))/INDEX(Historical!$D$7:$D$1044,MATCH(B26,Historical!$B$7:$B$1044,0))-1)*100) -> 21.311475 | T26: =IF(INDEX(Historical!$F$7:$F$1044,MATCH(B26,Historical!$B$7:$B$1044,0))=0,"n/a",((INDEX(Historical!$C$7:$C$1044,MATCH(B26,Historical!$B$7:$B$1044,0))/INDEX(Historical!$F$7:$F$1044,MATCH(B26,Historical!$B$7:$B$1044,0)))^(1/3)-1)*100) -> 20.304239 | U26: =IF(INDEX(Historical!$H$7:$H$1044,MATCH(B26,Historical!$B$7:$B$1044,0))=0,"n/a",((INDEX(Historical!$C$7:$C$1044,MATCH(B26,Historical!$B$7:$B$1044,0))/INDEX(Historical!$H$7:$H$1044,MATCH(B26,Historical!$B$7:$B$1044,0)))^(1/5)-1)*100) -> 16.153616 | V26: =IF(INDEX(Historical!$M$7:$M$1044,MATCH(B26,Historical!$B$7:$B$1044,0))=0,"n/a",((INDEX(Historical!$C$7:$C$1044,MATCH(B26,Historical!$B$7:$B$1044,0))/INDEX(Historical!$M$7:$M$1044,MATCH(B26,Historical!$B$7:$B$1044,0)))^(1/10)-1)*100) -> 14.266707 | W26: =IF(OR(U26<=0,U26="n/a",V26<=0,V26="n/a"),"n/a",U26/V26) -> 1.1322596 | X26: =IF(OR(AJ26<=0,AJ26="n/a",U26<=0,U26="n/a"),"n/a",U26/AJ26) -> 0.69657681 | Z26: =IF(OR(AC26<0.01,AC26="n/a"),"n/a",M26/AC26*100) -> 36.199095 | AA26: =IF(OR(AC26<0.01,AC26="n/a"),"n/a",I26/AC26) -> 27.355204 | AB26: 12 | AC26: 4.42 | AD26: 4.55 | AE26: 3.94 | AF26: 5.11 | AG26: 19.6 | AH26: -6.17 | AI26: 9.34 | AJ26: 23.19 | AK26: 5.41 | AL26: 3530 | AM26: 0.74 | AN26: 0 | AO26: =IF(U26="n/a","n/a",IF(AA26<0,"n/a",IF(AA26="n/a","n/a",J26+U26-AA26))) -> -9.8782891 | AP26: =IF(U26="n/a","n/a",J26+U26) -> 17.476914 | AQ26: =IF(OR(AC26<0.01,AC26="n/a",AF26="n/a"),"n/a",(I26/SQRT(22.5*AC26*(I26/AF26))-1)*100) -> 149.2523 | AR26: =INDEX(Historical!$C$7:$C$1045,MATCH(B26,Historical!$B$7:$B$1045,0))*IF(AH26="n/a",1.03,IF(AH26<0,1.01,IF(AH26>10,1.1,(1+AH26/100)))) -> 1.4948 | AS26: =IF($AI26="n/a",1.03*AR26,IF($AI26<0,1.01*AR26,IF($AI26>10,1.1*AR26,(1+$AI26/100)*AR26))) -> 1.6344143 | AT26: =IF($AK26="n/a",1.03*AS26,IF($AK26<0,1.01*AS26,IF($AK26>10,1.1*AS26,(1+$AK26/100)*AS26))) -> 1.7228361 | AU26: =IF($AK26="n/a",1.03*AT26,IF($AK26<0,1.01*AT26,IF($AK26>10,1.1*AT26,(1+$AK26/100)*AT26))) -> 1.8160416 | AV26: =IF($AK26="n/a",1.03*AU26,IF($AK26<0,1.01*AU26,IF($AK26>10,1.1*AU26,(1+$AK26/100)*AU26))) -> 1.9142894 | AW26: =SUM(AR26:AV26) -> 8.5823814 | AX26: =AW26/I26*100 -> 7.0981568 | AY26: 0.7 | AZ26: 7.87 | BA26: -52.78 | BB26: -17.12 | BC26: -29.3 | BE26: 1993 | BF26: =IF(BE26>2020,0,IF(BE26>2008,1,IF(BE26>2001,2,IF(BE26>1990,3,IF(BE26>1980,4,IF(BE26>1973,5,IF(BE26>1970,6,IF(BE26>1960,7,IF(BE26>1958,8,IF(BE26>1953,9,10)))))))))) -> 3 | BG26: 13.96 | BH26: USD | BI26: Corp
A27: Brady Corporation | B27: BRC | C27: Industrials | D27: Commercial Services & Supplies | E27: 40 | F27: 69 | G27: N | H27: N | I27: 81.82 | J27: =(M27/I27)*100 -> 1.1977512 | K27: 0.245 | L27: 4 | M27: =K27*L27 -> 0.98 | N27: A31 | O27: 0.24 | P27: 45940 | Q27: 45961 | R27: =(K27-O27)/O27*100 -> 2.0833333 | S27: =IF(INDEX(Historical!$D$7:$D1133,MATCH(B27,Historical!$B$7:$B$1044,0))=0,"n/a",(INDEX(Historical!$C$7:$C$1044,MATCH(B27,Historical!$B$7:$B$1044,0))/INDEX(Historical!$D$7:$D$1044,MATCH(B27,Historical!$B$7:$B$1044,0))-1)*100) -> 2.1164021 | T27: =IF(INDEX(Historical!$F$7:$F$1044,MATCH(B27,Historical!$B$7:$B$1044,0))=0,"n/a",((INDEX(Historical!$C$7:$C$1044,MATCH(B27,Historical!$B$7:$B$1044,0))/INDEX(Historical!$F$7:$F$1044,MATCH(B27,Historical!$B$7:$B$1044,0)))^(1/3)-1)*100) -> 2.1628292 | U27: =IF(INDEX(Historical!$H$7:$H$1044,MATCH(B27,Historical!$B$7:$B$1044,0))=0,"n/a",((INDEX(Historical!$C$7:$C$1044,MATCH(B27,Historical!$B$7:$B$1044,0))/INDEX(Historical!$H$7:$H$1044,MATCH(B27,Historical!$B$7:$B$1044,0)))^(1/5)-1)*100) -> 2.0357534 | V27: =IF(INDEX(Historical!$M$7:$M$1044,MATCH(B27,Historical!$B$7:$B$1044,0))=0,"n/a",((INDEX(Historical!$C$7:$C$1044,MATCH(B27,Historical!$B$7:$B$1044,0))/INDEX(Historical!$M$7:$M$1044,MATCH(B27,Historical!$B$7:$B$1044,0)))^(1/10)-1)*100) -> 1.8610684 | W27: =IF(OR(U27<=0,U27="n/a",V27<=0,V27="n/a"),"n/a",U27/V27) -> 1.0938627 | X27: =IF(OR(AJ27<=0,AJ27="n/a",U27<=0,U27="n/a"),"n/a",U27/AJ27) -> 0.1534102 | Z27: =IF(OR(AC27<0.01,AC27="n/a"),"n/a",M27/AC27*100) -> 22.95082 | AA27: =IF(OR(AC27<0.01,AC27="n/a"),"n/a",I27/AC27) -> 19.161593 | AB27: 7 | AC27: 4.27 | AD27: 1.46 | AE27: 2.46 | AF27: 2.94 | AG27: 16.78 | AH27: 9.35 | AI27: 12.72 | AJ27: 13.27 | AK27: 9.86 | AL27: 3860 | AM27: 10.05 | AN27: 0.11 | AO27: =IF(U27="n/a","n/a",IF(AA27<0,"n/a",IF(AA27="n/a","n/a",J27+U27-AA27))) -> -15.928088 | AP27: =IF(U27="n/a","n/a",J27+U27) -> 3.2335046 | AQ27: =IF(OR(AC27<0.01,AC27="n/a",AF27="n/a"),"n/a",(I27/SQRT(22.5*AC27*(I27/AF27))-1)*100) -> 58.233417 | AR27: =INDEX(Historical!$C$7:$C$1045,MATCH(B27,Historical!$B$7:$B$1045,0))*IF(AH27="n/a",1.03,IF(AH27<0,1.01,IF(AH27>10,1.1,(1+AH27/100)))) -> 1.0552275 | AS27: =IF($AI27="n/a",1.03*AR27,IF($AI27<0,1.01*AR27,IF($AI27>10,1.1*AR27,(1+$AI27/100)*AR27))) -> 1.1607502 | AT27: =IF($AK27="n/a",1.03*AS27,IF($AK27<0,1.01*AS27,IF($AK27>10,1.1*AS27,(1+$AK27/100)*AS27))) -> 1.2752002 | AU27: =IF($AK27="n/a",1.03*AT27,IF($AK27<0,1.01*AT27,IF($AK27>10,1.1*AT27,(1+$AK27/100)*AT27))) -> 1.400935 | AV27: =IF($AK27="n/a",1.03*AU27,IF($AK27<0,1.01*AU27,IF($AK27>10,1.1*AU27,(1+$AK27/100)*AU27))) -> 1.5390672 | AW27: =SUM(AR27:AV27) -> 6.4311801 | AX27: =AW27/I27*100 -> 7.8601566 | AY27: 0.62 | AZ27: 24.42 | BA27: -17.59 | BB27: -3.96 | BC27: 2.04 | BE27: 1986 | BF27: =IF(BE27>2020,0,IF(BE27>2008,1,IF(BE27>2001,2,IF(BE27>1990,3,IF(BE27>1980,4,IF(BE27>1973,5,IF(BE27>1970,6,IF(BE27>1960,7,IF(BE27>1958,8,IF(BE27>1953,9,10)))))))))) -> 4 | BG27: 11.96 | BH27: USD | BI27: Corp
A28: Brown & Brown, Inc. | B28: BRO | C28: Financials | D28: Insurance | E28: 32 | F28: 111 | G28: - | H28: - | I28: 60.15 | J28: =(M28/I28)*100 -> 1.0972569 | K28: 0.165 | L28: 4 | M28: =K28*L28 -> 0.66 | N28: B08 | O28: 0.15 | P28: 45966 | Q28: 45973 | R28: =(K28-O28)/O28*100 -> 10 | S28: =IF(INDEX(Historical!$D$7:$D1134,MATCH(B28,Historical!$B$7:$B$1044,0))=0,"n/a",(INDEX(Historical!$C$7:$C$1044,MATCH(B28,Historical!$B$7:$B$1044,0))/INDEX(Historical!$D$7:$D$1044,MATCH(B28,Historical!$B$7:$B$1044,0))-1)*100) -> 13.888889 | T28: =IF(INDEX(Historical!$F$7:$F$1044,MATCH(B28,Historical!$B$7:$B$1044,0))=0,"n/a",((INDEX(Historical!$C$7:$C$1044,MATCH(B28,Historical!$B$7:$B$1044,0))/INDEX(Historical!$F$7:$F$1044,MATCH(B28,Historical!$B$7:$B$1044,0)))^(1/3)-1)*100) -> 13.331195 | U28: =IF(INDEX(Historical!$H$7:$H$1044,MATCH(B28,Historical!$B$7:$B$1044,0))=0,"n/a",((INDEX(Historical!$C$7:$C$1044,MATCH(B28,Historical!$B$7:$B$1044,0))/INDEX(Historical!$H$7:$H$1044,MATCH(B28,Historical!$B$7:$B$1044,0)))^(1/5)-1)*100) -> 12.094437 | V28: =IF(INDEX(Historical!$M$7:$M$1044,MATCH(B28,Historical!$B$7:$B$1044,0))=0,"n/a",((INDEX(Historical!$C$7:$C$1044,MATCH(B28,Historical!$B$7:$B$1044,0))/INDEX(Historical!$M$7:$M$1044,MATCH(B28,Historical!$B$7:$B$1044,0)))^(1/10)-1)*100) -> 10.516889 | W28: =IF(OR(U28<=0,U28="n/a",V28<=0,V28="n/a"),"n/a",U28/V28) -> 1.1500014 | X28: =IF(OR(AJ28<=0,AJ28="n/a",U28<=0,U28="n/a"),"n/a",U28/AJ28) -> 0.90391908 | Z28: =IF(OR(AC28<0.01,AC28="n/a"),"n/a",M28/AC28*100) -> 21.221865 | AA28: =IF(OR(AC28<0.01,AC28="n/a"),"n/a",I28/AC28) -> 19.340836 | AB28: 12 | AC28: 3.11 | AD28: 1.59 | AE28: 3.19 | AF28: 1.6 | AG28: 11.7 | AH28: 6.24 | AI28: 8.53 | AJ28: 13.38 | AK28: 7.71 | AL28: 20390 | AM28: 14.68 | AN28: 0.64 | AO28: =IF(U28="n/a","n/a",IF(AA28<0,"n/a",IF(AA28="n/a","n/a",J28+U28-AA28))) -> -6.1491418 | AP28: =IF(U28="n/a","n/a",J28+U28) -> 13.191694 | AQ28: =IF(OR(AC28<0.01,AC28="n/a",AF28="n/a"),"n/a",(I28/SQRT(22.5*AC28*(I28/AF28))-1)*100) -> 17.275246 | AR28: =INDEX(Historical!$C$7:$C$1045,MATCH(B28,Historical!$B$7:$B$1045,0))*IF(AH28="n/a",1.03,IF(AH28<0,1.01,IF(AH28>10,1.1,(1+AH28/100)))) -> 0.653376 | AS28: =IF($AI28="n/a",1.03*AR28,IF($AI28<0,1.01*AR28,IF($AI28>10,1.1*AR28,(1+$AI28/100)*AR28))) -> 0.70910897 | AT28: =IF($AK28="n/a",1.03*AS28,IF($AK28<0,1.01*AS28,IF($AK28>10,1.1*AS28,(1+$AK28/100)*AS28))) -> 0.76378127 | AU28: =IF($AK28="n/a",1.03*AT28,IF($AK28<0,1.01*AT28,IF($AK28>10,1.1*AT28,(1+$AK28/100)*AT28))) -> 0.82266881 | AV28: =IF($AK28="n/a",1.03*AU28,IF($AK28<0,1.01*AU28,IF($AK28>10,1.1*AU28,(1+$AK28/100)*AU28))) -> 0.88609658 | AW28: =SUM(AR28:AV28) -> 3.8350316 | AX28: =AW28/I28*100 -> 6.3757799 | AY28: 0.69 | AZ28: -2.29 | BA28: -47.16 | BB28: -11.1 | BC28: -26.14 | BE28: 1995 | BF28: =IF(BE28>2020,0,IF(BE28>2008,1,IF(BE28>2001,2,IF(BE28>1990,3,IF(BE28>1980,4,IF(BE28>1973,5,IF(BE28>1970,6,IF(BE28>1960,7,IF(BE28>1958,8,IF(BE28>1953,9,10)))))))))) -> 3 | BG28: 4.89 | BH28: USD | BI28: Corp
A29: Cardinal Health, Inc. | B29: CAH | C29: Health Care | D29: Health Care Providers & Services | E29: 29 | F29: 126 | G29: - | H29: - | I29: 192.88 | J29: =(M29/I29)*100 -> 1.0591041 | K29: 0.5107 | L29: 4 | M29: =K29*L29 -> 2.0428 | N29: A15 | O29: 0.5056 | P29: 45839 | Q29: 45853 | R29: =(K29-O29)/O29*100 -> 1.0087025 | S29: =IF(INDEX(Historical!$D$7:$D1139,MATCH(B29,Historical!$B$7:$B$1044,0))=0,"n/a",(INDEX(Historical!$C$7:$C$1044,MATCH(B29,Historical!$B$7:$B$1044,0))/INDEX(Historical!$D$7:$D$1044,MATCH(B29,Historical!$B$7:$B$1044,0))-1)*100) -> 1.0037766 | T29: =IF(INDEX(Historical!$F$7:$F$1044,MATCH(B29,Historical!$B$7:$B$1044,0))=0,"n/a",((INDEX(Historical!$C$7:$C$1044,MATCH(B29,Historical!$B$7:$B$1044,0))/INDEX(Historical!$F$7:$F$1044,MATCH(B29,Historical!$B$7:$B$1044,0)))^(1/3)-1)*100) -> 0.99695463 | U29: =IF(INDEX(Historical!$H$7:$H$1044,MATCH(B29,Historical!$B$7:$B$1044,0))=0,"n/a",((INDEX(Historical!$C$7:$C$1044,MATCH(B29,Historical!$B$7:$B$1044,0))/INDEX(Historical!$H$7:$H$1044,MATCH(B29,Historical!$B$7:$B$1044,0)))^(1/5)-1)*100) -> 0.99946895 | V29: =IF(INDEX(Historical!$M$7:$M$1044,MATCH(B29,Historical!$B$7:$B$1044,0))=0,"n/a",((INDEX(Historical!$C$7:$C$1044,MATCH(B29,Historical!$B$7:$B$1044,0))/INDEX(Historical!$M$7:$M$1044,MATCH(B29,Historical!$B$7:$B$1044,0)))^(1/10)-1)*100) -> 3.371225 | W29: =IF(OR(U29<=0,U29="n/a",V29<=0,V29="n/a"),"n/a",U29/V29) -> 0.29647056 | X29: =IF(OR(AJ29<=0,AJ29="n/a",U29<=0,U29="n/a"),"n/a",U29/AJ29) -> n/a | Z29: =IF(OR(AC29<0.01,AC29="n/a"),"n/a",M29/AC29*100) -> 29.392806 | AA29: =IF(OR(AC29<0.01,AC29="n/a"),"n/a",I29/AC29) -> 27.752518 | AB29: 6 | AC29: 6.95 | AD29: 1.01 | AE29: 0.19 | AF29: n/a | AG29: n/a | AH29: 25.29 | AI29: 12.42 | AJ29: n/a | AK29: 16.52 | AL29: 45390 | AM29: 0.25 | AN29: n/a | AO29: =IF(U29="n/a","n/a",IF(AA29<0,"n/a",IF(AA29="n/a","n/a",J29+U29-AA29))) -> -25.693945 | AP29: =IF(U29="n/a","n/a",J29+U29) -> 2.0585731 | AQ29: =IF(OR(AC29<0.01,AC29="n/a",AF29="n/a"),"n/a",(I29/SQRT(22.5*AC29*(I29/AF29))-1)*100) -> n/a | AR29: =INDEX(Historical!$C$7:$C$1045,MATCH(B29,Historical!$B$7:$B$1045,0))*IF(AH29="n/a",1.03,IF(AH29<0,1.01,IF(AH29>10,1.1,(1+AH29/100)))) -> 2.23586 | AS29: =IF($AI29="n/a",1.03*AR29,IF($AI29<0,1.01*AR29,IF($AI29>10,1.1*AR29,(1+$AI29/100)*AR29))) -> 2.459446 | AT29: =IF($AK29="n/a",1.03*AS29,IF($AK29<0,1.01*AS29,IF($AK29>10,1.1*AS29,(1+$AK29/100)*AS29))) -> 2.7053906 | AU29: =IF($AK29="n/a",1.03*AT29,IF($AK29<0,1.01*AT29,IF($AK29>10,1.1*AT29,(1+$AK29/100)*AT29))) -> 2.9759297 | AV29: =IF($AK29="n/a",1.03*AU29,IF($AK29<0,1.01*AU29,IF($AK29>10,1.1*AU29,(1+$AK29/100)*AU29))) -> 3.2735226 | AW29: =SUM(AR29:AV29) -> 13.650149 | AX29: =AW29/I29*100 -> 7.0770162 | AY29: 0.59 | AZ29: 41.09 | BA29: -17.43 | BB29: -9.84 | BC29: 1.99 | BE29: 1997 | BF29: =IF(BE29>2020,0,IF(BE29>2008,1,IF(BE29>2001,2,IF(BE29>1990,3,IF(BE29>1980,4,IF(BE29>1973,5,IF(BE29>1970,6,IF(BE29>1960,7,IF(BE29>1958,8,IF(BE29>1953,9,10)))))))))) -> 3 | BG29: 3.16 | BH29: USD | BI29: Corp
A30: Casey's General Stores, Inc. | B30: CASY | C30: Consumer Staples | D30: Consumer Staples Distribution & Retail | E30: 25 | F30: 144 | G30: N | H30: N | I30: 822.15 | J30: =(M30/I30)*100 -> 0.27732166 | K30: 0.57 | L30: 4 | M30: =K30*L30 -> 2.28 | N30: B15 | O30: 0.5 | P30: 45870 | Q30: 45884 | R30: =(K30-O30)/O30*100 -> 14 | S30: =IF(INDEX(Historical!$D$7:$D1142,MATCH(B30,Historical!$B$7:$B$1044,0))=0,"n/a",(INDEX(Historical!$C$7:$C$1044,MATCH(B30,Historical!$B$7:$B$1044,0))/INDEX(Historical!$D$7:$D$1044,MATCH(B30,Historical!$B$7:$B$1044,0))-1)*100) -> 15.053763 | T30: =IF(INDEX(Historical!$F$7:$F$1044,MATCH(B30,Historical!$B$7:$B$1044,0))=0,"n/a",((INDEX(Historical!$C$7:$C$1044,MATCH(B30,Historical!$B$7:$B$1044,0))/INDEX(Historical!$F$7:$F$1044,MATCH(B30,Historical!$B$7:$B$1044,0)))^(1/3)-1)*100) -> 13.593541 | U30: =IF(INDEX(Historical!$H$7:$H$1044,MATCH(B30,Historical!$B$7:$B$1044,0))=0,"n/a",((INDEX(Historical!$C$7:$C$1044,MATCH(B30,Historical!$B$7:$B$1044,0))/INDEX(Historical!$H$7:$H$1044,MATCH(B30,Historical!$B$7:$B$1044,0)))^(1/5)-1)*100) -> 10.825771 | V30: =IF(INDEX(Historical!$M$7:$M$1044,MATCH(B30,Historical!$B$7:$B$1044,0))=0,"n/a",((INDEX(Historical!$C$7:$C$1044,MATCH(B30,Historical!$B$7:$B$1044,0))/INDEX(Historical!$M$7:$M$1044,MATCH(B30,Historical!$B$7:$B$1044,0)))^(1/10)-1)*100) -> 9.8028086 | W30: =IF(OR(U30<=0,U30="n/a",V30<=0,V30="n/a"),"n/a",U30/V30) -> 1.104354 | X30: =IF(OR(AJ30<=0,AJ30="n/a",U30<=0,U30="n/a"),"n/a",U30/AJ30) -> 0.6948505 | Z30: =IF(OR(AC30<0.01,AC30="n/a"),"n/a",M30/AC30*100) -> 13.088404 | AA30: =IF(OR(AC30<0.01,AC30="n/a"),"n/a",I30/AC30) -> 47.195752 | AB30: 12 | AC30: 17.42 | AD30: 2.76 | AE30: 1.79 | AF30: 7.89 | AG30: 17.88 | AH30: 23.54 | AI30: 10.31 | AJ30: 15.58 | AK30: 14.95 | AL30: 30390 | AM30: 0.52 | AN30: 0.75 | AO30: =IF(U30="n/a","n/a",IF(AA30<0,"n/a",IF(AA30="n/a","n/a",J30+U30-AA30))) -> -36.092659 | AP30: =IF(U30="n/a","n/a",J30+U30) -> 11.103093 | AQ30: =IF(OR(AC30<0.01,AC30="n/a",AF30="n/a"),"n/a",(I30/SQRT(22.5*AC30*(I30/AF30))-1)*100) -> 306.81663 | AR30: =INDEX(Historical!$C$7:$C$1045,MATCH(B30,Historical!$B$7:$B$1045,0))*IF(AH30="n/a",1.03,IF(AH30<0,1.01,IF(AH30>10,1.1,(1+AH30/100)))) -> 2.354 | AS30: =IF($AI30="n/a",1.03*AR30,IF($AI30<0,1.01*AR30,IF($AI30>10,1.1*AR30,(1+$AI30/100)*AR30))) -> 2.5894 | AT30: =IF($AK30="n/a",1.03*AS30,IF($AK30<0,1.01*AS30,IF($AK30>10,1.1*AS30,(1+$AK30/100)*AS30))) -> 2.84834 | AU30: =IF($AK30="n/a",1.03*AT30,IF($AK30<0,1.01*AT30,IF($AK30>10,1.1*AT30,(1+$AK30/100)*AT30))) -> 3.133174 | AV30: =IF($AK30="n/a",1.03*AU30,IF($AK30<0,1.01*AU30,IF($AK30>10,1.1*AU30,(1+$AK30/100)*AU30))) -> 3.4464914 | AW30: =SUM(AR30:AV30) -> 14.371405 | AX30: =AW30/I30*100 -> 1.7480272 | AY30: 0.61 | AZ30: 91.2 | BA30: 1.94 | BB30: 14.72 | BC30: 37.82 | BE30: 2000 | BF30: =IF(BE30>2020,0,IF(BE30>2008,1,IF(BE30>2001,2,IF(BE30>1990,3,IF(BE30>1980,4,IF(BE30>1973,5,IF(BE30>1970,6,IF(BE30>1960,7,IF(BE30>1958,8,IF(BE30>1953,9,10)))))))))) -> 3 | BG30: 7.74 | BH30: USD | BI30: Corp
A31: Caterpillar Inc. | B31: CAT | C31: Industrials | D31: Machinery | E31: 32 | F31: 107 | G31: N | H31: Y | I31: 890.11 | J31: =(M31/I31)*100 -> 0.67856782 | K31: 1.51 | L31: 4 | M31: =K31*L31 -> 6.04 | N31: B19 | O31: 1.41 | P31: 45859 | Q31: 45889 | R31: =(K31-O31)/O31*100 -> 7.0921986 | S31: =IF(INDEX(Historical!$D$7:$D1143,MATCH(B31,Historical!$B$7:$B$1044,0))=0,"n/a",(INDEX(Historical!$C$7:$C$1044,MATCH(B31,Historical!$B$7:$B$1044,0))/INDEX(Historical!$D$7:$D$1044,MATCH(B31,Historical!$B$7:$B$1044,0))-1)*100) -> 7.7490775 | T31: =IF(INDEX(Historical!$F$7:$F$1044,MATCH(B31,Historical!$B$7:$B$1044,0))=0,"n/a",((INDEX(Historical!$C$7:$C$1044,MATCH(B31,Historical!$B$7:$B$1044,0))/INDEX(Historical!$F$7:$F$1044,MATCH(B31,Historical!$B$7:$B$1044,0)))^(1/3)-1)*100) -> 8.1243784 | U31: =IF(INDEX(Historical!$H$7:$H$1044,MATCH(B31,Historical!$B$7:$B$1044,0))=0,"n/a",((INDEX(Historical!$C$7:$C$1044,MATCH(B31,Historical!$B$7:$B$1044,0))/INDEX(Historical!$H$7:$H$1044,MATCH(B31,Historical!$B$7:$B$1044,0)))^(1/5)-1)*100) -> 7.2267459 | V31: =IF(INDEX(Historical!$M$7:$M$1044,MATCH(B31,Historical!$B$7:$B$1044,0))=0,"n/a",((INDEX(Historical!$C$7:$C$1044,MATCH(B31,Historical!$B$7:$B$1044,0))/INDEX(Historical!$M$7:$M$1044,MATCH(B31,Historical!$B$7:$B$1044,0)))^(1/10)-1)*100) -> 7.1042123 | W31: =IF(OR(U31<=0,U31="n/a",V31<=0,V31="n/a"),"n/a",U31/V31) -> 1.017248 | X31: =IF(OR(AJ31<=0,AJ31="n/a",U31<=0,U31="n/a"),"n/a",U31/AJ31) -> 0.257638 | Z31: =IF(OR(AC31<0.01,AC31="n/a"),"n/a",M31/AC31*100) -> 32.076474 | AA31: =IF(OR(AC31<0.01,AC31="n/a"),"n/a",I31/AC31) -> 47.270844 | AB31: 12 | AC31: 18.83 | AD31: 1.56 | AE31: 6.13 | AF31: 19.43 | AG31: 43.54 | AH31: 21.19 | AI31: 21.05 | AJ31: 28.05 | AK31: 20.41 | AL31: 414160 | AM31: 0.21 | AN31: 2.07 | AO31: =IF(U31="n/a","n/a",IF(AA31<0,"n/a",IF(AA31="n/a","n/a",J31+U31-AA31))) -> -39.365531 | AP31: =IF(U31="n/a","n/a",J31+U31) -> 7.9053137 | AQ31: =IF(OR(AC31<0.01,AC31="n/a",AF31="n/a"),"n/a",(I31/SQRT(22.5*AC31*(I31/AF31))-1)*100) -> 538.91314 | AR31: =INDEX(Historical!$C$7:$C$1045,MATCH(B31,Historical!$B$7:$B$1045,0))*IF(AH31="n/a",1.03,IF(AH31<0,1.01,IF(AH31>10,1.1,(1+AH31/100)))) -> 6.424 | AS31: =IF($AI31="n/a",1.03*AR31,IF($AI31<0,1.01*AR31,IF($AI31>10,1.1*AR31,(1+$AI31/100)*AR31))) -> 7.0664 | AT31: =IF($AK31="n/a",1.03*AS31,IF($AK31<0,1.01*AS31,IF($AK31>10,1.1*AS31,(1+$AK31/100)*AS31))) -> 7.77304 | AU31: =IF($AK31="n/a",1.03*AT31,IF($AK31<0,1.01*AT31,IF($AK31>10,1.1*AT31,(1+$AK31/100)*AT31))) -> 8.550344 | AV31: =IF($AK31="n/a",1.03*AU31,IF($AK31<0,1.01*AU31,IF($AK31>10,1.1*AU31,(1+$AK31/100)*AU31))) -> 9.4053784 | AW31: =SUM(AR31:AV31) -> 39.219162 | AX31: =AW31/I31*100 -> 4.4061029 | AY31: 1.55 | AZ31: 194.57 | BA31: 5.3 | BB31: 19.04 | BC31: 51.21 | BE31: 1994 | BF31: =IF(BE31>2020,0,IF(BE31>2008,1,IF(BE31>2001,2,IF(BE31>1990,3,IF(BE31>1980,4,IF(BE31>1973,5,IF(BE31>1970,6,IF(BE31>1960,7,IF(BE31>1958,8,IF(BE31>1953,9,10)))))))))) -> 3 | BG31: 9.53 | BH31: USD | BI31: Corp
A32: Chubb Limited | B32: CB | C32: Financials | D32: Insurance | E32: 32 | F32: 105 | G32: N | H32: N | I32: 327 | J32: =(M32/I32)*100 -> 1.1865443 | K32: 0.97 | L32: 4 | M32: =K32*L32 -> 3.88 | N32: A21 | O32: 0.91 | P32: 45821 | Q32: 45841 | R32: =(K32-O32)/O32*100 -> 6.5934066 | S32: =IF(INDEX(Historical!$D$7:$D1144,MATCH(B32,Historical!$B$7:$B$1044,0))=0,"n/a",(INDEX(Historical!$C$7:$C$1044,MATCH(B32,Historical!$B$7:$B$1044,0))/INDEX(Historical!$D$7:$D$1044,MATCH(B32,Historical!$B$7:$B$1044,0))-1)*100) -> 6.2146893 | T32: =IF(INDEX(Historical!$F$7:$F$1044,MATCH(B32,Historical!$B$7:$B$1044,0))=0,"n/a",((INDEX(Historical!$C$7:$C$1044,MATCH(B32,Historical!$B$7:$B$1044,0))/INDEX(Historical!$F$7:$F$1044,MATCH(B32,Historical!$B$7:$B$1044,0)))^(1/3)-1)*100) -> 4.8713233 | U32: =IF(INDEX(Historical!$H$7:$H$1044,MATCH(B32,Historical!$B$7:$B$1044,0))=0,"n/a",((INDEX(Historical!$C$7:$C$1044,MATCH(B32,Historical!$B$7:$B$1044,0))/INDEX(Historical!$H$7:$H$1044,MATCH(B32,Historical!$B$7:$B$1044,0)))^(1/5)-1)*100) -> 4.2061339 | V32: =IF(INDEX(Historical!$M$7:$M$1044,MATCH(B32,Historical!$B$7:$B$1044,0))=0,"n/a",((INDEX(Historical!$C$7:$C$1044,MATCH(B32,Historical!$B$7:$B$1044,0))/INDEX(Historical!$M$7:$M$1044,MATCH(B32,Historical!$B$7:$B$1044,0)))^(1/10)-1)*100) -> 3.5996747 | W32: =IF(OR(U32<=0,U32="n/a",V32<=0,V32="n/a"),"n/a",U32/V32) -> 1.1684761 | X32: =IF(OR(AJ32<=0,AJ32="n/a",U32<=0,U32="n/a"),"n/a",U32/AJ32) -> 0.15612969 | Y32: Switz.,US$ | Z32: =IF(OR(AC32<0.01,AC32="n/a"),"n/a",M32/AC32*100) -> 13.705404 | AA32: =IF(OR(AC32<0.01,AC32="n/a"),"n/a",I32/AC32) -> 11.550689 | AB32: 12 | AC32: 28.31 | AD32: 1.28 | AE32: 2.08 | AF32: 1.72 | AG32: 16.2 | AH32: 9.31 | AI32: 7.93 | AJ32: 26.94 | AK32: 8.71 | AL32: 126830 | AM32: 0.38 | AN32: 0.31 | AO32: =IF(U32="n/a","n/a",IF(AA32<0,"n/a",IF(AA32="n/a","n/a",J32+U32-AA32))) -> -6.1580106 | AP32: =IF(U32="n/a","n/a",J32+U32) -> 5.3926783 | AQ32: =IF(OR(AC32<0.01,AC32="n/a",AF32="n/a"),"n/a",(I32/SQRT(22.5*AC32*(I32/AF32))-1)*100) -> -6.0326659 | AR32: =INDEX(Historical!$C$7:$C$1045,MATCH(B32,Historical!$B$7:$B$1045,0))*IF(AH32="n/a",1.03,IF(AH32<0,1.01,IF(AH32>10,1.1,(1+AH32/100)))) -> 4.110056 | AS32: =IF($AI32="n/a",1.03*AR32,IF($AI32<0,1.01*AR32,IF($AI32>10,1.1*AR32,(1+$AI32/100)*AR32))) -> 4.4359834 | AT32: =IF($AK32="n/a",1.03*AS32,IF($AK32<0,1.01*AS32,IF($AK32>10,1.1*AS32,(1+$AK32/100)*AS32))) -> 4.8223576 | AU32: =IF($AK32="n/a",1.03*AT32,IF($AK32<0,1.01*AT32,IF($AK32>10,1.1*AT32,(1+$AK32/100)*AT32))) -> 5.2423849 | AV32: =IF($AK32="n/a",1.03*AU32,IF($AK32<0,1.01*AU32,IF($AK32>10,1.1*AU32,(1+$AK32/100)*AU32))) -> 5.6989967 | AW32: =SUM(AR32:AV32) -> 24.309779 | AX32: =AW32/I32*100 -> 7.4341831 | AY32: 0.45 | AZ32: 23.82 | BA32: -5.4 | BB32: -0.63 | BC32: 9.02 | BE32: 1994 | BF32: =IF(BE32>2020,0,IF(BE32>2008,1,IF(BE32>2001,2,IF(BE32>1990,3,IF(BE32>1980,4,IF(BE32>1973,5,IF(BE32>1970,6,IF(BE32>1960,7,IF(BE32>1958,8,IF(BE32>1953,9,10)))))))))) -> 3 | BG32: 4.72 | BH32: USD | BI32: Corp
A33: Commerce Bancshares, Inc. | B33: CBSH | C33: Financials | D33: Banks | E33: 57 | F33: 25 | G33: - | H33: - | I33: 52.03 | J33: =(M33/I33)*100 -> 2.1141649 | K33: 0.275 | L33: 4 | M33: =K33*L33 -> 1.1 | N33: C26 | O33: 0.26190476 | P33: 45723 | Q33: 45741 | R33: =(K33-O33)/O33*100 -> 5 | S33: =IF(INDEX(Historical!$D$7:$D1147,MATCH(B33,Historical!$B$7:$B$1044,0))=0,"n/a",(INDEX(Historical!$C$7:$C$1044,MATCH(B33,Historical!$B$7:$B$1044,0))/INDEX(Historical!$D$7:$D$1044,MATCH(B33,Historical!$B$7:$B$1044,0))-1)*100) -> 6.9444444 | T33: =IF(INDEX(Historical!$F$7:$F$1044,MATCH(B33,Historical!$B$7:$B$1044,0))=0,"n/a",((INDEX(Historical!$C$7:$C$1044,MATCH(B33,Historical!$B$7:$B$1044,0))/INDEX(Historical!$F$7:$F$1044,MATCH(B33,Historical!$B$7:$B$1044,0)))^(1/3)-1)*100) -> 6.3044812 | U33: =IF(INDEX(Historical!$H$7:$H$1044,MATCH(B33,Historical!$B$7:$B$1044,0))=0,"n/a",((INDEX(Historical!$C$7:$C$1044,MATCH(B33,Historical!$B$7:$B$1044,0))/INDEX(Historical!$H$7:$H$1044,MATCH(B33,Historical!$B$7:$B$1044,0)))^(1/5)-1)*100) -> 5.3860398 | V33: =IF(INDEX(Historical!$M$7:$M$1044,MATCH(B33,Historical!$B$7:$B$1044,0))=0,"n/a",((INDEX(Historical!$C$7:$C$1044,MATCH(B33,Historical!$B$7:$B$1044,0))/INDEX(Historical!$M$7:$M$1044,MATCH(B33,Historical!$B$7:$B$1044,0)))^(1/10)-1)*100) -> 8.1788042 | W33: =IF(OR(U33<=0,U33="n/a",V33<=0,V33="n/a"),"n/a",U33/V33) -> 0.65853635 | X33: =IF(OR(AJ33<=0,AJ33="n/a",U33<=0,U33="n/a"),"n/a",U33/AJ33) -> 0.44402637 | Y33: Adj/Stk Div | Z33: =IF(OR(AC33<0.01,AC33="n/a"),"n/a",M33/AC33*100) -> 27.093596 | AA33: =IF(OR(AC33<0.01,AC33="n/a"),"n/a",I33/AC33) -> 12.815271 | AB33: 12 | AC33: 4.06 | AD33: 2.17 | AE33: 3.5 | AF33: 1.77 | AG33: 14.71 | AH33: -0.14 | AI33: 8.18 | AJ33: 12.13 | AK33: 5.49 | AL33: 7640 | AM33: 3.66 | AN33: 0.6 | AO33: =IF(U33="n/a","n/a",IF(AA33<0,"n/a",IF(AA33="n/a","n/a",J33+U33-AA33))) -> -5.3150662 | AP33: =IF(U33="n/a","n/a",J33+U33) -> 7.5002047 | AQ33: =IF(OR(AC33<0.01,AC33="n/a",AF33="n/a"),"n/a",(I33/SQRT(22.5*AC33*(I33/AF33))-1)*100) -> 0.40590854 | AR33: =INDEX(Historical!$C$7:$C$1045,MATCH(B33,Historical!$B$7:$B$1045,0))*IF(AH33="n/a",1.03,IF(AH33<0,1.01,IF(AH33>10,1.1,(1+AH33/100)))) -> 1.0580952 | AS33: =IF($AI33="n/a",1.03*AR33,IF($AI33<0,1.01*AR33,IF($AI33>10,1.1*AR33,(1+$AI33/100)*AR33))) -> 1.1446474 | AT33: =IF($AK33="n/a",1.03*AS33,IF($AK33<0,1.01*AS33,IF($AK33>10,1.1*AS33,(1+$AK33/100)*AS33))) -> 1.2074886 | AU33: =IF($AK33="n/a",1.03*AT33,IF($AK33<0,1.01*AT33,IF($AK33>10,1.1*AT33,(1+$AK33/100)*AT33))) -> 1.2737797 | AV33: =IF($AK33="n/a",1.03*AU33,IF($AK33<0,1.01*AU33,IF($AK33>10,1.1*AU33,(1+$AK33/100)*AU33))) -> 1.3437102 | AW33: =SUM(AR33:AV33) -> 6.0277211 | AX33: =AW33/I33*100 -> 11.585088 | AY33: 0.6 | AZ33: 10.74 | BA33: -21.58 | BB33: 3.51 | BC33: -5.34 | BE33: 1969 | BF33: =IF(BE33>2020,0,IF(BE33>2008,1,IF(BE33>2001,2,IF(BE33>1990,3,IF(BE33>1980,4,IF(BE33>1973,5,IF(BE33>1970,6,IF(BE33>1960,7,IF(BE33>1958,8,IF(BE33>1953,9,10)))))))))) -> 7 | BG33: 1.68 | BH33: USD | BI33: Corp
A34: Community Bank System, Inc. | B34: CBU | C34: Financials | D34: Banks | E34: 34 | F34: 88 | G34: N | H34: N | I34: 63.36 | J34: =(M34/I34)*100 -> 2.9671717 | K34: 0.47 | L34: 4 | M34: =K34*L34 -> 1.88 | N34: C01 | O34: 0.46 | P34: 45912 | Q34: 45940 | R34: =(K34-O34)/O34*100 -> 2.173913 | S34: =IF(INDEX(Historical!$D$7:$D1149,MATCH(B34,Historical!$B$7:$B$1044,0))=0,"n/a",(INDEX(Historical!$C$7:$C$1044,MATCH(B34,Historical!$B$7:$B$1044,0))/INDEX(Historical!$D$7:$D$1044,MATCH(B34,Historical!$B$7:$B$1044,0))-1)*100) -> 2.2099448 | T34: =IF(INDEX(Historical!$F$7:$F$1044,MATCH(B34,Historical!$B$7:$B$1044,0))=0,"n/a",((INDEX(Historical!$C$7:$C$1044,MATCH(B34,Historical!$B$7:$B$1044,0))/INDEX(Historical!$F$7:$F$1044,MATCH(B34,Historical!$B$7:$B$1044,0)))^(1/3)-1)*100) -> 2.2606483 | U34: =IF(INDEX(Historical!$H$7:$H$1044,MATCH(B34,Historical!$B$7:$B$1044,0))=0,"n/a",((INDEX(Historical!$C$7:$C$1044,MATCH(B34,Historical!$B$7:$B$1044,0))/INDEX(Historical!$H$7:$H$1044,MATCH(B34,Historical!$B$7:$B$1044,0)))^(1/5)-1)*100) -> 2.3145873 | V34: =IF(INDEX(Historical!$M$7:$M$1044,MATCH(B34,Historical!$B$7:$B$1044,0))=0,"n/a",((INDEX(Historical!$C$7:$C$1044,MATCH(B34,Historical!$B$7:$B$1044,0))/INDEX(Historical!$M$7:$M$1044,MATCH(B34,Historical!$B$7:$B$1044,0)))^(1/10)-1)*100) -> 4.2512305 | W34: =IF(OR(U34<=0,U34="n/a",V34<=0,V34="n/a"),"n/a",U34/V34) -> 0.54445114 | X34: =IF(OR(AJ34<=0,AJ34="n/a",U34<=0,U34="n/a"),"n/a",U34/AJ34) -> 0.44511294 | Z34: =IF(OR(AC34<0.01,AC34="n/a"),"n/a",M34/AC34*100) -> 45.742092 | AA34: =IF(OR(AC34<0.01,AC34="n/a"),"n/a",I34/AC34) -> 15.416058 | AB34: 12 | AC34: 4.11 | AD34: n/a | AE34: 3.24 | AF34: 1.64 | AG34: 11.27 | AH34: 12.1 | AI34: 13.43 | AJ34: 5.2 | AK34: n/a | AL34: 3330 | AM34: 0.91 | AN34: 0.32 | AO34: =IF(U34="n/a","n/a",IF(AA34<0,"n/a",IF(AA34="n/a","n/a",J34+U34-AA34))) -> -10.134299 | AP34: =IF(U34="n/a","n/a",J34+U34) -> 5.281759 | AQ34: =IF(OR(AC34<0.01,AC34="n/a",AF34="n/a"),"n/a",(I34/SQRT(22.5*AC34*(I34/AF34))-1)*100) -> 6.0028003 | AR34: =INDEX(Historical!$C$7:$C$1045,MATCH(B34,Historical!$B$7:$B$1045,0))*IF(AH34="n/a",1.03,IF(AH34<0,1.01,IF(AH34>10,1.1,(1+AH34/100)))) -> 2.035 | AS34: =IF($AI34="n/a",1.03*AR34,IF($AI34<0,1.01*AR34,IF($AI34>10,1.1*AR34,(1+$AI34/100)*AR34))) -> 2.2385 | AT34: =IF($AK34="n/a",1.03*AS34,IF($AK34<0,1.01*AS34,IF($AK34>10,1.1*AS34,(1+$AK34/100)*AS34))) -> 2.305655 | AU34: =IF($AK34="n/a",1.03*AT34,IF($AK34<0,1.01*AT34,IF($AK34>10,1.1*AT34,(1+$AK34/100)*AT34))) -> 2.3748247 | AV34: =IF($AK34="n/a",1.03*AU34,IF($AK34<0,1.01*AU34,IF($AK34>10,1.1*AU34,(1+$AK34/100)*AU34))) -> 2.4460694 | AW34: =SUM(AR34:AV34) -> 11.400049 | AX34: =AW34/I34*100 -> 17.992502 | AY34: 0.79 | AZ34: 23.94 | BA34: -6.13 | BB34: 4.83 | BC34: 7.07 | BE34: 1993 | BF34: =IF(BE34>2020,0,IF(BE34>2008,1,IF(BE34>2001,2,IF(BE34>1990,3,IF(BE34>1980,4,IF(BE34>1973,5,IF(BE34>1970,6,IF(BE34>1960,7,IF(BE34>1958,8,IF(BE34>1953,9,10)))))))))) -> 3 | BG34: 1.26 | BH34: USD | BI34: Corp
A35: Muncy Columbia Financial Corporation | B35: CCFN | C35: Financials | D35: Banks | E35: 29 | F35: 129 | G35: Y | H35: Y | I35: 71.9 | J35: =(M35/I35)*100 -> 2.5591099 | K35: 0.46 | L35: 4 | M35: =K35*L35 -> 1.84 | N35: C15 | O35: 0.45 | P35: 46085 | Q35: 46100 | R35: =(K35-O35)/O35*100 -> 2.2222222 | S35: =IF(INDEX(Historical!$D$7:$D1151,MATCH(B35,Historical!$B$7:$B$1044,0))=0,"n/a",(INDEX(Historical!$C$7:$C$1044,MATCH(B35,Historical!$B$7:$B$1044,0))/INDEX(Historical!$D$7:$D$1044,MATCH(B35,Historical!$B$7:$B$1044,0))-1)*100) -> 2.2727273 | T35: =IF(INDEX(Historical!$F$7:$F$1044,MATCH(B35,Historical!$B$7:$B$1044,0))=0,"n/a",((INDEX(Historical!$C$7:$C$1044,MATCH(B35,Historical!$B$7:$B$1044,0))/INDEX(Historical!$F$7:$F$1044,MATCH(B35,Historical!$B$7:$B$1044,0)))^(1/3)-1)*100) -> 2.5302488 | U35: =IF(INDEX(Historical!$H$7:$H$1044,MATCH(B35,Historical!$B$7:$B$1044,0))=0,"n/a",((INDEX(Historical!$C$7:$C$1044,MATCH(B35,Historical!$B$7:$B$1044,0))/INDEX(Historical!$H$7:$H$1044,MATCH(B35,Historical!$B$7:$B$1044,0)))^(1/5)-1)*100) -> 2.5120872 | V35: =IF(INDEX(Historical!$M$7:$M$1044,MATCH(B35,Historical!$B$7:$B$1044,0))=0,"n/a",((INDEX(Historical!$C$7:$C$1044,MATCH(B35,Historical!$B$7:$B$1044,0))/INDEX(Historical!$M$7:$M$1044,MATCH(B35,Historical!$B$7:$B$1044,0)))^(1/10)-1)*100) -> 2.4720299 | W35: =IF(OR(U35<=0,U35="n/a",V35<=0,V35="n/a"),"n/a",U35/V35) -> 1.0162042 | X35: =IF(OR(AJ35<=0,AJ35="n/a",U35<=0,U35="n/a"),"n/a",U35/AJ35) -> n/a | Z35: =IF(OR(AC35<0.01,AC35="n/a"),"n/a",M35/AC35*100) -> n/a | AA35: =IF(OR(AC35<0.01,AC35="n/a"),"n/a",I35/AC35) -> n/a | AB35: 12 | AC35: n/a | AD35: n/a | AE35: n/a | AF35: n/a | AG35: n/a | AH35: n/a | AI35: n/a | AJ35: n/a | AK35: n/a | AL35: n/a | AM35: n/a | AN35: n/a | AO35: =IF(U35="n/a","n/a",IF(AA35<0,"n/a",IF(AA35="n/a","n/a",J35+U35-AA35))) -> n/a | AP35: =IF(U35="n/a","n/a",J35+U35) -> 5.0711971 | AQ35: =IF(OR(AC35<0.01,AC35="n/a",AF35="n/a"),"n/a",(I35/SQRT(22.5*AC35*(I35/AF35))-1)*100) -> n/a | AR35: =INDEX(Historical!$C$7:$C$1045,MATCH(B35,Historical!$B$7:$B$1045,0))*IF(AH35="n/a",1.03,IF(AH35<0,1.01,IF(AH35>10,1.1,(1+AH35/100)))) -> 1.854 | AS35: =IF($AI35="n/a",1.03*AR35,IF($AI35<0,1.01*AR35,IF($AI35>10,1.1*AR35,(1+$AI35/100)*AR35))) -> 1.90962 | AT35: =IF($AK35="n/a",1.03*AS35,IF($AK35<0,1.01*AS35,IF($AK35>10,1.1*AS35,(1+$AK35/100)*AS35))) -> 1.9669086 | AU35: =IF($AK35="n/a",1.03*AT35,IF($AK35<0,1.01*AT35,IF($AK35>10,1.1*AT35,(1+$AK35/100)*AT35))) -> 2.0259159 | AV35: =IF($AK35="n/a",1.03*AU35,IF($AK35<0,1.01*AU35,IF($AK35>10,1.1*AU35,(1+$AK35/100)*AU35))) -> 2.0866933 | AW35: =SUM(AR35:AV35) -> 9.8431378 | AX35: =AW35/I35*100 -> 13.690039 | AY35: n/a | AZ35: n/a | BA35: n/a | BB35: n/a | BC35: n/a | BD35: OTC | BE35: 1998 | BF35: =IF(BE35>2020,0,IF(BE35>2008,1,IF(BE35>2001,2,IF(BE35>1990,3,IF(BE35>1980,4,IF(BE35>1973,5,IF(BE35>1970,6,IF(BE35>1960,7,IF(BE35>1958,8,IF(BE35>1953,9,10)))))))))) -> 3 | BG35: n/a | BH35: USD | BI35: Corp
A36: Cullen/Frost Bankers, Inc. | B36: CFR | C36: Financials | D36: Banks | E36: 33 | F36: 104 | G36: - | H36: - | I36: 144.93 | J36: =(M36/I36)*100 -> 2.8427517 | K36: 1.03 | L36: 4 | M36: =K36*L36 -> 4.12 | N36: C15 | O36: 1 | P36: 46171 | Q36: 46188 | R36: =(K36-O36)/O36*100 -> 3 | S36: =IF(INDEX(Historical!$D$7:$D1155,MATCH(B36,Historical!$B$7:$B$1044,0))=0,"n/a",(INDEX(Historical!$C$7:$C$1044,MATCH(B36,Historical!$B$7:$B$1044,0))/INDEX(Historical!$D$7:$D$1044,MATCH(B36,Historical!$B$7:$B$1044,0))-1)*100) -> 5.6149733 | T36: =IF(INDEX(Historical!$F$7:$F$1044,MATCH(B36,Historical!$B$7:$B$1044,0))=0,"n/a",((INDEX(Historical!$C$7:$C$1044,MATCH(B36,Historical!$B$7:$B$1044,0))/INDEX(Historical!$F$7:$F$1044,MATCH(B36,Historical!$B$7:$B$1044,0)))^(1/3)-1)*100) -> 6.827737 | U36: =IF(INDEX(Historical!$H$7:$H$1044,MATCH(B36,Historical!$B$7:$B$1044,0))=0,"n/a",((INDEX(Historical!$C$7:$C$1044,MATCH(B36,Historical!$B$7:$B$1044,0))/INDEX(Historical!$H$7:$H$1044,MATCH(B36,Historical!$B$7:$B$1044,0)))^(1/5)-1)*100) -> 6.7457142 | V36: =IF(INDEX(Historical!$M$7:$M$1044,MATCH(B36,Historical!$B$7:$B$1044,0))=0,"n/a",((INDEX(Historical!$C$7:$C$1044,MATCH(B36,Historical!$B$7:$B$1044,0))/INDEX(Historical!$M$7:$M$1044,MATCH(B36,Historical!$B$7:$B$1044,0)))^(1/10)-1)*100) -> 6.5216243 | W36: =IF(OR(U36<=0,U36="n/a",V36<=0,V36="n/a"),"n/a",U36/V36) -> 1.0343611 | X36: =IF(OR(AJ36<=0,AJ36="n/a",U36<=0,U36="n/a"),"n/a",U36/AJ36) -> 0.47238895 | Z36: =IF(OR(AC36<0.01,AC36="n/a"),"n/a",M36/AC36*100) -> 41.532258 | AA36: =IF(OR(AC36<0.01,AC36="n/a"),"n/a",I36/AC36) -> 14.609879 | AB36: 12 | AC36: 9.92 | AD36: 2.75 | AE36: 3.13 | AF36: 2.07 | AG36: 15.16 | AH36: 4.3 | AI36: 3.83 | AJ36: 14.28 | AK36: 4.91 | AL36: 9130 | AM36: 6.33 | AN36: 1.12 | AO36: =IF(U36="n/a","n/a",IF(AA36<0,"n/a",IF(AA36="n/a","n/a",J36+U36-AA36))) -> -5.0214132 | AP36: =IF(U36="n/a","n/a",J36+U36) -> 9.5884658 | AQ36: =IF(OR(AC36<0.01,AC36="n/a",AF36="n/a"),"n/a",(I36/SQRT(22.5*AC36*(I36/AF36))-1)*100) -> 15.935709 | AR36: =INDEX(Historical!$C$7:$C$1045,MATCH(B36,Historical!$B$7:$B$1045,0))*IF(AH36="n/a",1.03,IF(AH36<0,1.01,IF(AH36>10,1.1,(1+AH36/100)))) -> 4.11985 | AS36: =IF($AI36="n/a",1.03*AR36,IF($AI36<0,1.01*AR36,IF($AI36>10,1.1*AR36,(1+$AI36/100)*AR36))) -> 4.2776403 | AT36: =IF($AK36="n/a",1.03*AS36,IF($AK36<0,1.01*AS36,IF($AK36>10,1.1*AS36,(1+$AK36/100)*AS36))) -> 4.4876724 | AU36: =IF($AK36="n/a",1.03*AT36,IF($AK36<0,1.01*AT36,IF($AK36>10,1.1*AT36,(1+$AK36/100)*AT36))) -> 4.7080171 | AV36: =IF($AK36="n/a",1.03*AU36,IF($AK36<0,1.01*AU36,IF($AK36>10,1.1*AU36,(1+$AK36/100)*AU36))) -> 4.9391807 | AW36: =SUM(AR36:AV36) -> 22.53236 | AX36: =AW36/I36*100 -> 15.547064 | AY36: 0.57 | AZ36: 26.81 | BA36: -2.71 | BB36: 4.23 | BC36: 9.77 | BE36: 1994 | BF36: =IF(BE36>2020,0,IF(BE36>2008,1,IF(BE36>2001,2,IF(BE36>1990,3,IF(BE36>1980,4,IF(BE36>1973,5,IF(BE36>1970,6,IF(BE36>1960,7,IF(BE36>1958,8,IF(BE36>1953,9,10)))))))))) -> 3 | BG36: 1.22 | BH36: USD | BI36: Corp
A37: Church & Dwight Co., Inc. | B37: CHD | C37: Consumer Staples | D37: Household Products | E37: 30 | F37: 124 | G37: Y | H37: Y | I37: 97.06 | J37: =(M37/I37)*100 -> 1.2672574 | K37: 0.3075 | L37: 4 | M37: =K37*L37 -> 1.23 | N37: C01 | O37: 0.295 | P37: 46066 | Q37: 46083 | R37: =(K37-O37)/O37*100 -> 4.2372881 | S37: =IF(INDEX(Historical!$D$7:$D1159,MATCH(B37,Historical!$B$7:$B$1044,0))=0,"n/a",(INDEX(Historical!$C$7:$C$1044,MATCH(B37,Historical!$B$7:$B$1044,0))/INDEX(Historical!$D$7:$D$1044,MATCH(B37,Historical!$B$7:$B$1044,0))-1)*100) -> 3.9647577 | T37: =IF(INDEX(Historical!$F$7:$F$1044,MATCH(B37,Historical!$B$7:$B$1044,0))=0,"n/a",((INDEX(Historical!$C$7:$C$1044,MATCH(B37,Historical!$B$7:$B$1044,0))/INDEX(Historical!$F$7:$F$1044,MATCH(B37,Historical!$B$7:$B$1044,0)))^(1/3)-1)*100) -> 3.9674924 | U37: =IF(INDEX(Historical!$H$7:$H$1044,MATCH(B37,Historical!$B$7:$B$1044,0))=0,"n/a",((INDEX(Historical!$C$7:$C$1044,MATCH(B37,Historical!$B$7:$B$1044,0))/INDEX(Historical!$H$7:$H$1044,MATCH(B37,Historical!$B$7:$B$1044,0)))^(1/5)-1)*100) -> 4.2130616 | V37: =IF(INDEX(Historical!$M$7:$M$1044,MATCH(B37,Historical!$B$7:$B$1044,0))=0,"n/a",((INDEX(Historical!$C$7:$C$1044,MATCH(B37,Historical!$B$7:$B$1044,0))/INDEX(Historical!$M$7:$M$1044,MATCH(B37,Historical!$B$7:$B$1044,0)))^(1/10)-1)*100) -> 5.8231587 | W37: =IF(OR(U37<=0,U37="n/a",V37<=0,V37="n/a"),"n/a",U37/V37) -> 0.72350108 | X37: =IF(OR(AJ37<=0,AJ37="n/a",U37<=0,U37="n/a"),"n/a",U37/AJ37) -> n/a | Z37: =IF(OR(AC37<0.01,AC37="n/a"),"n/a",M37/AC37*100) -> 40.863787 | AA37: =IF(OR(AC37<0.01,AC37="n/a"),"n/a",I37/AC37) -> 32.245847 | AB37: 12 | AC37: 3.01 | AD37: 3.58 | AE37: 3.71 | AF37: 5.74 | AG37: 17.62 | AH37: 6.35 | AI37: 6.66 | AJ37: -0.65 | AK37: 6.77 | AL37: 22990 | AM37: 0.22 | AN37: 0.6 | AO37: =IF(U37="n/a","n/a",IF(AA37<0,"n/a",IF(AA37="n/a","n/a",J37+U37-AA37))) -> -26.765528 | AP37: =IF(U37="n/a","n/a",J37+U37) -> 5.480319 | AQ37: =IF(OR(AC37<0.01,AC37="n/a",AF37="n/a"),"n/a",(I37/SQRT(22.5*AC37*(I37/AF37))-1)*100) -> 186.81482 | AR37: =INDEX(Historical!$C$7:$C$1045,MATCH(B37,Historical!$B$7:$B$1045,0))*IF(AH37="n/a",1.03,IF(AH37<0,1.01,IF(AH37>10,1.1,(1+AH37/100)))) -> 1.25493 | AS37: =IF($AI37="n/a",1.03*AR37,IF($AI37<0,1.01*AR37,IF($AI37>10,1.1*AR37,(1+$AI37/100)*AR37))) -> 1.3385083 | AT37: =IF($AK37="n/a",1.03*AS37,IF($AK37<0,1.01*AS37,IF($AK37>10,1.1*AS37,(1+$AK37/100)*AS37))) -> 1.4291254 | AU37: =IF($AK37="n/a",1.03*AT37,IF($AK37<0,1.01*AT37,IF($AK37>10,1.1*AT37,(1+$AK37/100)*AT37))) -> 1.5258771 | AV37: =IF($AK37="n/a",1.03*AU37,IF($AK37<0,1.01*AU37,IF($AK37>10,1.1*AU37,(1+$AK37/100)*AU37))) -> 1.629179 | AW37: =SUM(AR37:AV37) -> 7.1776199 | AX37: =AW37/I37*100 -> 7.3950338 | AY37: 0.48 | AZ37: 19.34 | BA37: -8.47 | BB37: -0.33 | BC37: 5.83 | BE37: 1997 | BF37: =IF(BE37>2020,0,IF(BE37>2008,1,IF(BE37>2001,2,IF(BE37>1990,3,IF(BE37>1980,4,IF(BE37>1973,5,IF(BE37>1970,6,IF(BE37>1960,7,IF(BE37>1958,8,IF(BE37>1953,9,10)))))))))) -> 3 | BG37: 8.28 | BH37: USD | BI37: Corp
A38: C.H. Robinson Worldwide, Inc. | B38: CHRW | C38: Industrials | D38: Air Freight & Logistics | E38: 27 | F38: 139 | G38: - | H38: - | I38: 181.81 | J38: =(M38/I38)*100 -> 1.3860624 | K38: 0.63 | L38: 4 | M38: =K38*L38 -> 2.52 | N38: C29 | O38: 0.62 | P38: 45996 | Q38: 46027 | R38: =(K38-O38)/O38*100 -> 1.6129032 | S38: =IF(INDEX(Historical!$D$7:$D1162,MATCH(B38,Historical!$B$7:$B$1044,0))=0,"n/a",(INDEX(Historical!$C$7:$C$1044,MATCH(B38,Historical!$B$7:$B$1044,0))/INDEX(Historical!$D$7:$D$1044,MATCH(B38,Historical!$B$7:$B$1044,0))-1)*100) -> 1.2244898 | T38: =IF(INDEX(Historical!$F$7:$F$1044,MATCH(B38,Historical!$B$7:$B$1044,0))=0,"n/a",((INDEX(Historical!$C$7:$C$1044,MATCH(B38,Historical!$B$7:$B$1044,0))/INDEX(Historical!$F$7:$F$1044,MATCH(B38,Historical!$B$7:$B$1044,0)))^(1/3)-1)*100) -> 4.0741805 | U38: =IF(INDEX(Historical!$H$7:$H$1044,MATCH(B38,Historical!$B$7:$B$1044,0))=0,"n/a",((INDEX(Historical!$C$7:$C$1044,MATCH(B38,Historical!$B$7:$B$1044,0))/INDEX(Historical!$H$7:$H$1044,MATCH(B38,Historical!$B$7:$B$1044,0)))^(1/5)-1)*100) -> 3.9834692 | V38: =IF(INDEX(Historical!$M$7:$M$1044,MATCH(B38,Historical!$B$7:$B$1044,0))=0,"n/a",((INDEX(Historical!$C$7:$C$1044,MATCH(B38,Historical!$B$7:$B$1044,0))/INDEX(Historical!$M$7:$M$1044,MATCH(B38,Historical!$B$7:$B$1044,0)))^(1/10)-1)*100) -> 4.6779485 | W38: =IF(OR(U38<=0,U38="n/a",V38<=0,V38="n/a"),"n/a",U38/V38) -> 0.8515419 | X38: =IF(OR(AJ38<=0,AJ38="n/a",U38<=0,U38="n/a"),"n/a",U38/AJ38) -> 0.74042178 | Y38: Rec Date Streak | Z38: =IF(OR(AC38<0.01,AC38="n/a"),"n/a",M38/AC38*100) -> 51.012146 | AA38: =IF(OR(AC38<0.01,AC38="n/a"),"n/a",I38/AC38) -> 36.803644 | AB38: 12 | AC38: 4.94 | AD38: 1.58 | AE38: 1.32 | AF38: 11.67 | AG38: 34.84 | AH38: 20.85 | AI38: 18.23 | AJ38: 5.38 | AK38: 15.8 | AL38: 21430 | AM38: 0.69 | AN38: 0.97 | AO38: =IF(U38="n/a","n/a",IF(AA38<0,"n/a",IF(AA38="n/a","n/a",J38+U38-AA38))) -> -31.434112 | AP38: =IF(U38="n/a","n/a",J38+U38) -> 5.3695316 | AQ38: =IF(OR(AC38<0.01,AC38="n/a",AF38="n/a"),"n/a",(I38/SQRT(22.5*AC38*(I38/AF38))-1)*100) -> 336.90758 | AR38: =INDEX(Historical!$C$7:$C$1045,MATCH(B38,Historical!$B$7:$B$1045,0))*IF(AH38="n/a",1.03,IF(AH38<0,1.01,IF(AH38>10,1.1,(1+AH38/100)))) -> 2.728 | AS38: =IF($AI38="n/a",1.03*AR38,IF($AI38<0,1.01*AR38,IF($AI38>10,1.1*AR38,(1+$AI38/100)*AR38))) -> 3.0008 | AT38: =IF($AK38="n/a",1.03*AS38,IF($AK38<0,1.01*AS38,IF($AK38>10,1.1*AS38,(1+$AK38/100)*AS38))) -> 3.30088 | AU38: =IF($AK38="n/a",1.03*AT38,IF($AK38<0,1.01*AT38,IF($AK38>10,1.1*AT38,(1+$AK38/100)*AT38))) -> 3.630968 | AV38: =IF($AK38="n/a",1.03*AU38,IF($AK38<0,1.01*AU38,IF($AK38>10,1.1*AU38,(1+$AK38/100)*AU38))) -> 3.9940648 | AW38: =SUM(AR38:AV38) -> 16.654713 | AX38: =AW38/I38*100 -> 9.1605043 | AY38: 0.97 | AZ38: 109.99 | BA38: -10.59 | BB38: 3.2 | BC38: 18.85 | BE38: 1999 | BF38: =IF(BE38>2020,0,IF(BE38>2008,1,IF(BE38>2001,2,IF(BE38>1990,3,IF(BE38>1980,4,IF(BE38>1973,5,IF(BE38>1970,6,IF(BE38>1960,7,IF(BE38>1958,8,IF(BE38>1953,9,10)))))))))) -> 3 | BG38: 11.45 | BH38: USD | BI38: Corp
A39: Cincinnati Financial Corporation | B39: CINF | C39: Financials | D39: Insurance | E39: 66 | F39: 8 | G39: N | H39: N | I39: 163.6 | J39: =(M39/I39)*100 -> 2.2982885 | K39: 0.94 | L39: 4 | M39: =K39*L39 -> 3.76 | N39: A16 | O39: 0.87 | P39: 46105 | Q39: 46127 | R39: =(K39-O39)/O39*100 -> 8.045977 | S39: =IF(INDEX(Historical!$D$7:$D1163,MATCH(B39,Historical!$B$7:$B$1044,0))=0,"n/a",(INDEX(Historical!$C$7:$C$1044,MATCH(B39,Historical!$B$7:$B$1044,0))/INDEX(Historical!$D$7:$D$1044,MATCH(B39,Historical!$B$7:$B$1044,0))-1)*100) -> 7.5471698 | T39: =IF(INDEX(Historical!$F$7:$F$1044,MATCH(B39,Historical!$B$7:$B$1044,0))=0,"n/a",((INDEX(Historical!$C$7:$C$1044,MATCH(B39,Historical!$B$7:$B$1044,0))/INDEX(Historical!$F$7:$F$1044,MATCH(B39,Historical!$B$7:$B$1044,0)))^(1/3)-1)*100) -> 8.1983856 | U39: =IF(INDEX(Historical!$H$7:$H$1044,MATCH(B39,Historical!$B$7:$B$1044,0))=0,"n/a",((INDEX(Historical!$C$7:$C$1044,MATCH(B39,Historical!$B$7:$B$1044,0))/INDEX(Historical!$H$7:$H$1044,MATCH(B39,Historical!$B$7:$B$1044,0)))^(1/5)-1)*100) -> 7.701765 | V39: =IF(INDEX(Historical!$M$7:$M$1044,MATCH(B39,Historical!$B$7:$B$1044,0))=0,"n/a",((INDEX(Historical!$C$7:$C$1044,MATCH(B39,Historical!$B$7:$B$1044,0))/INDEX(Historical!$M$7:$M$1044,MATCH(B39,Historical!$B$7:$B$1044,0)))^(1/10)-1)*100) -> 6.5112476 | W39: =IF(OR(U39<=0,U39="n/a",V39<=0,V39="n/a"),"n/a",U39/V39) -> 1.1828401 | X39: =IF(OR(AJ39<=0,AJ39="n/a",U39<=0,U39="n/a"),"n/a",U39/AJ39) -> 0.5076971 | Z39: =IF(OR(AC39<0.01,AC39="n/a"),"n/a",M39/AC39*100) -> 24.785761 | AA39: =IF(OR(AC39<0.01,AC39="n/a"),"n/a",I39/AC39) -> 10.784443 | AB39: 12 | AC39: 15.17 | AD39: n/a | AE39: 2 | AF39: 1.6 | AG39: 16.04 | AH39: 9.08 | AI39: 4.83 | AJ39: 15.17 | AK39: n/a | AL39: 25310 | AM39: 1.98 | AN39: 0.06 | AO39: =IF(U39="n/a","n/a",IF(AA39<0,"n/a",IF(AA39="n/a","n/a",J39+U39-AA39))) -> -0.78438944 | AP39: =IF(U39="n/a","n/a",J39+U39) -> 10.000054 | AQ39: =IF(OR(AC39<0.01,AC39="n/a",AF39="n/a"),"n/a",(I39/SQRT(22.5*AC39*(I39/AF39))-1)*100) -> -12.427532 | AR39: =INDEX(Historical!$C$7:$C$1045,MATCH(B39,Historical!$B$7:$B$1045,0))*IF(AH39="n/a",1.03,IF(AH39<0,1.01,IF(AH39>10,1.1,(1+AH39/100)))) -> 3.730536 | AS39: =IF($AI39="n/a",1.03*AR39,IF($AI39<0,1.01*AR39,IF($AI39>10,1.1*AR39,(1+$AI39/100)*AR39))) -> 3.9107209 | AT39: =IF($AK39="n/a",1.03*AS39,IF($AK39<0,1.01*AS39,IF($AK39>10,1.1*AS39,(1+$AK39/100)*AS39))) -> 4.0280425 | AU39: =IF($AK39="n/a",1.03*AT39,IF($AK39<0,1.01*AT39,IF($AK39>10,1.1*AT39,(1+$AK39/100)*AT39))) -> 4.1488838 | AV39: =IF($AK39="n/a",1.03*AU39,IF($AK39<0,1.01*AU39,IF($AK39>10,1.1*AU39,(1+$AK39/100)*AU39))) -> 4.2733503 | AW39: =SUM(AR39:AV39) -> 20.091533 | AX39: =AW39/I39*100 -> 12.280888 | AY39: 0.6 | AZ39: 20.42 | BA39: -6.12 | BB39: 0.51 | BC39: 2.39 | BE39: 1961 | BF39: =IF(BE39>2020,0,IF(BE39>2008,1,IF(BE39>2001,2,IF(BE39>1990,3,IF(BE39>1980,4,IF(BE39>1973,5,IF(BE39>1970,6,IF(BE39>1960,7,IF(BE39>1958,8,IF(BE39>1953,9,10)))))))))) -> 7 | BG39: 6.21 | BH39: USD | BI39: Corp
A40: Colgate-Palmolive Company | B40: CL | C40: Consumer Staples | D40: Household Products | E40: 63 | F40: 14 | G40: Y | H40: Y | I40: 85.36 | J40: =(M40/I40)*100 -> 2.4835989 | K40: 0.53 | L40: 4 | M40: =K40*L40 -> 2.12 | N40: B15 | O40: 0.52 | P40: 46132 | Q40: 46157 | R40: =(K40-O40)/O40*100 -> 1.9230769 | S40: =IF(INDEX(Historical!$D$7:$D1165,MATCH(B40,Historical!$B$7:$B$1044,0))=0,"n/a",(INDEX(Historical!$C$7:$C$1044,MATCH(B40,Historical!$B$7:$B$1044,0))/INDEX(Historical!$D$7:$D$1044,MATCH(B40,Historical!$B$7:$B$1044,0))-1)*100) -> 4.040404 | T40: =IF(INDEX(Historical!$F$7:$F$1044,MATCH(B40,Historical!$B$7:$B$1044,0))=0,"n/a",((INDEX(Historical!$C$7:$C$1044,MATCH(B40,Historical!$B$7:$B$1044,0))/INDEX(Historical!$F$7:$F$1044,MATCH(B40,Historical!$B$7:$B$1044,0)))^(1/3)-1)*100) -> 3.4629266 | U40: =IF(INDEX(Historical!$H$7:$H$1044,MATCH(B40,Historical!$B$7:$B$1044,0))=0,"n/a",((INDEX(Historical!$C$7:$C$1044,MATCH(B40,Historical!$B$7:$B$1044,0))/INDEX(Historical!$H$7:$H$1044,MATCH(B40,Historical!$B$7:$B$1044,0)))^(1/5)-1)*100) -> 3.3155839 | V40: =IF(INDEX(Historical!$M$7:$M$1044,MATCH(B40,Historical!$B$7:$B$1044,0))=0,"n/a",((INDEX(Historical!$C$7:$C$1044,MATCH(B40,Historical!$B$7:$B$1044,0))/INDEX(Historical!$M$7:$M$1044,MATCH(B40,Historical!$B$7:$B$1044,0)))^(1/10)-1)*100) -> 3.223266 | W40: =IF(OR(U40<=0,U40="n/a",V40<=0,V40="n/a"),"n/a",U40/V40) -> 1.0286411 | X40: =IF(OR(AJ40<=0,AJ40="n/a",U40<=0,U40="n/a"),"n/a",U40/AJ40) -> n/a | Z40: =IF(OR(AC40<0.01,AC40="n/a"),"n/a",M40/AC40*100) -> 80.916031 | AA40: =IF(OR(AC40<0.01,AC40="n/a"),"n/a",I40/AC40) -> 32.580153 | AB40: 12 | AC40: 2.62 | AD40: 3.84 | AE40: 3.36 | AF40: 1266.47 | AG40: 1602.26 | AH40: 3.47 | AI40: 5.97 | AJ40: -3.47 | AK40: 5.5 | AL40: 68480 | AM40: 0.19 | AN40: 158.41 | AO40: =IF(U40="n/a","n/a",IF(AA40<0,"n/a",IF(AA40="n/a","n/a",J40+U40-AA40))) -> -26.78097 | AP40: =IF(U40="n/a","n/a",J40+U40) -> 5.7991827 | AQ40: =IF(OR(AC40<0.01,AC40="n/a",AF40="n/a"),"n/a",(I40/SQRT(22.5*AC40*(I40/AF40))-1)*100) -> 4182.3558 | AR40: =INDEX(Historical!$C$7:$C$1045,MATCH(B40,Historical!$B$7:$B$1045,0))*IF(AH40="n/a",1.03,IF(AH40<0,1.01,IF(AH40>10,1.1,(1+AH40/100)))) -> 2.131482 | AS40: =IF($AI40="n/a",1.03*AR40,IF($AI40<0,1.01*AR40,IF($AI40>10,1.1*AR40,(1+$AI40/100)*AR40))) -> 2.2587315 | AT40: =IF($AK40="n/a",1.03*AS40,IF($AK40<0,1.01*AS40,IF($AK40>10,1.1*AS40,(1+$AK40/100)*AS40))) -> 2.3829617 | AU40: =IF($AK40="n/a",1.03*AT40,IF($AK40<0,1.01*AT40,IF($AK40>10,1.1*AT40,(1+$AK40/100)*AT40))) -> 2.5140246 | AV40: =IF($AK40="n/a",1.03*AU40,IF($AK40<0,1.01*AU40,IF($AK40>10,1.1*AU40,(1+$AK40/100)*AU40))) -> 2.652296 | AW40: =SUM(AR40:AV40) -> 11.939496 | AX40: =AW40/I40*100 -> 13.987226 | AY40: 0.3 | AZ40: 14.51 | BA40: -14.06 | BB40: -3.17 | BC40: 1.78 | BE40: 1964 | BF40: =IF(BE40>2020,0,IF(BE40>2008,1,IF(BE40>2001,2,IF(BE40>1990,3,IF(BE40>1980,4,IF(BE40>1973,5,IF(BE40>1970,6,IF(BE40>1960,7,IF(BE40>1958,8,IF(BE40>1953,9,10)))))))))) -> 7 | BG40: 13.16 | BH40: USD | BI40: Corp
A41: The Clorox Company | B41: CLX | C41: Consumer Staples | D41: Household Products | E41: 48 | F41: 56 | G41: N | H41: Y | I41: 96.44 | J41: =(M41/I41)*100 -> 5.1430942 | K41: 1.24 | L41: 4 | M41: =K41*L41 -> 4.96 | N41: B11 | O41: 1.24 | P41: 45882 | Q41: 45898 | R41: =(K41-O41)/O41*100 -> 0 | S41: =IF(INDEX(Historical!$D$7:$D1166,MATCH(B41,Historical!$B$7:$B$1044,0))=0,"n/a",(INDEX(Historical!$C$7:$C$1044,MATCH(B41,Historical!$B$7:$B$1044,0))/INDEX(Historical!$D$7:$D$1044,MATCH(B41,Historical!$B$7:$B$1044,0))-1)*100) -> 1.6528926 | T41: =IF(INDEX(Historical!$F$7:$F$1044,MATCH(B41,Historical!$B$7:$B$1044,0))=0,"n/a",((INDEX(Historical!$C$7:$C$1044,MATCH(B41,Historical!$B$7:$B$1044,0))/INDEX(Historical!$F$7:$F$1044,MATCH(B41,Historical!$B$7:$B$1044,0)))^(1/3)-1)*100) -> 1.6809862 | U41: =IF(INDEX(Historical!$H$7:$H$1044,MATCH(B41,Historical!$B$7:$B$1044,0))=0,"n/a",((INDEX(Historical!$C$7:$C$1044,MATCH(B41,Historical!$B$7:$B$1044,0))/INDEX(Historical!$H$7:$H$1044,MATCH(B41,Historical!$B$7:$B$1044,0)))^(1/5)-1)*100) -> 2.5404159 | V41: =IF(INDEX(Historical!$M$7:$M$1044,MATCH(B41,Historical!$B$7:$B$1044,0))=0,"n/a",((INDEX(Historical!$C$7:$C$1044,MATCH(B41,Historical!$B$7:$B$1044,0))/INDEX(Historical!$M$7:$M$1044,MATCH(B41,Historical!$B$7:$B$1044,0)))^(1/10)-1)*100) -> 5.0015756 | W41: =IF(OR(U41<=0,U41="n/a",V41<=0,V41="n/a"),"n/a",U41/V41) -> 0.50792312 | X41: =IF(OR(AJ41<=0,AJ41="n/a",U41<=0,U41="n/a"),"n/a",U41/AJ41) -> n/a | Z41: =IF(OR(AC41<0.01,AC41="n/a"),"n/a",M41/AC41*100) -> 81.045752 | AA41: =IF(OR(AC41<0.01,AC41="n/a"),"n/a",I41/AC41) -> 15.75817 | AB41: 6 | AC41: 6.12 | AD41: n/a | AE41: 1.73 | AF41: n/a | AG41: 4163.16 | AH41: -24.01 | AI41: 12.57 | AJ41: -2.39 | AK41: -3.04 | AL41: 11660 | AM41: 0.64 | AN41: n/a | AO41: =IF(U41="n/a","n/a",IF(AA41<0,"n/a",IF(AA41="n/a","n/a",J41+U41-AA41))) -> -8.0746599 | AP41: =IF(U41="n/a","n/a",J41+U41) -> 7.6835101 | AQ41: =IF(OR(AC41<0.01,AC41="n/a",AF41="n/a"),"n/a",(I41/SQRT(22.5*AC41*(I41/AF41))-1)*100) -> n/a | AR41: =INDEX(Historical!$C$7:$C$1045,MATCH(B41,Historical!$B$7:$B$1045,0))*IF(AH41="n/a",1.03,IF(AH41<0,1.01,IF(AH41>10,1.1,(1+AH41/100)))) -> 4.9692 | AS41: =IF($AI41="n/a",1.03*AR41,IF($AI41<0,1.01*AR41,IF($AI41>10,1.1*AR41,(1+$AI41/100)*AR41))) -> 5.46612 | AT41: =IF($AK41="n/a",1.03*AS41,IF($AK41<0,1.01*AS41,IF($AK41>10,1.1*AS41,(1+$AK41/100)*AS41))) -> 5.5207812 | AU41: =IF($AK41="n/a",1.03*AT41,IF($AK41<0,1.01*AT41,IF($AK41>10,1.1*AT41,(1+$AK41/100)*AT41))) -> 5.575989 | AV41: =IF($AK41="n/a",1.03*AU41,IF($AK41<0,1.01*AU41,IF($AK41>10,1.1*AU41,(1+$AK41/100)*AU41))) -> 5.6317489 | AW41: =SUM(AR41:AV41) -> 27.163839 | AX41: =AW41/I41*100 -> 28.166569 | AY41: 0.58 | AZ41: 3.27 | BA41: -32.27 | BB41: -11.22 | BC41: -14.96 | BE41: 1978 | BF41: =IF(BE41>2020,0,IF(BE41>2008,1,IF(BE41>2001,2,IF(BE41>1990,3,IF(BE41>1980,4,IF(BE41>1973,5,IF(BE41>1970,6,IF(BE41>1960,7,IF(BE41>1958,8,IF(BE41>1953,9,10)))))))))) -> 5 | BG41: 13.49 | BH41: USD | BI41: Corp
A42: Canadian National Railway Company | B42: CNI | C42: Industrials | D42: Road & Rail | E42: 31 | F42: 120 | G42: - | H42: - | I42: 112.13 | J42: =(M42/I42)*100 -> 2.38277 | K42: 0.66795 | L42: 4 | M42: =K42*L42 -> 2.6718 | N42: C29 | O42: 0.6124 | P42: 46091 | Q42: 46112 | R42: =(K42-O42)/O42*100 -> 9.0708687 | S42: =IF(INDEX(Historical!$D$7:$D1173,MATCH(B42,Historical!$B$7:$B$1044,0))=0,"n/a",(INDEX(Historical!$C$7:$C$1044,MATCH(B42,Historical!$B$7:$B$1044,0))/INDEX(Historical!$D$7:$D$1044,MATCH(B42,Historical!$B$7:$B$1044,0))-1)*100) -> 2.5522979 | T42: =IF(INDEX(Historical!$F$7:$F$1044,MATCH(B42,Historical!$B$7:$B$1044,0))=0,"n/a",((INDEX(Historical!$C$7:$C$1044,MATCH(B42,Historical!$B$7:$B$1044,0))/INDEX(Historical!$F$7:$F$1044,MATCH(B42,Historical!$B$7:$B$1044,0)))^(1/3)-1)*100) -> 4.1095251 | U42: =IF(INDEX(Historical!$H$7:$H$1044,MATCH(B42,Historical!$B$7:$B$1044,0))=0,"n/a",((INDEX(Historical!$C$7:$C$1044,MATCH(B42,Historical!$B$7:$B$1044,0))/INDEX(Historical!$H$7:$H$1044,MATCH(B42,Historical!$B$7:$B$1044,0)))^(1/5)-1)*100) -> 8.1389248 | V42: =IF(INDEX(Historical!$M$7:$M$1044,MATCH(B42,Historical!$B$7:$B$1044,0))=0,"n/a",((INDEX(Historical!$C$7:$C$1044,MATCH(B42,Historical!$B$7:$B$1044,0))/INDEX(Historical!$M$7:$M$1044,MATCH(B42,Historical!$B$7:$B$1044,0)))^(1/10)-1)*100) -> 9.9259932 | W42: =IF(OR(U42<=0,U42="n/a",V42<=0,V42="n/a"),"n/a",U42/V42) -> 0.81996074 | X42: =IF(OR(AJ42<=0,AJ42="n/a",U42<=0,U42="n/a"),"n/a",U42/AJ42) -> 1.0542649 | Y42: @,Canada | Z42: =IF(OR(AC42<0.01,AC42="n/a"),"n/a",M42/AC42*100) -> 48.666667 | AA42: =IF(OR(AC42<0.01,AC42="n/a"),"n/a",I42/AC42) -> 20.424408 | AB42: 12 | AC42: 5.49 | AD42: 2.2 | AE42: 5.48 | AF42: 4.43 | AG42: 22.4 | AH42: 2.99 | AI42: 11.1 | AJ42: 7.72 | AK42: 7.98 | AL42: 68560 | AM42: 3.3 | AN42: 1.05 | AO42: =IF(U42="n/a","n/a",IF(AA42<0,"n/a",IF(AA42="n/a","n/a",J42+U42-AA42))) -> -9.9027132 | AP42: =IF(U42="n/a","n/a",J42+U42) -> 10.521695 | AQ42: =IF(OR(AC42<0.01,AC42="n/a",AF42="n/a"),"n/a",(I42/SQRT(22.5*AC42*(I42/AF42))-1)*100) -> 100.53277 | AR42: =INDEX(Historical!$C$7:$C$1045,MATCH(B42,Historical!$B$7:$B$1045,0))*IF(AH42="n/a",1.03,IF(AH42<0,1.01,IF(AH42>10,1.1,(1+AH42/100)))) -> 2.6153281 | AS42: =IF($AI42="n/a",1.03*AR42,IF($AI42<0,1.01*AR42,IF($AI42>10,1.1*AR42,(1+$AI42/100)*AR42))) -> 2.8768609 | AT42: =IF($AK42="n/a",1.03*AS42,IF($AK42<0,1.01*AS42,IF($AK42>10,1.1*AS42,(1+$AK42/100)*AS42))) -> 3.1064344 | AU42: =IF($AK42="n/a",1.03*AT42,IF($AK42<0,1.01*AT42,IF($AK42>10,1.1*AT42,(1+$AK42/100)*AT42))) -> 3.3543278 | AV42: =IF($AK42="n/a",1.03*AU42,IF($AK42<0,1.01*AU42,IF($AK42>10,1.1*AU42,(1+$AK42/100)*AU42))) -> 3.6220032 | AW42: =SUM(AR42:AV42) -> 15.574954 | AX42: =AW42/I42*100 -> 13.890087 | AY42: 0.94 | AZ42: 23.57 | BA42: -3.17 | BB42: 4.24 | BC42: 12.81 | BE42: 1998 | BF42: =IF(BE42>2020,0,IF(BE42>2008,1,IF(BE42>2001,2,IF(BE42>1990,3,IF(BE42>1980,4,IF(BE42>1973,5,IF(BE42>1970,6,IF(BE42>1960,7,IF(BE42>1958,8,IF(BE42>1953,9,10)))))))))) -> 3 | BG42: 8.25 | BH42: CAD | BI42: Corp
A43: Chesapeake Financial Shares, Inc. | B43: CPKF | C43: Financials | D43: Banks | E43: 35 | F43: 87 | G43: - | H43: - | I43: 34.5 | J43: =(M43/I43)*100 -> 2.0869565 | K43: 0.18 | L43: 4 | M43: =K43*L43 -> 0.72 | N43: C15 | O43: 0.17 | P43: 46174 | Q43: 46188 | R43: =(K43-O43)/O43*100 -> 5.8823529 | S43: =IF(INDEX(Historical!$D$7:$D1182,MATCH(B43,Historical!$B$7:$B$1044,0))=0,"n/a",(INDEX(Historical!$C$7:$C$1044,MATCH(B43,Historical!$B$7:$B$1044,0))/INDEX(Historical!$D$7:$D$1044,MATCH(B43,Historical!$B$7:$B$1044,0))-1)*100) -> 4 | T43: =IF(INDEX(Historical!$F$7:$F$1044,MATCH(B43,Historical!$B$7:$B$1044,0))=0,"n/a",((INDEX(Historical!$C$7:$C$1044,MATCH(B43,Historical!$B$7:$B$1044,0))/INDEX(Historical!$F$7:$F$1044,MATCH(B43,Historical!$B$7:$B$1044,0)))^(1/3)-1)*100) -> 3.8711933 | U43: =IF(INDEX(Historical!$H$7:$H$1044,MATCH(B43,Historical!$B$7:$B$1044,0))=0,"n/a",((INDEX(Historical!$C$7:$C$1044,MATCH(B43,Historical!$B$7:$B$1044,0))/INDEX(Historical!$H$7:$H$1044,MATCH(B43,Historical!$B$7:$B$1044,0)))^(1/5)-1)*100) -> 5.3873952 | V43: =IF(INDEX(Historical!$M$7:$M$1044,MATCH(B43,Historical!$B$7:$B$1044,0))=0,"n/a",((INDEX(Historical!$C$7:$C$1044,MATCH(B43,Historical!$B$7:$B$1044,0))/INDEX(Historical!$M$7:$M$1044,MATCH(B43,Historical!$B$7:$B$1044,0)))^(1/10)-1)*100) -> 5.308679 | W43: =IF(OR(U43<=0,U43="n/a",V43<=0,V43="n/a"),"n/a",U43/V43) -> 1.0148278 | X43: =IF(OR(AJ43<=0,AJ43="n/a",U43<=0,U43="n/a"),"n/a",U43/AJ43) -> n/a | Z43: =IF(OR(AC43<0.01,AC43="n/a"),"n/a",M43/AC43*100) -> n/a | AA43: =IF(OR(AC43<0.01,AC43="n/a"),"n/a",I43/AC43) -> n/a | AB43: 12 | AC43: n/a | AD43: n/a | AE43: n/a | AF43: n/a | AG43: n/a | AH43: n/a | AI43: n/a | AJ43: n/a | AK43: n/a | AL43: n/a | AM43: n/a | AN43: n/a | AO43: =IF(U43="n/a","n/a",IF(AA43<0,"n/a",IF(AA43="n/a","n/a",J43+U43-AA43))) -> n/a | AP43: =IF(U43="n/a","n/a",J43+U43) -> 7.4743517 | AQ43: =IF(OR(AC43<0.01,AC43="n/a",AF43="n/a"),"n/a",(I43/SQRT(22.5*AC43*(I43/AF43))-1)*100) -> n/a | AR43: =INDEX(Historical!$C$7:$C$1045,MATCH(B43,Historical!$B$7:$B$1045,0))*IF(AH43="n/a",1.03,IF(AH43<0,1.01,IF(AH43>10,1.1,(1+AH43/100)))) -> 0.6695 | AS43: =IF($AI43="n/a",1.03*AR43,IF($AI43<0,1.01*AR43,IF($AI43>10,1.1*AR43,(1+$AI43/100)*AR43))) -> 0.689585 | AT43: =IF($AK43="n/a",1.03*AS43,IF($AK43<0,1.01*AS43,IF($AK43>10,1.1*AS43,(1+$AK43/100)*AS43))) -> 0.71027255 | AU43: =IF($AK43="n/a",1.03*AT43,IF($AK43<0,1.01*AT43,IF($AK43>10,1.1*AT43,(1+$AK43/100)*AT43))) -> 0.73158073 | AV43: =IF($AK43="n/a",1.03*AU43,IF($AK43<0,1.01*AU43,IF($AK43>10,1.1*AU43,(1+$AK43/100)*AU43))) -> 0.75352815 | AW43: =SUM(AR43:AV43) -> 3.5544664 | AX43: =AW43/I43*100 -> 10.302801 | AY43: n/a | AZ43: n/a | BA43: n/a | BB43: n/a | BC43: n/a | BD43: OTC | BE43: 1992 | BF43: =IF(BE43>2020,0,IF(BE43>2008,1,IF(BE43>2001,2,IF(BE43>1990,3,IF(BE43>1980,4,IF(BE43>1973,5,IF(BE43>1970,6,IF(BE43>1960,7,IF(BE43>1958,8,IF(BE43>1953,9,10)))))))))) -> 3 | BG43: n/a | BH43: USD | BI43: Corp
A44: Carlisle Companies Incorporated | B44: CSL | C44: Industrials | D44: Industrial Conglomerates | E44: 49 | F44: 54 | G44: N | H44: N | I44: 355.26 | J44: =(M44/I44)*100 -> 1.2385295 | K44: 1.1 | L44: 4 | M44: =K44*L44 -> 4.4 | N44: C01 | O44: 1 | P44: 45888 | Q44: 45902 | R44: =(K44-O44)/O44*100 -> 10 | S44: =IF(INDEX(Historical!$D$7:$D1187,MATCH(B44,Historical!$B$7:$B$1044,0))=0,"n/a",(INDEX(Historical!$C$7:$C$1044,MATCH(B44,Historical!$B$7:$B$1044,0))/INDEX(Historical!$D$7:$D$1044,MATCH(B44,Historical!$B$7:$B$1044,0))-1)*100) -> 13.513514 | T44: =IF(INDEX(Historical!$F$7:$F$1044,MATCH(B44,Historical!$B$7:$B$1044,0))=0,"n/a",((INDEX(Historical!$C$7:$C$1044,MATCH(B44,Historical!$B$7:$B$1044,0))/INDEX(Historical!$F$7:$F$1044,MATCH(B44,Historical!$B$7:$B$1044,0)))^(1/3)-1)*100) -> 17.636798 | U44: =IF(INDEX(Historical!$H$7:$H$1044,MATCH(B44,Historical!$B$7:$B$1044,0))=0,"n/a",((INDEX(Historical!$C$7:$C$1044,MATCH(B44,Historical!$B$7:$B$1044,0))/INDEX(Historical!$H$7:$H$1044,MATCH(B44,Historical!$B$7:$B$1044,0)))^(1/5)-1)*100) -> 15.424788 | V44: =IF(INDEX(Historical!$M$7:$M$1044,MATCH(B44,Historical!$B$7:$B$1044,0))=0,"n/a",((INDEX(Historical!$C$7:$C$1044,MATCH(B44,Historical!$B$7:$B$1044,0))/INDEX(Historical!$M$7:$M$1044,MATCH(B44,Historical!$B$7:$B$1044,0)))^(1/10)-1)*100) -> 14.336702 | W44: =IF(OR(U44<=0,U44="n/a",V44<=0,V44="n/a"),"n/a",U44/V44) -> 1.0758952 | X44: =IF(OR(AJ44<=0,AJ44="n/a",U44<=0,U44="n/a"),"n/a",U44/AJ44) -> 0.63686161 | Z44: =IF(OR(AC44<0.01,AC44="n/a"),"n/a",M44/AC44*100) -> 25.670945 | AA44: =IF(OR(AC44<0.01,AC44="n/a"),"n/a",I44/AC44) -> 20.726954 | AB44: 12 | AC44: 17.14 | AD44: 1.4 | AE44: 2.89 | AF44: 8.7 | AG44: 38.44 | AH44: 8.18 | AI44: 11.61 | AJ44: 24.22 | AK44: 10.82 | AL44: 14380 | AM44: 1.28 | AN44: 1.74 | AO44: =IF(U44="n/a","n/a",IF(AA44<0,"n/a",IF(AA44="n/a","n/a",J44+U44-AA44))) -> -4.0636369 | AP44: =IF(U44="n/a","n/a",J44+U44) -> 16.663318 | AQ44: =IF(OR(AC44<0.01,AC44="n/a",AF44="n/a"),"n/a",(I44/SQRT(22.5*AC44*(I44/AF44))-1)*100) -> 183.09755 | AR44: =INDEX(Historical!$C$7:$C$1045,MATCH(B44,Historical!$B$7:$B$1045,0))*IF(AH44="n/a",1.03,IF(AH44<0,1.01,IF(AH44>10,1.1,(1+AH44/100)))) -> 4.54356 | AS44: =IF($AI44="n/a",1.03*AR44,IF($AI44<0,1.01*AR44,IF($AI44>10,1.1*AR44,(1+$AI44/100)*AR44))) -> 4.997916 | AT44: =IF($AK44="n/a",1.03*AS44,IF($AK44<0,1.01*AS44,IF($AK44>10,1.1*AS44,(1+$AK44/100)*AS44))) -> 5.4977076 | AU44: =IF($AK44="n/a",1.03*AT44,IF($AK44<0,1.01*AT44,IF($AK44>10,1.1*AT44,(1+$AK44/100)*AT44))) -> 6.0474784 | AV44: =IF($AK44="n/a",1.03*AU44,IF($AK44<0,1.01*AU44,IF($AK44>10,1.1*AU44,(1+$AK44/100)*AU44))) -> 6.6522262 | AW44: =SUM(AR44:AV44) -> 27.738888 | AX44: =AW44/I44*100 -> 7.8080527 | AY44: 0.87 | AZ44: 21.07 | BA44: -18.5 | BB44: -0.39 | BC44: 0.54 | BE44: 1977 | BF44: =IF(BE44>2020,0,IF(BE44>2008,1,IF(BE44>2001,2,IF(BE44>1990,3,IF(BE44>1980,4,IF(BE44>1973,5,IF(BE44>1970,6,IF(BE44>1960,7,IF(BE44>1958,8,IF(BE44>1953,9,10)))))))))) -> 5 | BG44: 12.83 | BH44: USD | BI44: Corp
A45: Cintas Corporation | B45: CTAS | C45: Industrials | D45: Commercial Services & Supplies | E45: 43 | F45: 64 | G45: - | H45: - | I45: 174.65 | J45: =(M45/I45)*100 -> 1.0306327 | K45: 0.45 | L45: 4 | M45: =K45*L45 -> 1.8 | N45: Dec | O45: 0.39 | P45: 45884 | Q45: 45915 | R45: =(K45-O45)/O45*100 -> 15.384615 | S45: =IF(INDEX(Historical!$D$7:$D1192,MATCH(B45,Historical!$B$7:$B$1044,0))=0,"n/a",(INDEX(Historical!$C$7:$C$1044,MATCH(B45,Historical!$B$7:$B$1044,0))/INDEX(Historical!$D$7:$D$1044,MATCH(B45,Historical!$B$7:$B$1044,0))-1)*100) -> 15.463918 | T45: =IF(INDEX(Historical!$F$7:$F$1044,MATCH(B45,Historical!$B$7:$B$1044,0))=0,"n/a",((INDEX(Historical!$C$7:$C$1044,MATCH(B45,Historical!$B$7:$B$1044,0))/INDEX(Historical!$F$7:$F$1044,MATCH(B45,Historical!$B$7:$B$1044,0)))^(1/3)-1)*100) -> 16.96071 | U45: =IF(INDEX(Historical!$H$7:$H$1044,MATCH(B45,Historical!$B$7:$B$1044,0))=0,"n/a",((INDEX(Historical!$C$7:$C$1044,MATCH(B45,Historical!$B$7:$B$1044,0))/INDEX(Historical!$H$7:$H$1044,MATCH(B45,Historical!$B$7:$B$1044,0)))^(1/5)-1)*100) -> 19.050875 | V45: =IF(INDEX(Historical!$M$7:$M$1044,MATCH(B45,Historical!$B$7:$B$1044,0))=0,"n/a",((INDEX(Historical!$C$7:$C$1044,MATCH(B45,Historical!$B$7:$B$1044,0))/INDEX(Historical!$M$7:$M$1044,MATCH(B45,Historical!$B$7:$B$1044,0)))^(1/10)-1)*100) -> 20.397646 | W45: =IF(OR(U45<=0,U45="n/a",V45<=0,V45="n/a"),"n/a",U45/V45) -> 0.93397416 | X45: =IF(OR(AJ45<=0,AJ45="n/a",U45<=0,U45="n/a"),"n/a",U45/AJ45) -> 1.1360092 | Z45: =IF(OR(AC45<0.01,AC45="n/a"),"n/a",M45/AC45*100) -> 37.974684 | AA45: =IF(OR(AC45<0.01,AC45="n/a"),"n/a",I45/AC45) -> 36.845992 | AB45: 5 | AC45: 4.74 | AD45: 2.91 | AE45: 6.34 | AF45: 14.59 | AG45: 41.17 | AH45: 11.21 | AI45: 11.06 | AJ45: 16.77 | AK45: 11.04 | AL45: 69880 | AM45: 14.48 | AN45: 0.61 | AO45: =IF(U45="n/a","n/a",IF(AA45<0,"n/a",IF(AA45="n/a","n/a",J45+U45-AA45))) -> -16.764484 | AP45: =IF(U45="n/a","n/a",J45+U45) -> 20.081507 | AQ45: =IF(OR(AC45<0.01,AC45="n/a",AF45="n/a"),"n/a",(I45/SQRT(22.5*AC45*(I45/AF45))-1)*100) -> 388.80035 | AR45: =INDEX(Historical!$C$7:$C$1045,MATCH(B45,Historical!$B$7:$B$1045,0))*IF(AH45="n/a",1.03,IF(AH45<0,1.01,IF(AH45>10,1.1,(1+AH45/100)))) -> 1.848 | AS45: =IF($AI45="n/a",1.03*AR45,IF($AI45<0,1.01*AR45,IF($AI45>10,1.1*AR45,(1+$AI45/100)*AR45))) -> 2.0328 | AT45: =IF($AK45="n/a",1.03*AS45,IF($AK45<0,1.01*AS45,IF($AK45>10,1.1*AS45,(1+$AK45/100)*AS45))) -> 2.23608 | AU45: =IF($AK45="n/a",1.03*AT45,IF($AK45<0,1.01*AT45,IF($AK45>10,1.1*AT45,(1+$AK45/100)*AT45))) -> 2.459688 | AV45: =IF($AK45="n/a",1.03*AU45,IF($AK45<0,1.01*AU45,IF($AK45>10,1.1*AU45,(1+$AK45/100)*AU45))) -> 2.7056568 | AW45: =SUM(AR45:AV45) -> 11.282225 | AX45: =AW45/I45*100 -> 6.4599054 | AY45: 0.97 | AZ45: 5.46 | BA45: -23.81 | BB45: -5.11 | BC45: -10.26 | BE45: 1984 | BF45: =IF(BE45>2020,0,IF(BE45>2008,1,IF(BE45>2001,2,IF(BE45>1990,3,IF(BE45>1980,4,IF(BE45>1973,5,IF(BE45>1970,6,IF(BE45>1960,7,IF(BE45>1958,8,IF(BE45>1953,9,10)))))))))) -> 4 | BG45: 19.46 | BH45: USD | BI45: Corp
A46: Community Trust Bancorp, Inc. | B46: CTBI | C46: Financials | D46: Banks | E46: 45 | F46: 59 | G46: N | H46: - | I46: 64.93 | J46: =(M46/I46)*100 -> 3.2650547 | K46: 0.53 | L46: 4 | M46: =K46*L46 -> 2.12 | N46: A01 | O46: 0.47 | P46: 45915 | Q46: 45931 | R46: =(K46-O46)/O46*100 -> 12.765957 | S46: =IF(INDEX(Historical!$D$7:$D1193,MATCH(B46,Historical!$B$7:$B$1044,0))=0,"n/a",(INDEX(Historical!$C$7:$C$1044,MATCH(B46,Historical!$B$7:$B$1044,0))/INDEX(Historical!$D$7:$D$1044,MATCH(B46,Historical!$B$7:$B$1044,0))-1)*100) -> 4.8648649 | T46: =IF(INDEX(Historical!$F$7:$F$1044,MATCH(B46,Historical!$B$7:$B$1044,0))=0,"n/a",((INDEX(Historical!$C$7:$C$1044,MATCH(B46,Historical!$B$7:$B$1044,0))/INDEX(Historical!$F$7:$F$1044,MATCH(B46,Historical!$B$7:$B$1044,0)))^(1/3)-1)*100) -> 5.7594769 | U46: =IF(INDEX(Historical!$H$7:$H$1044,MATCH(B46,Historical!$B$7:$B$1044,0))=0,"n/a",((INDEX(Historical!$C$7:$C$1044,MATCH(B46,Historical!$B$7:$B$1044,0))/INDEX(Historical!$H$7:$H$1044,MATCH(B46,Historical!$B$7:$B$1044,0)))^(1/5)-1)*100) -> 4.9316199 | V46: =IF(INDEX(Historical!$M$7:$M$1044,MATCH(B46,Historical!$B$7:$B$1044,0))=0,"n/a",((INDEX(Historical!$C$7:$C$1044,MATCH(B46,Historical!$B$7:$B$1044,0))/INDEX(Historical!$M$7:$M$1044,MATCH(B46,Historical!$B$7:$B$1044,0)))^(1/10)-1)*100) -> 4.8338743 | W46: =IF(OR(U46<=0,U46="n/a",V46<=0,V46="n/a"),"n/a",U46/V46) -> 1.020221 | X46: =IF(OR(AJ46<=0,AJ46="n/a",U46<=0,U46="n/a"),"n/a",U46/AJ46) -> 0.48587388 | Z46: =IF(OR(AC46<0.01,AC46="n/a"),"n/a",M46/AC46*100) -> 37.127846 | AA46: =IF(OR(AC46<0.01,AC46="n/a"),"n/a",I46/AC46) -> 11.371278 | AB46: 12 | AC46: 5.71 | AD46: n/a | AE46: 2.84 | AF46: 1.35 | AG46: 12.48 | AH46: 11.97 | AI46: 2.63 | AJ46: 10.15 | AK46: n/a | AL46: 1180 | AM46: 2.61 | AN46: 0.44 | AO46: =IF(U46="n/a","n/a",IF(AA46<0,"n/a",IF(AA46="n/a","n/a",J46+U46-AA46))) -> -3.1746039 | AP46: =IF(U46="n/a","n/a",J46+U46) -> 8.1966745 | AQ46: =IF(OR(AC46<0.01,AC46="n/a",AF46="n/a"),"n/a",(I46/SQRT(22.5*AC46*(I46/AF46))-1)*100) -> -17.399957 | AR46: =INDEX(Historical!$C$7:$C$1045,MATCH(B46,Historical!$B$7:$B$1045,0))*IF(AH46="n/a",1.03,IF(AH46<0,1.01,IF(AH46>10,1.1,(1+AH46/100)))) -> 2.134 | AS46: =IF($AI46="n/a",1.03*AR46,IF($AI46<0,1.01*AR46,IF($AI46>10,1.1*AR46,(1+$AI46/100)*AR46))) -> 2.1901242 | AT46: =IF($AK46="n/a",1.03*AS46,IF($AK46<0,1.01*AS46,IF($AK46>10,1.1*AS46,(1+$AK46/100)*AS46))) -> 2.2558279 | AU46: =IF($AK46="n/a",1.03*AT46,IF($AK46<0,1.01*AT46,IF($AK46>10,1.1*AT46,(1+$AK46/100)*AT46))) -> 2.3235028 | AV46: =IF($AK46="n/a",1.03*AU46,IF($AK46<0,1.01*AU46,IF($AK46>10,1.1*AU46,(1+$AK46/100)*AU46))) -> 2.3932078 | AW46: =SUM(AR46:AV46) -> 11.296663 | AX46: =AW46/I46*100 -> 17.398218 | AY46: 0.57 | AZ46: 34.43 | BA46: -5.21 | BB46: 4.5 | BC46: 11.54 | BE46: 1981 | BF46: =IF(BE46>2020,0,IF(BE46>2008,1,IF(BE46>2001,2,IF(BE46>1990,3,IF(BE46>1980,4,IF(BE46>1973,5,IF(BE46>1970,6,IF(BE46>1960,7,IF(BE46>1958,8,IF(BE46>1953,9,10)))))))))) -> 4 | BG46: 1.59 | BH46: USD | BI46: Corp
A47: Chevron Corporation | B47: CVX | C47: Energy | D47: Oil, Gas & Consumable Fuels | E47: 39 | F47: 76 | G47: Y | H47: Y | I47: 193.31 | J47: =(M47/I47)*100 -> 3.6832031 | K47: 1.78 | L47: 4 | M47: =K47*L47 -> 7.12 | N47: C12 | O47: 1.71 | P47: 46070 | Q47: 46091 | R47: =(K47-O47)/O47*100 -> 4.0935673 | S47: =IF(INDEX(Historical!$D$7:$D1199,MATCH(B47,Historical!$B$7:$B$1044,0))=0,"n/a",(INDEX(Historical!$C$7:$C$1044,MATCH(B47,Historical!$B$7:$B$1044,0))/INDEX(Historical!$D$7:$D$1044,MATCH(B47,Historical!$B$7:$B$1044,0))-1)*100) -> 4.9079755 | T47: =IF(INDEX(Historical!$F$7:$F$1044,MATCH(B47,Historical!$B$7:$B$1044,0))=0,"n/a",((INDEX(Historical!$C$7:$C$1044,MATCH(B47,Historical!$B$7:$B$1044,0))/INDEX(Historical!$F$7:$F$1044,MATCH(B47,Historical!$B$7:$B$1044,0)))^(1/3)-1)*100) -> 6.390436 | U47: =IF(INDEX(Historical!$H$7:$H$1044,MATCH(B47,Historical!$B$7:$B$1044,0))=0,"n/a",((INDEX(Historical!$C$7:$C$1044,MATCH(B47,Historical!$B$7:$B$1044,0))/INDEX(Historical!$H$7:$H$1044,MATCH(B47,Historical!$B$7:$B$1044,0)))^(1/5)-1)*100) -> 5.6763364 | V47: =IF(INDEX(Historical!$M$7:$M$1044,MATCH(B47,Historical!$B$7:$B$1044,0))=0,"n/a",((INDEX(Historical!$C$7:$C$1044,MATCH(B47,Historical!$B$7:$B$1044,0))/INDEX(Historical!$M$7:$M$1044,MATCH(B47,Historical!$B$7:$B$1044,0)))^(1/10)-1)*100) -> 4.7999881 | W47: =IF(OR(U47<=0,U47="n/a",V47<=0,V47="n/a"),"n/a",U47/V47) -> 1.182573 | X47: =IF(OR(AJ47<=0,AJ47="n/a",U47<=0,U47="n/a"),"n/a",U47/AJ47) -> n/a | Z47: =IF(OR(AC47<0.01,AC47="n/a"),"n/a",M47/AC47*100) -> 107.06767 | AA47: =IF(OR(AC47<0.01,AC47="n/a"),"n/a",I47/AC47) -> 29.069173 | AB47: 12 | AC47: 6.65 | AD47: 0.95 | AE47: 2.09 | AF47: 2.07 | AG47: 7.26 | AH47: 66.66 | AI47: -7.24 | AJ47: n/a | AK47: 18.12 | AL47: 385730 | AM47: 0.47 | AN47: 0.25 | AO47: =IF(U47="n/a","n/a",IF(AA47<0,"n/a",IF(AA47="n/a","n/a",J47+U47-AA47))) -> -19.709633 | AP47: =IF(U47="n/a","n/a",J47+U47) -> 9.3595396 | AQ47: =IF(OR(AC47<0.01,AC47="n/a",AF47="n/a"),"n/a",(I47/SQRT(22.5*AC47*(I47/AF47))-1)*100) -> 63.534825 | AR47: =INDEX(Historical!$C$7:$C$1045,MATCH(B47,Historical!$B$7:$B$1045,0))*IF(AH47="n/a",1.03,IF(AH47<0,1.01,IF(AH47>10,1.1,(1+AH47/100)))) -> 7.524 | AS47: =IF($AI47="n/a",1.03*AR47,IF($AI47<0,1.01*AR47,IF($AI47>10,1.1*AR47,(1+$AI47/100)*AR47))) -> 7.59924 | AT47: =IF($AK47="n/a",1.03*AS47,IF($AK47<0,1.01*AS47,IF($AK47>10,1.1*AS47,(1+$AK47/100)*AS47))) -> 8.359164 | AU47: =IF($AK47="n/a",1.03*AT47,IF($AK47<0,1.01*AT47,IF($AK47>10,1.1*AT47,(1+$AK47/100)*AT47))) -> 9.1950804 | AV47: =IF($AK47="n/a",1.03*AU47,IF($AK47<0,1.01*AU47,IF($AK47>10,1.1*AU47,(1+$AK47/100)*AU47))) -> 10.114588 | AW47: =SUM(AR47:AV47) -> 42.792073 | AX47: =AW47/I47*100 -> 22.136502 | AY47: 0.51 | AZ47: 44.51 | BA47: -9.97 | BB47: 0.25 | BC47: 16.22 | BE47: 1988 | BF47: =IF(BE47>2020,0,IF(BE47>2008,1,IF(BE47>2001,2,IF(BE47>1990,3,IF(BE47>1980,4,IF(BE47>1973,5,IF(BE47>1970,6,IF(BE47>1960,7,IF(BE47>1958,8,IF(BE47>1953,9,10)))))))))) -> 4 | BG47: 4.23 | BH47: USD | BI47: Corp
A48: California Water Service Group | B48: CWT | C48: Utilities | D48: Water Utilities | E48: 59 | F48: 19 | G48: N | H48: N | I48: 42.24 | J48: =(M48/I48)*100 -> 3.1723485 | K48: 0.335 | L48: 4 | M48: =K48*L48 -> 1.34 | N48: B23 | O48: 0.3 | P48: 46062 | Q48: 46073 | R48: =(K48-O48)/O48*100 -> 11.666667 | S48: =IF(INDEX(Historical!$D$7:$D1202,MATCH(B48,Historical!$B$7:$B$1044,0))=0,"n/a",(INDEX(Historical!$C$7:$C$1044,MATCH(B48,Historical!$B$7:$B$1044,0))/INDEX(Historical!$D$7:$D$1044,MATCH(B48,Historical!$B$7:$B$1044,0))-1)*100) -> 7.1428571 | T48: =IF(INDEX(Historical!$F$7:$F$1044,MATCH(B48,Historical!$B$7:$B$1044,0))=0,"n/a",((INDEX(Historical!$C$7:$C$1044,MATCH(B48,Historical!$B$7:$B$1044,0))/INDEX(Historical!$F$7:$F$1044,MATCH(B48,Historical!$B$7:$B$1044,0)))^(1/3)-1)*100) -> 6.2658569 | U48: =IF(INDEX(Historical!$H$7:$H$1044,MATCH(B48,Historical!$B$7:$B$1044,0))=0,"n/a",((INDEX(Historical!$C$7:$C$1044,MATCH(B48,Historical!$B$7:$B$1044,0))/INDEX(Historical!$H$7:$H$1044,MATCH(B48,Historical!$B$7:$B$1044,0)))^(1/5)-1)*100) -> 7.1402028 | V48: =IF(INDEX(Historical!$M$7:$M$1044,MATCH(B48,Historical!$B$7:$B$1044,0))=0,"n/a",((INDEX(Historical!$C$7:$C$1044,MATCH(B48,Historical!$B$7:$B$1044,0))/INDEX(Historical!$M$7:$M$1044,MATCH(B48,Historical!$B$7:$B$1044,0)))^(1/10)-1)*100) -> 6.0011665 | W48: =IF(OR(U48<=0,U48="n/a",V48<=0,V48="n/a"),"n/a",U48/V48) -> 1.1898025 | X48: =IF(OR(AJ48<=0,AJ48="n/a",U48<=0,U48="n/a"),"n/a",U48/AJ48) -> 3.9448634 | Z48: =IF(OR(AC48<0.01,AC48="n/a"),"n/a",M48/AC48*100) -> 67.336683 | AA48: =IF(OR(AC48<0.01,AC48="n/a"),"n/a",I48/AC48) -> 21.226131 | AB48: 12 | AC48: 1.99 | AD48: 1.76 | AE48: 2.5 | AF48: 1.41 | AG48: 6.96 | AH48: 20.16 | AI48: 7.23 | AJ48: 1.81 | AK48: 8.68 | AL48: 2530 | AM48: 0.81 | AN48: 0.95 | AO48: =IF(U48="n/a","n/a",IF(AA48<0,"n/a",IF(AA48="n/a","n/a",J48+U48-AA48))) -> -10.913579 | AP48: =IF(U48="n/a","n/a",J48+U48) -> 10.312551 | AQ48: =IF(OR(AC48<0.01,AC48="n/a",AF48="n/a"),"n/a",(I48/SQRT(22.5*AC48*(I48/AF48))-1)*100) -> 15.333033 | AR48: =INDEX(Historical!$C$7:$C$1045,MATCH(B48,Historical!$B$7:$B$1045,0))*IF(AH48="n/a",1.03,IF(AH48<0,1.01,IF(AH48>10,1.1,(1+AH48/100)))) -> 1.32 | AS48: =IF($AI48="n/a",1.03*AR48,IF($AI48<0,1.01*AR48,IF($AI48>10,1.1*AR48,(1+$AI48/100)*AR48))) -> 1.415436 | AT48: =IF($AK48="n/a",1.03*AS48,IF($AK48<0,1.01*AS48,IF($AK48>10,1.1*AS48,(1+$AK48/100)*AS48))) -> 1.5382958 | AU48: =IF($AK48="n/a",1.03*AT48,IF($AK48<0,1.01*AT48,IF($AK48>10,1.1*AT48,(1+$AK48/100)*AT48))) -> 1.6718199 | AV48: =IF($AK48="n/a",1.03*AU48,IF($AK48<0,1.01*AU48,IF($AK48>10,1.1*AU48,(1+$AK48/100)*AU48))) -> 1.8169339 | AW48: =SUM(AR48:AV48) -> 7.7624857 | AX48: =AW48/I48*100 -> 18.377097 | AY48: 0.57 | AZ48: 2.3 | BA48: -17.42 | BB48: -7.03 | BC48: -7.2 | BE48: 1968 | BF48: =IF(BE48>2020,0,IF(BE48>2008,1,IF(BE48>2001,2,IF(BE48>1990,3,IF(BE48>1980,4,IF(BE48>1973,5,IF(BE48>1970,6,IF(BE48>1960,7,IF(BE48>1958,8,IF(BE48>1953,9,10)))))))))) -> 7 | BG48: 2.15 | BH48: USD | BI48: Corp
A49: Citizens Financial Services, Inc. | B49: CZFS | C49: Financials | D49: Banks | E49: 27 | F49: 138 | G49: - | H49: - | I49: 63.16 | J49: =(M49/I49)*100 -> 3.1665611 | K49: 0.5 | L49: 4 | M49: =K49*L49 -> 2 | N49: C30 | O49: 0.495 | P49: 45912 | Q49: 45926 | R49: =(K49-O49)/O49*100 -> 1.010101 | S49: =IF(INDEX(Historical!$D$7:$D1203,MATCH(B49,Historical!$B$7:$B$1044,0))=0,"n/a",(INDEX(Historical!$C$7:$C$1044,MATCH(B49,Historical!$B$7:$B$1044,0))/INDEX(Historical!$D$7:$D$1044,MATCH(B49,Historical!$B$7:$B$1044,0))-1)*100) -> 2.5484821 | T49: =IF(INDEX(Historical!$F$7:$F$1044,MATCH(B49,Historical!$B$7:$B$1044,0))=0,"n/a",((INDEX(Historical!$C$7:$C$1044,MATCH(B49,Historical!$B$7:$B$1044,0))/INDEX(Historical!$F$7:$F$1044,MATCH(B49,Historical!$B$7:$B$1044,0)))^(1/3)-1)*100) -> 2.2224907 | U49: =IF(INDEX(Historical!$H$7:$H$1044,MATCH(B49,Historical!$B$7:$B$1044,0))=0,"n/a",((INDEX(Historical!$C$7:$C$1044,MATCH(B49,Historical!$B$7:$B$1044,0))/INDEX(Historical!$H$7:$H$1044,MATCH(B49,Historical!$B$7:$B$1044,0)))^(1/5)-1)*100) -> 2.1984551 | V49: =IF(INDEX(Historical!$M$7:$M$1044,MATCH(B49,Historical!$B$7:$B$1044,0))=0,"n/a",((INDEX(Historical!$C$7:$C$1044,MATCH(B49,Historical!$B$7:$B$1044,0))/INDEX(Historical!$M$7:$M$1044,MATCH(B49,Historical!$B$7:$B$1044,0)))^(1/10)-1)*100) -> 2.2700607 | W49: =IF(OR(U49<=0,U49="n/a",V49<=0,V49="n/a"),"n/a",U49/V49) -> 0.9684565 | X49: =IF(OR(AJ49<=0,AJ49="n/a",U49<=0,U49="n/a"),"n/a",U49/AJ49) -> 0.55516543 | Z49: =IF(OR(AC49<0.01,AC49="n/a"),"n/a",M49/AC49*100) -> 24.390244 | AA49: =IF(OR(AC49<0.01,AC49="n/a"),"n/a",I49/AC49) -> 7.702439 | AB49: 12 | AC49: 8.2 | AD49: n/a | AE49: 1.74 | AF49: 0.88 | AG49: 12.07 | AH49: 2.49 | AI49: 1.54 | AJ49: 3.96 | AK49: n/a | AL49: 303.63 | AM49: 6.56 | AN49: 0.58 | AO49: =IF(U49="n/a","n/a",IF(AA49<0,"n/a",IF(AA49="n/a","n/a",J49+U49-AA49))) -> -2.3374228 | AP49: =IF(U49="n/a","n/a",J49+U49) -> 5.3650162 | AQ49: =IF(OR(AC49<0.01,AC49="n/a",AF49="n/a"),"n/a",(I49/SQRT(22.5*AC49*(I49/AF49))-1)*100) -> -45.113668 | AR49: =INDEX(Historical!$C$7:$C$1045,MATCH(B49,Historical!$B$7:$B$1045,0))*IF(AH49="n/a",1.03,IF(AH49<0,1.01,IF(AH49>10,1.1,(1+AH49/100)))) -> 2.029505 | AS49: =IF($AI49="n/a",1.03*AR49,IF($AI49<0,1.01*AR49,IF($AI49>10,1.1*AR49,(1+$AI49/100)*AR49))) -> 2.0607593 | AT49: =IF($AK49="n/a",1.03*AS49,IF($AK49<0,1.01*AS49,IF($AK49>10,1.1*AS49,(1+$AK49/100)*AS49))) -> 2.1225821 | AU49: =IF($AK49="n/a",1.03*AT49,IF($AK49<0,1.01*AT49,IF($AK49>10,1.1*AT49,(1+$AK49/100)*AT49))) -> 2.1862596 | AV49: =IF($AK49="n/a",1.03*AU49,IF($AK49<0,1.01*AU49,IF($AK49>10,1.1*AU49,(1+$AK49/100)*AU49))) -> 2.2518474 | AW49: =SUM(AR49:AV49) -> 10.650953 | AX49: =AW49/I49*100 -> 16.863447 | AY49: 0.42 | AZ49: 26.35 | BA49: -9.23 | BB49: 0.26 | BC49: 5.24 | BD49: OTC | BE49: 1999 | BF49: =IF(BE49>2020,0,IF(BE49>2008,1,IF(BE49>2001,2,IF(BE49>1990,3,IF(BE49>1980,4,IF(BE49>1973,5,IF(BE49>1970,6,IF(BE49>1960,7,IF(BE49>1958,8,IF(BE49>1953,9,10)))))))))) -> 3 | BG49: 1.3 | BH49: USD | BI49: Corp
A50: Donaldson Company, Inc. | B50: DCI | C50: Industrials | D50: Machinery | E50: 39 | F50: 74 | G50: N | H50: N | I50: 88.17 | J50: =(M50/I50)*100 -> 1.3610071 | K50: 0.3 | L50: 4 | M50: =K50*L50 -> 1.2 | N50: B31 | O50: 0.27 | P50: 45824 | Q50: 45838 | R50: =(K50-O50)/O50*100 -> 11.111111 | S50: =IF(INDEX(Historical!$D$7:$D1205,MATCH(B50,Historical!$B$7:$B$1044,0))=0,"n/a",(INDEX(Historical!$C$7:$C$1044,MATCH(B50,Historical!$B$7:$B$1044,0))/INDEX(Historical!$D$7:$D$1044,MATCH(B50,Historical!$B$7:$B$1044,0))-1)*100) -> 10.377358 | T50: =IF(INDEX(Historical!$F$7:$F$1044,MATCH(B50,Historical!$B$7:$B$1044,0))=0,"n/a",((INDEX(Historical!$C$7:$C$1044,MATCH(B50,Historical!$B$7:$B$1044,0))/INDEX(Historical!$F$7:$F$1044,MATCH(B50,Historical!$B$7:$B$1044,0)))^(1/3)-1)*100) -> 8.7380373 | U50: =IF(INDEX(Historical!$H$7:$H$1044,MATCH(B50,Historical!$B$7:$B$1044,0))=0,"n/a",((INDEX(Historical!$C$7:$C$1044,MATCH(B50,Historical!$B$7:$B$1044,0))/INDEX(Historical!$H$7:$H$1044,MATCH(B50,Historical!$B$7:$B$1044,0)))^(1/5)-1)*100) -> 6.8516702 | V50: =IF(INDEX(Historical!$M$7:$M$1044,MATCH(B50,Historical!$B$7:$B$1044,0))=0,"n/a",((INDEX(Historical!$C$7:$C$1044,MATCH(B50,Historical!$B$7:$B$1044,0))/INDEX(Historical!$M$7:$M$1044,MATCH(B50,Historical!$B$7:$B$1044,0)))^(1/10)-1)*100) -> 5.7331342 | W50: =IF(OR(U50<=0,U50="n/a",V50<=0,V50="n/a"),"n/a",U50/V50) -> 1.1951003 | X50: =IF(OR(AJ50<=0,AJ50="n/a",U50<=0,U50="n/a"),"n/a",U50/AJ50) -> 0.78215414 | Z50: =IF(OR(AC50<0.01,AC50="n/a"),"n/a",M50/AC50*100) -> 37.5 | AA50: =IF(OR(AC50<0.01,AC50="n/a"),"n/a",I50/AC50) -> 27.553125 | AB50: 7 | AC50: 3.2 | AD50: 1.88 | AE50: 2.72 | AF50: 6.48 | AG50: 24.27 | AH50: 11.76 | AI50: 9.98 | AJ50: 8.76 | AK50: 10.73 | AL50: 10210 | AM50: 0.61 | AN50: 0.43 | AO50: =IF(U50="n/a","n/a",IF(AA50<0,"n/a",IF(AA50="n/a","n/a",J50+U50-AA50))) -> -19.340448 | AP50: =IF(U50="n/a","n/a",J50+U50) -> 8.2126774 | AQ50: =IF(OR(AC50<0.01,AC50="n/a",AF50="n/a"),"n/a",(I50/SQRT(22.5*AC50*(I50/AF50))-1)*100) -> 181.69665 | AR50: =INDEX(Historical!$C$7:$C$1045,MATCH(B50,Historical!$B$7:$B$1045,0))*IF(AH50="n/a",1.03,IF(AH50<0,1.01,IF(AH50>10,1.1,(1+AH50/100)))) -> 1.287 | AS50: =IF($AI50="n/a",1.03*AR50,IF($AI50<0,1.01*AR50,IF($AI50>10,1.1*AR50,(1+$AI50/100)*AR50))) -> 1.4154426 | AT50: =IF($AK50="n/a",1.03*AS50,IF($AK50<0,1.01*AS50,IF($AK50>10,1.1*AS50,(1+$AK50/100)*AS50))) -> 1.5569869 | AU50: =IF($AK50="n/a",1.03*AT50,IF($AK50<0,1.01*AT50,IF($AK50>10,1.1*AT50,(1+$AK50/100)*AT50))) -> 1.7126855 | AV50: =IF($AK50="n/a",1.03*AU50,IF($AK50<0,1.01*AU50,IF($AK50>10,1.1*AU50,(1+$AK50/100)*AU50))) -> 1.8839541 | AW50: =SUM(AR50:AV50) -> 7.8560691 | AX50: =AW50/I50*100 -> 8.9101385 | AY50: 1 | AZ50: 37.23 | BA50: -21.86 | BB50: -1.68 | BC50: 1.26 | BE50: 1987 | BF50: =IF(BE50>2020,0,IF(BE50>2008,1,IF(BE50>2001,2,IF(BE50>1990,3,IF(BE50>1980,4,IF(BE50>1973,5,IF(BE50>1970,6,IF(BE50>1960,7,IF(BE50>1958,8,IF(BE50>1953,9,10)))))))))) -> 4 | BG50: 12.57 | BH50: USD | BI50: Corp
A51: Dover Corporation | B51: DOV | C51: Industrials | D51: Machinery | E51: 70 | F51: 2 | G51: Y | H51: N | I51: 226.41 | J51: =(M51/I51)*100 -> 0.91868734 | K51: 0.52 | L51: 4 | M51: =K51*L51 -> 2.08 | N51: C15 | O51: 0.515 | P51: 45898 | Q51: 45915 | R51: =(K51-O51)/O51*100 -> 0.97087379 | S51: =IF(INDEX(Historical!$D$7:$D1215,MATCH(B51,Historical!$B$7:$B$1044,0))=0,"n/a",(INDEX(Historical!$C$7:$C$1044,MATCH(B51,Historical!$B$7:$B$1044,0))/INDEX(Historical!$D$7:$D$1044,MATCH(B51,Historical!$B$7:$B$1044,0))-1)*100) -> 0.97560976 | T51: =IF(INDEX(Historical!$F$7:$F$1044,MATCH(B51,Historical!$B$7:$B$1044,0))=0,"n/a",((INDEX(Historical!$C$7:$C$1044,MATCH(B51,Historical!$B$7:$B$1044,0))/INDEX(Historical!$F$7:$F$1044,MATCH(B51,Historical!$B$7:$B$1044,0)))^(1/3)-1)*100) -> 0.98528512 | U51: =IF(INDEX(Historical!$H$7:$H$1044,MATCH(B51,Historical!$B$7:$B$1044,0))=0,"n/a",((INDEX(Historical!$C$7:$C$1044,MATCH(B51,Historical!$B$7:$B$1044,0))/INDEX(Historical!$H$7:$H$1044,MATCH(B51,Historical!$B$7:$B$1044,0)))^(1/5)-1)*100) -> 0.995221 | V51: =IF(INDEX(Historical!$M$7:$M$1044,MATCH(B51,Historical!$B$7:$B$1044,0))=0,"n/a",((INDEX(Historical!$C$7:$C$1044,MATCH(B51,Historical!$B$7:$B$1044,0))/INDEX(Historical!$M$7:$M$1044,MATCH(B51,Historical!$B$7:$B$1044,0)))^(1/10)-1)*100) -> 2.3558454 | W51: =IF(OR(U51<=0,U51="n/a",V51<=0,V51="n/a"),"n/a",U51/V51) -> 0.4224475 | X51: =IF(OR(AJ51<=0,AJ51="n/a",U51<=0,U51="n/a"),"n/a",U51/AJ51) -> 0.090065249 | Z51: =IF(OR(AC51<0.01,AC51="n/a"),"n/a",M51/AC51*100) -> 25.902864 | AA51: =IF(OR(AC51<0.01,AC51="n/a"),"n/a",I51/AC51) -> 28.195517 | AB51: 12 | AC51: 8.03 | AD51: 2.11 | AE51: 3.68 | AF51: 4.07 | AG51: 15 | AH51: 10.89 | AI51: 9.37 | AJ51: 11.05 | AK51: 9.21 | AL51: 30490 | AM51: 0.68 | AN51: 0.44 | AO51: =IF(U51="n/a","n/a",IF(AA51<0,"n/a",IF(AA51="n/a","n/a",J51+U51-AA51))) -> -26.281608 | AP51: =IF(U51="n/a","n/a",J51+U51) -> 1.9139083 | AQ51: =IF(OR(AC51<0.01,AC51="n/a",AF51="n/a"),"n/a",(I51/SQRT(22.5*AC51*(I51/AF51))-1)*100) -> 125.83746 | AR51: =INDEX(Historical!$C$7:$C$1045,MATCH(B51,Historical!$B$7:$B$1045,0))*IF(AH51="n/a",1.03,IF(AH51<0,1.01,IF(AH51>10,1.1,(1+AH51/100)))) -> 2.277 | AS51: =IF($AI51="n/a",1.03*AR51,IF($AI51<0,1.01*AR51,IF($AI51>10,1.1*AR51,(1+$AI51/100)*AR51))) -> 2.4903549 | AT51: =IF($AK51="n/a",1.03*AS51,IF($AK51<0,1.01*AS51,IF($AK51>10,1.1*AS51,(1+$AK51/100)*AS51))) -> 2.7197166 | AU51: =IF($AK51="n/a",1.03*AT51,IF($AK51<0,1.01*AT51,IF($AK51>10,1.1*AT51,(1+$AK51/100)*AT51))) -> 2.9702025 | AV51: =IF($AK51="n/a",1.03*AU51,IF($AK51<0,1.01*AU51,IF($AK51>10,1.1*AU51,(1+$AK51/100)*AU51))) -> 3.2437581 | AW51: =SUM(AR51:AV51) -> 13.701032 | AX51: =AW51/I51*100 -> 6.0514253 | AY51: 1.21 | AZ51: 42.42 | BA51: -4.69 | BB51: 4.43 | BC51: 16.47 | BE51: 1956 | BF51: =IF(BE51>2020,0,IF(BE51>2008,1,IF(BE51>2001,2,IF(BE51>1990,3,IF(BE51>1980,4,IF(BE51>1973,5,IF(BE51>1970,6,IF(BE51>1960,7,IF(BE51>1958,8,IF(BE51>1953,9,10)))))))))) -> 9 | BG51: 8.39 | BH51: USD | BI51: Corp
A52: Eagle Bancorp Montana, Inc. | B52: EBMT | C52: Financials | D52: Banks | E52: 26 | F52: 141 | G52: - | H52: - | I52: 22.12 | J52: =(M52/I52)*100 -> 2.6220615 | K52: 0.145 | L52: 4 | M52: =K52*L52 -> 0.58 | N52: C01 | O52: 0.1425 | P52: 45884 | Q52: 45905 | R52: =(K52-O52)/O52*100 -> 1.754386 | S52: =IF(INDEX(Historical!$D$7:$D1224,MATCH(B52,Historical!$B$7:$B$1044,0))=0,"n/a",(INDEX(Historical!$C$7:$C$1044,MATCH(B52,Historical!$B$7:$B$1044,0))/INDEX(Historical!$D$7:$D$1044,MATCH(B52,Historical!$B$7:$B$1044,0))-1)*100) -> 1.7699115 | T52: =IF(INDEX(Historical!$F$7:$F$1044,MATCH(B52,Historical!$B$7:$B$1044,0))=0,"n/a",((INDEX(Historical!$C$7:$C$1044,MATCH(B52,Historical!$B$7:$B$1044,0))/INDEX(Historical!$F$7:$F$1044,MATCH(B52,Historical!$B$7:$B$1044,0)))^(1/3)-1)*100) -> 3.0788379 | U52: =IF(INDEX(Historical!$H$7:$H$1044,MATCH(B52,Historical!$B$7:$B$1044,0))=0,"n/a",((INDEX(Historical!$C$7:$C$1044,MATCH(B52,Historical!$B$7:$B$1044,0))/INDEX(Historical!$H$7:$H$1044,MATCH(B52,Historical!$B$7:$B$1044,0)))^(1/5)-1)*100) -> 8.3531204 | V52: =IF(INDEX(Historical!$M$7:$M$1044,MATCH(B52,Historical!$B$7:$B$1044,0))=0,"n/a",((INDEX(Historical!$C$7:$C$1044,MATCH(B52,Historical!$B$7:$B$1044,0))/INDEX(Historical!$M$7:$M$1044,MATCH(B52,Historical!$B$7:$B$1044,0)))^(1/10)-1)*100) -> 6.5459143 | W52: =IF(OR(U52<=0,U52="n/a",V52<=0,V52="n/a"),"n/a",U52/V52) -> 1.2760815 | X52: =IF(OR(AJ52<=0,AJ52="n/a",U52<=0,U52="n/a"),"n/a",U52/AJ52) -> n/a | Z52: =IF(OR(AC52<0.01,AC52="n/a"),"n/a",M52/AC52*100) -> 29.145729 | AA52: =IF(OR(AC52<0.01,AC52="n/a"),"n/a",I52/AC52) -> 11.115578 | AB52: 6 | AC52: 1.99 | AD52: n/a | AE52: 1.38 | AF52: 0.91 | AG52: 8.41 | AH52: 7.19 | AI52: 5.4 | AJ52: -9.42 | AK52: n/a | AL52: 176.19 | AM52: 7.87 | AN52: 0.37 | AO52: =IF(U52="n/a","n/a",IF(AA52<0,"n/a",IF(AA52="n/a","n/a",J52+U52-AA52))) -> -0.14039596 | AP52: =IF(U52="n/a","n/a",J52+U52) -> 10.975182 | AQ52: =IF(OR(AC52<0.01,AC52="n/a",AF52="n/a"),"n/a",(I52/SQRT(22.5*AC52*(I52/AF52))-1)*100) -> -32.950513 | AR52: =INDEX(Historical!$C$7:$C$1045,MATCH(B52,Historical!$B$7:$B$1045,0))*IF(AH52="n/a",1.03,IF(AH52<0,1.01,IF(AH52>10,1.1,(1+AH52/100)))) -> 0.6163425 | AS52: =IF($AI52="n/a",1.03*AR52,IF($AI52<0,1.01*AR52,IF($AI52>10,1.1*AR52,(1+$AI52/100)*AR52))) -> 0.649625 | AT52: =IF($AK52="n/a",1.03*AS52,IF($AK52<0,1.01*AS52,IF($AK52>10,1.1*AS52,(1+$AK52/100)*AS52))) -> 0.66911374 | AU52: =IF($AK52="n/a",1.03*AT52,IF($AK52<0,1.01*AT52,IF($AK52>10,1.1*AT52,(1+$AK52/100)*AT52))) -> 0.68918716 | AV52: =IF($AK52="n/a",1.03*AU52,IF($AK52<0,1.01*AU52,IF($AK52>10,1.1*AU52,(1+$AK52/100)*AU52))) -> 0.70986277 | AW52: =SUM(AR52:AV52) -> 3.3341312 | AX52: =AW52/I52*100 -> 15.072926 | AY52: 0.36 | AZ52: 46.49 | BA52: -7.62 | BB52: 2.88 | BC52: 16.77 | BE52: 2000 | BF52: =IF(BE52>2020,0,IF(BE52>2008,1,IF(BE52>2001,2,IF(BE52>1990,3,IF(BE52>1980,4,IF(BE52>1973,5,IF(BE52>1970,6,IF(BE52>1960,7,IF(BE52>1958,8,IF(BE52>1953,9,10)))))))))) -> 3 | BG52: 0.75 | BH52: USD | BI52: Corp
A53: Ecolab Inc. | B53: ECL | C53: Materials | D53: Chemicals | E53: 34 | F53: 89 | G53: N | H53: N | I53: 260.6 | J53: =(M53/I53)*100 -> 1.1204912 | K53: 0.73 | L53: 4 | M53: =K53*L53 -> 2.92 | N53: A16 | O53: 0.65 | P53: 46007 | Q53: 46037 | R53: =(K53-O53)/O53*100 -> 12.307692 | S53: =IF(INDEX(Historical!$D$7:$D1225,MATCH(B53,Historical!$B$7:$B$1044,0))=0,"n/a",(INDEX(Historical!$C$7:$C$1044,MATCH(B53,Historical!$B$7:$B$1044,0))/INDEX(Historical!$D$7:$D$1044,MATCH(B53,Historical!$B$7:$B$1044,0))-1)*100) -> 14.035088 | T53: =IF(INDEX(Historical!$F$7:$F$1044,MATCH(B53,Historical!$B$7:$B$1044,0))=0,"n/a",((INDEX(Historical!$C$7:$C$1044,MATCH(B53,Historical!$B$7:$B$1044,0))/INDEX(Historical!$F$7:$F$1044,MATCH(B53,Historical!$B$7:$B$1044,0)))^(1/3)-1)*100) -> 8.4212459 | U53: =IF(INDEX(Historical!$H$7:$H$1044,MATCH(B53,Historical!$B$7:$B$1044,0))=0,"n/a",((INDEX(Historical!$C$7:$C$1044,MATCH(B53,Historical!$B$7:$B$1044,0))/INDEX(Historical!$H$7:$H$1044,MATCH(B53,Historical!$B$7:$B$1044,0)))^(1/5)-1)*100) -> 6.6996758 | V53: =IF(INDEX(Historical!$M$7:$M$1044,MATCH(B53,Historical!$B$7:$B$1044,0))=0,"n/a",((INDEX(Historical!$C$7:$C$1044,MATCH(B53,Historical!$B$7:$B$1044,0))/INDEX(Historical!$M$7:$M$1044,MATCH(B53,Historical!$B$7:$B$1044,0)))^(1/10)-1)*100) -> 7.0138384 | W53: =IF(OR(U53<=0,U53="n/a",V53<=0,V53="n/a"),"n/a",U53/V53) -> 0.95520818 | X53: =IF(OR(AJ53<=0,AJ53="n/a",U53<=0,U53="n/a"),"n/a",U53/AJ53) -> n/a | Z53: =IF(OR(AC53<0.01,AC53="n/a"),"n/a",M53/AC53*100) -> 40.10989 | AA53: =IF(OR(AC53<0.01,AC53="n/a"),"n/a",I53/AC53) -> 35.796703 | AB53: 12 | AC53: 7.28 | AD53: 2.13 | AE53: 4.58 | AF53: 7.52 | AG53: 22.4 | AH53: 11.2 | AI53: 14.36 | AJ53: n/a | AK53: 12.8 | AL53: 73600 | AM53: 10.52 | AN53: 0.92 | AO53: =IF(U53="n/a","n/a",IF(AA53<0,"n/a",IF(AA53="n/a","n/a",J53+U53-AA53))) -> -27.976536 | AP53: =IF(U53="n/a","n/a",J53+U53) -> 7.8201669 | AQ53: =IF(OR(AC53<0.01,AC53="n/a",AF53="n/a"),"n/a",(I53/SQRT(22.5*AC53*(I53/AF53))-1)*100) -> 245.89093 | AR53: =INDEX(Historical!$C$7:$C$1045,MATCH(B53,Historical!$B$7:$B$1045,0))*IF(AH53="n/a",1.03,IF(AH53<0,1.01,IF(AH53>10,1.1,(1+AH53/100)))) -> 2.86 | AS53: =IF($AI53="n/a",1.03*AR53,IF($AI53<0,1.01*AR53,IF($AI53>10,1.1*AR53,(1+$AI53/100)*AR53))) -> 3.146 | AT53: =IF($AK53="n/a",1.03*AS53,IF($AK53<0,1.01*AS53,IF($AK53>10,1.1*AS53,(1+$AK53/100)*AS53))) -> 3.4606 | AU53: =IF($AK53="n/a",1.03*AT53,IF($AK53<0,1.01*AT53,IF($AK53>10,1.1*AT53,(1+$AK53/100)*AT53))) -> 3.80666 | AV53: =IF($AK53="n/a",1.03*AU53,IF($AK53<0,1.01*AU53,IF($AK53>10,1.1*AU53,(1+$AK53/100)*AU53))) -> 4.187326 | AW53: =SUM(AR53:AV53) -> 17.460586 | AX53: =AW53/I53*100 -> 6.7001481 | AY53: 0.94 | AZ53: 6.9 | BA53: -15.74 | BB53: -5.75 | BC53: -4.55 | BE53: 1993 | BF53: =IF(BE53>2020,0,IF(BE53>2008,1,IF(BE53>2001,2,IF(BE53>1990,3,IF(BE53>1980,4,IF(BE53>1973,5,IF(BE53>1970,6,IF(BE53>1960,7,IF(BE53>1958,8,IF(BE53>1953,9,10)))))))))) -> 3 | BG53: 8.82 | BH53: USD | BI53: Corp
A54: Consolidated Edison, Inc. | B54: ED | C54: Utilities | D54: Multi-Utilities | E54: 52 | F54: 45 | G54: N | H54: Y | I54: 111.49 | J54: =(M54/I54)*100 -> 3.1841421 | K54: 0.8875 | L54: 4 | M54: =K54*L54 -> 3.55 | N54: C15 | O54: 0.85 | P54: 46071 | Q54: 46097 | R54: =(K54-O54)/O54*100 -> 4.4117647 | S54: =IF(INDEX(Historical!$D$7:$D1226,MATCH(B54,Historical!$B$7:$B$1044,0))=0,"n/a",(INDEX(Historical!$C$7:$C$1044,MATCH(B54,Historical!$B$7:$B$1044,0))/INDEX(Historical!$D$7:$D$1044,MATCH(B54,Historical!$B$7:$B$1044,0))-1)*100) -> 2.4096386 | T54: =IF(INDEX(Historical!$F$7:$F$1044,MATCH(B54,Historical!$B$7:$B$1044,0))=0,"n/a",((INDEX(Historical!$C$7:$C$1044,MATCH(B54,Historical!$B$7:$B$1044,0))/INDEX(Historical!$F$7:$F$1044,MATCH(B54,Historical!$B$7:$B$1044,0)))^(1/3)-1)*100) -> 2.4701279 | U54: =IF(INDEX(Historical!$H$7:$H$1044,MATCH(B54,Historical!$B$7:$B$1044,0))=0,"n/a",((INDEX(Historical!$C$7:$C$1044,MATCH(B54,Historical!$B$7:$B$1044,0))/INDEX(Historical!$H$7:$H$1044,MATCH(B54,Historical!$B$7:$B$1044,0)))^(1/5)-1)*100) -> 2.1295688 | V54: =IF(INDEX(Historical!$M$7:$M$1044,MATCH(B54,Historical!$B$7:$B$1044,0))=0,"n/a",((INDEX(Historical!$C$7:$C$1044,MATCH(B54,Historical!$B$7:$B$1044,0))/INDEX(Historical!$M$7:$M$1044,MATCH(B54,Historical!$B$7:$B$1044,0)))^(1/10)-1)*100) -> 2.7189466 | W54: =IF(OR(U54<=0,U54="n/a",V54<=0,V54="n/a"),"n/a",U54/V54) -> 0.78323303 | X54: =IF(OR(AJ54<=0,AJ54="n/a",U54<=0,U54="n/a"),"n/a",U54/AJ54) -> 0.18598854 | Z54: =IF(OR(AC54<0.01,AC54="n/a"),"n/a",M54/AC54*100) -> 62.831858 | AA54: =IF(OR(AC54<0.01,AC54="n/a"),"n/a",I54/AC54) -> 19.732743 | AB54: 12 | AC54: 5.65 | AD54: 2.62 | AE54: 2.43 | AF54: 1.66 | AG54: 8.76 | AH54: 7.03 | AI54: 6.35 | AJ54: 11.45 | AK54: 6.57 | AL54: 41080 | AM54: 0.17 | AN54: 1.17 | AO54: =IF(U54="n/a","n/a",IF(AA54<0,"n/a",IF(AA54="n/a","n/a",J54+U54-AA54))) -> -14.419033 | AP54: =IF(U54="n/a","n/a",J54+U54) -> 5.3137108 | AQ54: =IF(OR(AC54<0.01,AC54="n/a",AF54="n/a"),"n/a",(I54/SQRT(22.5*AC54*(I54/AF54))-1)*100) -> 20.65811 | AR54: =INDEX(Historical!$C$7:$C$1045,MATCH(B54,Historical!$B$7:$B$1045,0))*IF(AH54="n/a",1.03,IF(AH54<0,1.01,IF(AH54>10,1.1,(1+AH54/100)))) -> 3.63902 | AS54: =IF($AI54="n/a",1.03*AR54,IF($AI54<0,1.01*AR54,IF($AI54>10,1.1*AR54,(1+$AI54/100)*AR54))) -> 3.8700978 | AT54: =IF($AK54="n/a",1.03*AS54,IF($AK54<0,1.01*AS54,IF($AK54>10,1.1*AS54,(1+$AK54/100)*AS54))) -> 4.1243632 | AU54: =IF($AK54="n/a",1.03*AT54,IF($AK54<0,1.01*AT54,IF($AK54>10,1.1*AT54,(1+$AK54/100)*AT54))) -> 4.3953339 | AV54: =IF($AK54="n/a",1.03*AU54,IF($AK54<0,1.01*AU54,IF($AK54>10,1.1*AU54,(1+$AK54/100)*AU54))) -> 4.6841073 | AW54: =SUM(AR54:AV54) -> 20.712922 | AX54: =AW54/I54*100 -> 18.578278 | AY54: 0.28 | AZ54: 17.41 | BA54: -4.08 | BB54: -0.19 | BC54: 7.64 | BE54: 1975 | BF54: =IF(BE54>2020,0,IF(BE54>2008,1,IF(BE54>2001,2,IF(BE54>1990,3,IF(BE54>1980,4,IF(BE54>1973,5,IF(BE54>1970,6,IF(BE54>1960,7,IF(BE54>1958,8,IF(BE54>1953,9,10)))))))))) -> 5 | BG54: 2.79 | BH54: USD | BI54: Corp
A55: Eagle Financial Services, Inc. | B55: EFSI | C55: Financials | D55: Banks | E55: 39 | F55: 73 | G55: - | H55: - | I55: 37.68 | J55: =(M55/I55)*100 -> 3.2908705 | K55: 0.31 | L55: 4 | M55: =K55*L55 -> 1.24 | N55: B16 | O55: 0.3 | P55: 45604 | Q55: 45611 | R55: =(K55-O55)/O55*100 -> 3.3333333 | S55: =IF(INDEX(Historical!$D$7:$D1228,MATCH(B55,Historical!$B$7:$B$1044,0))=0,"n/a",(INDEX(Historical!$C$7:$C$1044,MATCH(B55,Historical!$B$7:$B$1044,0))/INDEX(Historical!$D$7:$D$1044,MATCH(B55,Historical!$B$7:$B$1044,0))-1)*100) -> 2.4793388 | T55: =IF(INDEX(Historical!$F$7:$F$1044,MATCH(B55,Historical!$B$7:$B$1044,0))=0,"n/a",((INDEX(Historical!$C$7:$C$1044,MATCH(B55,Historical!$B$7:$B$1044,0))/INDEX(Historical!$F$7:$F$1044,MATCH(B55,Historical!$B$7:$B$1044,0)))^(1/3)-1)*100) -> 2.5434555 | U55: =IF(INDEX(Historical!$H$7:$H$1044,MATCH(B55,Historical!$B$7:$B$1044,0))=0,"n/a",((INDEX(Historical!$C$7:$C$1044,MATCH(B55,Historical!$B$7:$B$1044,0))/INDEX(Historical!$H$7:$H$1044,MATCH(B55,Historical!$B$7:$B$1044,0)))^(1/5)-1)*100) -> 3.5804204 | V55: =IF(INDEX(Historical!$M$7:$M$1044,MATCH(B55,Historical!$B$7:$B$1044,0))=0,"n/a",((INDEX(Historical!$C$7:$C$1044,MATCH(B55,Historical!$B$7:$B$1044,0))/INDEX(Historical!$M$7:$M$1044,MATCH(B55,Historical!$B$7:$B$1044,0)))^(1/10)-1)*100) -> 4.4800014 | W55: =IF(OR(U55<=0,U55="n/a",V55<=0,V55="n/a"),"n/a",U55/V55) -> 0.79920072 | X55: =IF(OR(AJ55<=0,AJ55="n/a",U55<=0,U55="n/a"),"n/a",U55/AJ55) -> n/a | Y55: 2025 = Year 39 | Z55: =IF(OR(AC55<0.01,AC55="n/a"),"n/a",M55/AC55*100) -> 35.227273 | AA55: =IF(OR(AC55<0.01,AC55="n/a"),"n/a",I55/AC55) -> 10.704545 | AB55: 12 | AC55: 3.52 | AD55: 0.8 | AE55: 1.71 | AF55: 1.07 | AG55: 10.32 | AH55: 6.09 | AI55: 9.74 | AJ55: -13.47 | AK55: 11.79 | AL55: 203.94 | AM55: 15.44 | AN55: 0.16 | AO55: =IF(U55="n/a","n/a",IF(AA55<0,"n/a",IF(AA55="n/a","n/a",J55+U55-AA55))) -> -3.8332546 | AP55: =IF(U55="n/a","n/a",J55+U55) -> 6.8712908 | AQ55: =IF(OR(AC55<0.01,AC55="n/a",AF55="n/a"),"n/a",(I55/SQRT(22.5*AC55*(I55/AF55))-1)*100) -> -28.651517 | AR55: =INDEX(Historical!$C$7:$C$1045,MATCH(B55,Historical!$B$7:$B$1045,0))*IF(AH55="n/a",1.03,IF(AH55<0,1.01,IF(AH55>10,1.1,(1+AH55/100)))) -> 1.315516 | AS55: =IF($AI55="n/a",1.03*AR55,IF($AI55<0,1.01*AR55,IF($AI55>10,1.1*AR55,(1+$AI55/100)*AR55))) -> 1.4436473 | AT55: =IF($AK55="n/a",1.03*AS55,IF($AK55<0,1.01*AS55,IF($AK55>10,1.1*AS55,(1+$AK55/100)*AS55))) -> 1.588012 | AU55: =IF($AK55="n/a",1.03*AT55,IF($AK55<0,1.01*AT55,IF($AK55>10,1.1*AT55,(1+$AK55/100)*AT55))) -> 1.7468132 | AV55: =IF($AK55="n/a",1.03*AU55,IF($AK55<0,1.01*AU55,IF($AK55>10,1.1*AU55,(1+$AK55/100)*AU55))) -> 1.9214945 | AW55: =SUM(AR55:AV55) -> 8.0154829 | AX55: =AW55/I55*100 -> 21.272513 | AY55: 0.21 | AZ55: 31.29 | BA55: -8.37 | BB55: 4.71 | BC55: 2.17 | BD55: OTC | BE55: 1987 | BF55: =IF(BE55>2020,0,IF(BE55>2008,1,IF(BE55>2001,2,IF(BE55>1990,3,IF(BE55>1980,4,IF(BE55>1973,5,IF(BE55>1970,6,IF(BE55>1960,7,IF(BE55>1958,8,IF(BE55>1953,9,10)))))))))) -> 4 | BG55: 1.01 | BH55: USD | BI55: Corp
A56: Emerson Electric Co. | B56: EMR | C56: Industrials | D56: Electrical Equipment | E56: 69 | F56: 7 | G56: N | H56: N | I56: 140.44 | J56: =(M56/I56)*100 -> 1.5807462 | K56: 0.555 | L56: 4 | M56: =K56*L56 -> 2.22 | N56: C11 | O56: 0.5275 | P56: 45975 | Q56: 46001 | R56: =(K56-O56)/O56*100 -> 5.2132701 | S56: =IF(INDEX(Historical!$D$7:$D1234,MATCH(B56,Historical!$B$7:$B$1044,0))=0,"n/a",(INDEX(Historical!$C$7:$C$1044,MATCH(B56,Historical!$B$7:$B$1044,0))/INDEX(Historical!$D$7:$D$1044,MATCH(B56,Historical!$B$7:$B$1044,0))-1)*100) -> 1.6646849 | T56: =IF(INDEX(Historical!$F$7:$F$1044,MATCH(B56,Historical!$B$7:$B$1044,0))=0,"n/a",((INDEX(Historical!$C$7:$C$1044,MATCH(B56,Historical!$B$7:$B$1044,0))/INDEX(Historical!$F$7:$F$1044,MATCH(B56,Historical!$B$7:$B$1044,0)))^(1/3)-1)*100) -> 1.1568637 | U56: =IF(INDEX(Historical!$H$7:$H$1044,MATCH(B56,Historical!$B$7:$B$1044,0))=0,"n/a",((INDEX(Historical!$C$7:$C$1044,MATCH(B56,Historical!$B$7:$B$1044,0))/INDEX(Historical!$H$7:$H$1044,MATCH(B56,Historical!$B$7:$B$1044,0)))^(1/5)-1)*100) -> 1.2880824 | V56: =IF(INDEX(Historical!$M$7:$M$1044,MATCH(B56,Historical!$B$7:$B$1044,0))=0,"n/a",((INDEX(Historical!$C$7:$C$1044,MATCH(B56,Historical!$B$7:$B$1044,0))/INDEX(Historical!$M$7:$M$1044,MATCH(B56,Historical!$B$7:$B$1044,0)))^(1/10)-1)*100) -> 1.2650256 | W56: =IF(OR(U56<=0,U56="n/a",V56<=0,V56="n/a"),"n/a",U56/V56) -> 1.0182264 | X56: =IF(OR(AJ56<=0,AJ56="n/a",U56<=0,U56="n/a"),"n/a",U56/AJ56) -> 0.28309504 | Z56: =IF(OR(AC56<0.01,AC56="n/a"),"n/a",M56/AC56*100) -> 54.278729 | AA56: =IF(OR(AC56<0.01,AC56="n/a"),"n/a",I56/AC56) -> 34.337408 | AB56: 9 | AC56: 4.09 | AD56: 2.02 | AE56: 4.34 | AF56: 3.89 | AG56: 11.31 | AH56: 8.29 | AI56: 10.34 | AJ56: 4.55 | AK56: 9.72 | AL56: 78970 | AM56: 0.27 | AN56: 0.69 | AO56: =IF(U56="n/a","n/a",IF(AA56<0,"n/a",IF(AA56="n/a","n/a",J56+U56-AA56))) -> -31.46858 | AP56: =IF(U56="n/a","n/a",J56+U56) -> 2.8688287 | AQ56: =IF(OR(AC56<0.01,AC56="n/a",AF56="n/a"),"n/a",(I56/SQRT(22.5*AC56*(I56/AF56))-1)*100) -> 143.65049 | AR56: =INDEX(Historical!$C$7:$C$1045,MATCH(B56,Historical!$B$7:$B$1045,0))*IF(AH56="n/a",1.03,IF(AH56<0,1.01,IF(AH56>10,1.1,(1+AH56/100)))) -> 2.3146988 | AS56: =IF($AI56="n/a",1.03*AR56,IF($AI56<0,1.01*AR56,IF($AI56>10,1.1*AR56,(1+$AI56/100)*AR56))) -> 2.5461686 | AT56: =IF($AK56="n/a",1.03*AS56,IF($AK56<0,1.01*AS56,IF($AK56>10,1.1*AS56,(1+$AK56/100)*AS56))) -> 2.7936562 | AU56: =IF($AK56="n/a",1.03*AT56,IF($AK56<0,1.01*AT56,IF($AK56>10,1.1*AT56,(1+$AK56/100)*AT56))) -> 3.0651996 | AV56: =IF($AK56="n/a",1.03*AU56,IF($AK56<0,1.01*AU56,IF($AK56>10,1.1*AU56,(1+$AK56/100)*AU56))) -> 3.363137 | AW56: =SUM(AR56:AV56) -> 14.08286 | AX56: =AW56/I56*100 -> 10.02767 | AY56: 1.25 | AZ56: 36.56 | BA56: -14.96 | BB56: 0.86 | BC56: 1.95 | BE56: 1958 | BF56: =IF(BE56>2020,0,IF(BE56>2008,1,IF(BE56>2001,2,IF(BE56>1990,3,IF(BE56>1980,4,IF(BE56>1973,5,IF(BE56>1970,6,IF(BE56>1960,7,IF(BE56>1958,8,IF(BE56>1953,9,10)))))))))) -> 9 | BG56: 5.45 | BH56: USD | BI56: Corp
A57: Enterprise Products Partners L.P. | B57: EPD | C57: Energy | D57: Oil, Gas & Consumable Fuels | E57: 29 | F57: 128 | G57: N | H57: - | I57: 38.7 | J57: =(M57/I57)*100 -> 5.6847545 | K57: 0.55 | L57: 4 | M57: =K57*L57 -> 2.2 | N57: B08 | O57: 0.545 | P57: 46052 | Q57: 46066 | R57: =(K57-O57)/O57*100 -> 0.91743119 | S57: =IF(INDEX(Historical!$D$7:$D1237,MATCH(B57,Historical!$B$7:$B$1044,0))=0,"n/a",(INDEX(Historical!$C$7:$C$1044,MATCH(B57,Historical!$B$7:$B$1044,0))/INDEX(Historical!$D$7:$D$1044,MATCH(B57,Historical!$B$7:$B$1044,0))-1)*100) -> 3.8461538 | T57: =IF(INDEX(Historical!$F$7:$F$1044,MATCH(B57,Historical!$B$7:$B$1044,0))=0,"n/a",((INDEX(Historical!$C$7:$C$1044,MATCH(B57,Historical!$B$7:$B$1044,0))/INDEX(Historical!$F$7:$F$1044,MATCH(B57,Historical!$B$7:$B$1044,0)))^(1/3)-1)*100) -> 4.7366392 | U57: =IF(INDEX(Historical!$H$7:$H$1044,MATCH(B57,Historical!$B$7:$B$1044,0))=0,"n/a",((INDEX(Historical!$C$7:$C$1044,MATCH(B57,Historical!$B$7:$B$1044,0))/INDEX(Historical!$H$7:$H$1044,MATCH(B57,Historical!$B$7:$B$1044,0)))^(1/5)-1)*100) -> 3.945753 | V57: =IF(INDEX(Historical!$M$7:$M$1044,MATCH(B57,Historical!$B$7:$B$1044,0))=0,"n/a",((INDEX(Historical!$C$7:$C$1044,MATCH(B57,Historical!$B$7:$B$1044,0))/INDEX(Historical!$M$7:$M$1044,MATCH(B57,Historical!$B$7:$B$1044,0)))^(1/10)-1)*100) -> 3.6448388 | W57: =IF(OR(U57<=0,U57="n/a",V57<=0,V57="n/a"),"n/a",U57/V57) -> 1.082559 | X57: =IF(OR(AJ57<=0,AJ57="n/a",U57<=0,U57="n/a"),"n/a",U57/AJ57) -> 0.43217448 | Z57: =IF(OR(AC57<0.01,AC57="n/a"),"n/a",M57/AC57*100) -> 81.784387 | AA57: =IF(OR(AC57<0.01,AC57="n/a"),"n/a",I57/AC57) -> 14.386617 | AB57: 12 | AC57: 2.69 | AD57: 1.41 | AE57: 1.64 | AF57: 2.81 | AG57: 19.7 | AH57: 7.92 | AI57: 10.89 | AJ57: 9.13 | AK57: 8.63 | AL57: 83660 | AM57: 33.28 | AN57: 1.15 | AO57: =IF(U57="n/a","n/a",IF(AA57<0,"n/a",IF(AA57="n/a","n/a",J57+U57-AA57))) -> -4.7561096 | AP57: =IF(U57="n/a","n/a",J57+U57) -> 9.6305075 | AQ57: =IF(OR(AC57<0.01,AC57="n/a",AF57="n/a"),"n/a",(I57/SQRT(22.5*AC57*(I57/AF57))-1)*100) -> 34.042106 | AR57: =INDEX(Historical!$C$7:$C$1045,MATCH(B57,Historical!$B$7:$B$1045,0))*IF(AH57="n/a",1.03,IF(AH57<0,1.01,IF(AH57>10,1.1,(1+AH57/100)))) -> 2.331072 | AS57: =IF($AI57="n/a",1.03*AR57,IF($AI57<0,1.01*AR57,IF($AI57>10,1.1*AR57,(1+$AI57/100)*AR57))) -> 2.5641792 | AT57: =IF($AK57="n/a",1.03*AS57,IF($AK57<0,1.01*AS57,IF($AK57>10,1.1*AS57,(1+$AK57/100)*AS57))) -> 2.7854679 | AU57: =IF($AK57="n/a",1.03*AT57,IF($AK57<0,1.01*AT57,IF($AK57>10,1.1*AT57,(1+$AK57/100)*AT57))) -> 3.0258537 | AV57: =IF($AK57="n/a",1.03*AU57,IF($AK57<0,1.01*AU57,IF($AK57>10,1.1*AU57,(1+$AK57/100)*AU57))) -> 3.2869849 | AW57: =SUM(AR57:AV57) -> 13.993558 | AX57: =AW57/I57*100 -> 36.159064 | AY57: 0.5 | AZ57: 30.5 | BA57: -2.6 | BB57: 3.28 | BC57: 15.92 | BE57: 1998 | BF57: =IF(BE57>2020,0,IF(BE57>2008,1,IF(BE57>2001,2,IF(BE57>1990,3,IF(BE57>1980,4,IF(BE57>1973,5,IF(BE57>1970,6,IF(BE57>1960,7,IF(BE57>1958,8,IF(BE57>1953,9,10)))))))))) -> 3 | BG57: 7.42 | BH57: USD | BI57: LP
A58: Erie Indemnity Company | B58: ERIE | C58: Financials | D58: Insurance | E58: 36 | F58: 81 | G58: - | H58: - | I58: 218.93 | J58: =(M58/I58)*100 -> 2.672087 | K58: 1.4625 | L58: 4 | M58: =K58*L58 -> 5.85 | N58: A23 | O58: 1.365 | P58: 46028 | Q58: 46043 | R58: =(K58-O58)/O58*100 -> 7.1428571 | S58: =IF(INDEX(Historical!$D$7:$D1242,MATCH(B58,Historical!$B$7:$B$1044,0))=0,"n/a",(INDEX(Historical!$C$7:$C$1044,MATCH(B58,Historical!$B$7:$B$1044,0))/INDEX(Historical!$D$7:$D$1044,MATCH(B58,Historical!$B$7:$B$1044,0))-1)*100) -> 7.0588235 | T58: =IF(INDEX(Historical!$F$7:$F$1044,MATCH(B58,Historical!$B$7:$B$1044,0))=0,"n/a",((INDEX(Historical!$C$7:$C$1044,MATCH(B58,Historical!$B$7:$B$1044,0))/INDEX(Historical!$F$7:$F$1044,MATCH(B58,Historical!$B$7:$B$1044,0)))^(1/3)-1)*100) -> 7.1362787 | U58: =IF(INDEX(Historical!$H$7:$H$1044,MATCH(B58,Historical!$B$7:$B$1044,0))=0,"n/a",((INDEX(Historical!$C$7:$C$1044,MATCH(B58,Historical!$B$7:$B$1044,0))/INDEX(Historical!$H$7:$H$1044,MATCH(B58,Historical!$B$7:$B$1044,0)))^(1/5)-1)*100) -> 7.1818053 | V58: =IF(INDEX(Historical!$M$7:$M$1044,MATCH(B58,Historical!$B$7:$B$1044,0))=0,"n/a",((INDEX(Historical!$C$7:$C$1044,MATCH(B58,Historical!$B$7:$B$1044,0))/INDEX(Historical!$M$7:$M$1044,MATCH(B58,Historical!$B$7:$B$1044,0)))^(1/10)-1)*100) -> 7.2009302 | W58: =IF(OR(U58<=0,U58="n/a",V58<=0,V58="n/a"),"n/a",U58/V58) -> 0.9973441 | X58: =IF(OR(AJ58<=0,AJ58="n/a",U58<=0,U58="n/a"),"n/a",U58/AJ58) -> 0.521176 | Z58: =IF(OR(AC58<0.01,AC58="n/a"),"n/a",M58/AC58*100) -> 53.917051 | AA58: =IF(OR(AC58<0.01,AC58="n/a"),"n/a",I58/AC58) -> 20.17788 | AB58: 12 | AC58: 10.85 | AD58: n/a | AE58: 2.49 | AF58: 4.33 | AG58: 25.85 | AH58: 18.24 | AI58: n/a | AJ58: 13.78 | AK58: n/a | AL58: 10200 | AM58: 45.95 | AN58: 0 | AO58: =IF(U58="n/a","n/a",IF(AA58<0,"n/a",IF(AA58="n/a","n/a",J58+U58-AA58))) -> -10.323988 | AP58: =IF(U58="n/a","n/a",J58+U58) -> 9.8538922 | AQ58: =IF(OR(AC58<0.01,AC58="n/a",AF58="n/a"),"n/a",(I58/SQRT(22.5*AC58*(I58/AF58))-1)*100) -> 97.056361 | AR58: =INDEX(Historical!$C$7:$C$1045,MATCH(B58,Historical!$B$7:$B$1045,0))*IF(AH58="n/a",1.03,IF(AH58<0,1.01,IF(AH58>10,1.1,(1+AH58/100)))) -> 6.006 | AS58: =IF($AI58="n/a",1.03*AR58,IF($AI58<0,1.01*AR58,IF($AI58>10,1.1*AR58,(1+$AI58/100)*AR58))) -> 6.18618 | AT58: =IF($AK58="n/a",1.03*AS58,IF($AK58<0,1.01*AS58,IF($AK58>10,1.1*AS58,(1+$AK58/100)*AS58))) -> 6.3717654 | AU58: =IF($AK58="n/a",1.03*AT58,IF($AK58<0,1.01*AT58,IF($AK58>10,1.1*AT58,(1+$AK58/100)*AT58))) -> 6.5629184 | AV58: =IF($AK58="n/a",1.03*AU58,IF($AK58<0,1.01*AU58,IF($AK58>10,1.1*AU58,(1+$AK58/100)*AU58))) -> 6.7598059 | AW58: =SUM(AR58:AV58) -> 31.88667 | AX58: =AW58/I58*100 -> 14.564779 | AY58: 0.34 | AZ58: 0.45 | BA58: -42.49 | BB58: -12.57 | BC58: -26.13 | BE58: 1991 | BF58: =IF(BE58>2020,0,IF(BE58>2008,1,IF(BE58>2001,2,IF(BE58>1990,3,IF(BE58>1980,4,IF(BE58>1973,5,IF(BE58>1970,6,IF(BE58>1960,7,IF(BE58>1958,8,IF(BE58>1953,9,10)))))))))) -> 3 | BG58: 18.01 | BH58: USD | BI58: Corp
A59: Eversource Energy | B59: ES | C59: Utilities | D59: Electric Utilities | E59: 28 | F59: 134 | G59: N | H59: Y | I59: 70.7 | J59: =(M59/I59)*100 -> 4.4554455 | K59: 0.7875 | L59: 4 | M59: =K59*L59 -> 3.15 | N59: C31 | O59: 0.7525 | P59: 46086 | Q59: 46112 | R59: =(K59-O59)/O59*100 -> 4.6511628 | S59: =IF(INDEX(Historical!$D$7:$D1243,MATCH(B59,Historical!$B$7:$B$1044,0))=0,"n/a",(INDEX(Historical!$C$7:$C$1044,MATCH(B59,Historical!$B$7:$B$1044,0))/INDEX(Historical!$D$7:$D$1044,MATCH(B59,Historical!$B$7:$B$1044,0))-1)*100) -> 5.2447552 | T59: =IF(INDEX(Historical!$F$7:$F$1044,MATCH(B59,Historical!$B$7:$B$1044,0))=0,"n/a",((INDEX(Historical!$C$7:$C$1044,MATCH(B59,Historical!$B$7:$B$1044,0))/INDEX(Historical!$F$7:$F$1044,MATCH(B59,Historical!$B$7:$B$1044,0)))^(1/3)-1)*100) -> 5.6838855 | U59: =IF(INDEX(Historical!$H$7:$H$1044,MATCH(B59,Historical!$B$7:$B$1044,0))=0,"n/a",((INDEX(Historical!$C$7:$C$1044,MATCH(B59,Historical!$B$7:$B$1044,0))/INDEX(Historical!$H$7:$H$1044,MATCH(B59,Historical!$B$7:$B$1044,0)))^(1/5)-1)*100) -> 5.8054717 | V59: =IF(INDEX(Historical!$M$7:$M$1044,MATCH(B59,Historical!$B$7:$B$1044,0))=0,"n/a",((INDEX(Historical!$C$7:$C$1044,MATCH(B59,Historical!$B$7:$B$1044,0))/INDEX(Historical!$M$7:$M$1044,MATCH(B59,Historical!$B$7:$B$1044,0)))^(1/10)-1)*100) -> 6.068152 | W59: =IF(OR(U59<=0,U59="n/a",V59<=0,V59="n/a"),"n/a",U59/V59) -> 0.95671164 | X59: =IF(OR(AJ59<=0,AJ59="n/a",U59<=0,U59="n/a"),"n/a",U59/AJ59) -> 1.1229152 | Z59: =IF(OR(AC59<0.01,AC59="n/a"),"n/a",M59/AC59*100) -> 69.078947 | AA59: =IF(OR(AC59<0.01,AC59="n/a"),"n/a",I59/AC59) -> 15.504386 | AB59: 12 | AC59: 4.56 | AD59: 4.28 | AE59: 1.96 | AF59: 1.64 | AG59: 10.84 | AH59: -0.98 | AI59: 5.29 | AJ59: 5.17 | AK59: 3.33 | AL59: 26570 | AM59: 0.15 | AN59: 1.87 | AO59: =IF(U59="n/a","n/a",IF(AA59<0,"n/a",IF(AA59="n/a","n/a",J59+U59-AA59))) -> -5.2434687 | AP59: =IF(U59="n/a","n/a",J59+U59) -> 10.260917 | AQ59: =IF(OR(AC59<0.01,AC59="n/a",AF59="n/a"),"n/a",(I59/SQRT(22.5*AC59*(I59/AF59))-1)*100) -> 6.3060424 | AR59: =INDEX(Historical!$C$7:$C$1045,MATCH(B59,Historical!$B$7:$B$1045,0))*IF(AH59="n/a",1.03,IF(AH59<0,1.01,IF(AH59>10,1.1,(1+AH59/100)))) -> 3.0401 | AS59: =IF($AI59="n/a",1.03*AR59,IF($AI59<0,1.01*AR59,IF($AI59>10,1.1*AR59,(1+$AI59/100)*AR59))) -> 3.2009213 | AT59: =IF($AK59="n/a",1.03*AS59,IF($AK59<0,1.01*AS59,IF($AK59>10,1.1*AS59,(1+$AK59/100)*AS59))) -> 3.307512 | AU59: =IF($AK59="n/a",1.03*AT59,IF($AK59<0,1.01*AT59,IF($AK59>10,1.1*AT59,(1+$AK59/100)*AT59))) -> 3.4176521 | AV59: =IF($AK59="n/a",1.03*AU59,IF($AK59<0,1.01*AU59,IF($AK59>10,1.1*AU59,(1+$AK59/100)*AU59))) -> 3.5314599 | AW59: =SUM(AR59:AV59) -> 16.497645 | AX59: =AW59/I59*100 -> 23.334718 | AY59: 0.74 | AZ59: 21.83 | BA59: -7.47 | BB59: -0.25 | BC59: 2.46 | BE59: 1999 | BF59: =IF(BE59>2020,0,IF(BE59>2008,1,IF(BE59>2001,2,IF(BE59>1990,3,IF(BE59>1980,4,IF(BE59>1973,5,IF(BE59>1970,6,IF(BE59>1960,7,IF(BE59>1958,8,IF(BE59>1953,9,10)))))))))) -> 3 | BG59: 2.74 | BH59: USD | BI59: Corp
A60: Essex Property Trust, Inc. | B60: ESS | C60: Real Estate | D60: Residential REITs | E60: 32 | F60: 113 | G60: N | H60: Y | I60: 263.21 | J60: =(M60/I60)*100 -> 3.9360207 | K60: 2.59 | L60: 4 | M60: =K60*L60 -> 10.36 | N60: A16 | O60: 2.57 | P60: 46112 | Q60: 46127 | R60: =(K60-O60)/O60*100 -> 0.77821012 | S60: =IF(INDEX(Historical!$D$7:$D1245,MATCH(B60,Historical!$B$7:$B$1044,0))=0,"n/a",(INDEX(Historical!$C$7:$C$1044,MATCH(B60,Historical!$B$7:$B$1044,0))/INDEX(Historical!$D$7:$D$1044,MATCH(B60,Historical!$B$7:$B$1044,0))-1)*100) -> 5.1759834 | T60: =IF(INDEX(Historical!$F$7:$F$1044,MATCH(B60,Historical!$B$7:$B$1044,0))=0,"n/a",((INDEX(Historical!$C$7:$C$1044,MATCH(B60,Historical!$B$7:$B$1044,0))/INDEX(Historical!$F$7:$F$1044,MATCH(B60,Historical!$B$7:$B$1044,0)))^(1/3)-1)*100) -> 5.3475995 | U60: =IF(INDEX(Historical!$H$7:$H$1044,MATCH(B60,Historical!$B$7:$B$1044,0))=0,"n/a",((INDEX(Historical!$C$7:$C$1044,MATCH(B60,Historical!$B$7:$B$1044,0))/INDEX(Historical!$H$7:$H$1044,MATCH(B60,Historical!$B$7:$B$1044,0)))^(1/5)-1)*100) -> 4.4242919 | V60: =IF(INDEX(Historical!$M$7:$M$1044,MATCH(B60,Historical!$B$7:$B$1044,0))=0,"n/a",((INDEX(Historical!$C$7:$C$1044,MATCH(B60,Historical!$B$7:$B$1044,0))/INDEX(Historical!$M$7:$M$1044,MATCH(B60,Historical!$B$7:$B$1044,0)))^(1/10)-1)*100) -> 6.1000868 | W60: =IF(OR(U60<=0,U60="n/a",V60<=0,V60="n/a"),"n/a",U60/V60) -> 0.72528342 | X60: =IF(OR(AJ60<=0,AJ60="n/a",U60<=0,U60="n/a"),"n/a",U60/AJ60) -> 1.1989951 | Z60: =IF(OR(AC60<0.01,AC60="n/a"),"n/a",M60/AC60*100) -> 116.53543 | AA60: =IF(OR(AC60<0.01,AC60="n/a"),"n/a",I60/AC60) -> 29.607424 | AB60: 12 | AC60: 8.89 | AD60: n/a | AE60: 9.2 | AF60: 3.11 | AG60: 10.41 | AH60: -44.91 | AI60: 5.89 | AJ60: 3.69 | AK60: -13.97 | AL60: 17550 | AM60: 0.72 | AN60: 1.26 | AO60: =IF(U60="n/a","n/a",IF(AA60<0,"n/a",IF(AA60="n/a","n/a",J60+U60-AA60))) -> -21.247112 | AP60: =IF(U60="n/a","n/a",J60+U60) -> 8.3603125 | AQ60: =IF(OR(AC60<0.01,AC60="n/a",AF60="n/a"),"n/a",(I60/SQRT(22.5*AC60*(I60/AF60))-1)*100) -> 102.29691 | AR60: =INDEX(Historical!$C$7:$C$1045,MATCH(B60,Historical!$B$7:$B$1045,0))*IF(AH60="n/a",1.03,IF(AH60<0,1.01,IF(AH60>10,1.1,(1+AH60/100)))) -> 10.2616 | AS60: =IF($AI60="n/a",1.03*AR60,IF($AI60<0,1.01*AR60,IF($AI60>10,1.1*AR60,(1+$AI60/100)*AR60))) -> 10.866008 | AT60: =IF($AK60="n/a",1.03*AS60,IF($AK60<0,1.01*AS60,IF($AK60>10,1.1*AS60,(1+$AK60/100)*AS60))) -> 10.974668 | AU60: =IF($AK60="n/a",1.03*AT60,IF($AK60<0,1.01*AT60,IF($AK60>10,1.1*AT60,(1+$AK60/100)*AT60))) -> 11.084415 | AV60: =IF($AK60="n/a",1.03*AU60,IF($AK60<0,1.01*AU60,IF($AK60>10,1.1*AU60,(1+$AK60/100)*AU60))) -> 11.195259 | AW60: =SUM(AR60:AV60) -> 54.381951 | AX60: =AW60/I60*100 -> 20.66105 | AY60: 0.74 | AZ60: 10.38 | BA60: -10.5 | BB60: 4.51 | BC60: 1.77 | BE60: 1995 | BF60: =IF(BE60>2020,0,IF(BE60>2008,1,IF(BE60>2001,2,IF(BE60>1990,3,IF(BE60>1980,4,IF(BE60>1973,5,IF(BE60>1970,6,IF(BE60>1960,7,IF(BE60>1958,8,IF(BE60>1953,9,10)))))))))) -> 3 | BG60: 4.36 | BH60: USD | BI60: REIT
A61: Expeditors International of Washington, Inc. | B61: EXPD | C61: Industrials | D61: Air Freight & Logistics | E61: 31 | F61: 115 | G61: - | H61: - | I61: 147.89 | J61: =(M61/I61)*100 -> 1.0413145 | K61: 0.77 | L61: 2 | M61: =K61*L61 -> 1.54 | N61: JnDe | O61: 0.73 | P61: 45810 | Q61: 45824 | R61: =(K61-O61)/O61*100 -> 5.4794521 | S61: =IF(INDEX(Historical!$D$7:$D1251,MATCH(B61,Historical!$B$7:$B$1044,0))=0,"n/a",(INDEX(Historical!$C$7:$C$1044,MATCH(B61,Historical!$B$7:$B$1044,0))/INDEX(Historical!$D$7:$D$1044,MATCH(B61,Historical!$B$7:$B$1044,0))-1)*100) -> 5.4794521 | T61: =IF(INDEX(Historical!$F$7:$F$1044,MATCH(B61,Historical!$B$7:$B$1044,0))=0,"n/a",((INDEX(Historical!$C$7:$C$1044,MATCH(B61,Historical!$B$7:$B$1044,0))/INDEX(Historical!$F$7:$F$1044,MATCH(B61,Historical!$B$7:$B$1044,0)))^(1/3)-1)*100) -> 4.7462879 | U61: =IF(INDEX(Historical!$H$7:$H$1044,MATCH(B61,Historical!$B$7:$B$1044,0))=0,"n/a",((INDEX(Historical!$C$7:$C$1044,MATCH(B61,Historical!$B$7:$B$1044,0))/INDEX(Historical!$H$7:$H$1044,MATCH(B61,Historical!$B$7:$B$1044,0)))^(1/5)-1)*100) -> 8.1676704 | V61: =IF(INDEX(Historical!$M$7:$M$1044,MATCH(B61,Historical!$B$7:$B$1044,0))=0,"n/a",((INDEX(Historical!$C$7:$C$1044,MATCH(B61,Historical!$B$7:$B$1044,0))/INDEX(Historical!$M$7:$M$1044,MATCH(B61,Historical!$B$7:$B$1044,0)))^(1/10)-1)*100) -> 7.8993485 | W61: =IF(OR(U61<=0,U61="n/a",V61<=0,V61="n/a"),"n/a",U61/V61) -> 1.0339676 | X61: =IF(OR(AJ61<=0,AJ61="n/a",U61<=0,U61="n/a"),"n/a",U61/AJ61) -> 1.0391438 | Z61: =IF(OR(AC61<0.01,AC61="n/a"),"n/a",M61/AC61*100) -> 25.882353 | AA61: =IF(OR(AC61<0.01,AC61="n/a"),"n/a",I61/AC61) -> 24.855462 | AB61: 12 | AC61: 5.95 | AD61: 4.43 | AE61: 1.78 | AF61: 8.41 | AG61: 35.4 | AH61: 1.72 | AI61: 6.95 | AJ61: 7.86 | AK61: 5.16 | AL61: 19670 | AM61: 0.59 | AN61: 0.24 | AO61: =IF(U61="n/a","n/a",IF(AA61<0,"n/a",IF(AA61="n/a","n/a",J61+U61-AA61))) -> -15.646477 | AP61: =IF(U61="n/a","n/a",J61+U61) -> 9.2089849 | AQ61: =IF(OR(AC61<0.01,AC61="n/a",AF61="n/a"),"n/a",(I61/SQRT(22.5*AC61*(I61/AF61))-1)*100) -> 204.80189 | AR61: =INDEX(Historical!$C$7:$C$1045,MATCH(B61,Historical!$B$7:$B$1045,0))*IF(AH61="n/a",1.03,IF(AH61<0,1.01,IF(AH61>10,1.1,(1+AH61/100)))) -> 1.566488 | AS61: =IF($AI61="n/a",1.03*AR61,IF($AI61<0,1.01*AR61,IF($AI61>10,1.1*AR61,(1+$AI61/100)*AR61))) -> 1.6753589 | AT61: =IF($AK61="n/a",1.03*AS61,IF($AK61<0,1.01*AS61,IF($AK61>10,1.1*AS61,(1+$AK61/100)*AS61))) -> 1.7618074 | AU61: =IF($AK61="n/a",1.03*AT61,IF($AK61<0,1.01*AT61,IF($AK61>10,1.1*AT61,(1+$AK61/100)*AT61))) -> 1.8527167 | AV61: =IF($AK61="n/a",1.03*AU61,IF($AK61<0,1.01*AU61,IF($AK61>10,1.1*AU61,(1+$AK61/100)*AU61))) -> 1.9483169 | AW61: =SUM(AR61:AV61) -> 8.8046879 | AX61: =AW61/I61*100 -> 5.9535384 | AY61: 1.05 | AZ61: 39.52 | BA61: -11.54 | BB61: 1.69 | BC61: 7.55 | BE61: 1995 | BF61: =IF(BE61>2020,0,IF(BE61>2008,1,IF(BE61>2001,2,IF(BE61>1990,3,IF(BE61>1980,4,IF(BE61>1973,5,IF(BE61>1970,6,IF(BE61>1960,7,IF(BE61>1958,8,IF(BE61>1953,9,10)))))))))) -> 3 | BG61: 16.58 | BH61: USD | BI61: Corp
A62: Fastenal Company | B62: FAST | C62: Industrials | D62: Trading Companies & Distributors | E62: 27 | F62: 140 | G62: - | H62: - | I62: 44.93 | J62: =(M62/I62)*100 -> 2.136657 | K62: 0.24 | L62: 4 | M62: =K62*L62 -> 0.96 | N62: B27 | O62: 0.22 | P62: 46051 | Q62: 46079 | R62: =(K62-O62)/O62*100 -> 9.0909091 | S62: =IF(INDEX(Historical!$D$7:$D1255,MATCH(B62,Historical!$B$7:$B$1044,0))=0,"n/a",(INDEX(Historical!$C$7:$C$1044,MATCH(B62,Historical!$B$7:$B$1044,0))/INDEX(Historical!$D$7:$D$1044,MATCH(B62,Historical!$B$7:$B$1044,0))-1)*100) -> 12.179487 | T62: =IF(INDEX(Historical!$F$7:$F$1044,MATCH(B62,Historical!$B$7:$B$1044,0))=0,"n/a",((INDEX(Historical!$C$7:$C$1044,MATCH(B62,Historical!$B$7:$B$1044,0))/INDEX(Historical!$F$7:$F$1044,MATCH(B62,Historical!$B$7:$B$1044,0)))^(1/3)-1)*100) -> 12.168812 | U62: =IF(INDEX(Historical!$H$7:$H$1044,MATCH(B62,Historical!$B$7:$B$1044,0))=0,"n/a",((INDEX(Historical!$C$7:$C$1044,MATCH(B62,Historical!$B$7:$B$1044,0))/INDEX(Historical!$H$7:$H$1044,MATCH(B62,Historical!$B$7:$B$1044,0)))^(1/5)-1)*100) -> 11.842691 | V62: =IF(INDEX(Historical!$M$7:$M$1044,MATCH(B62,Historical!$B$7:$B$1044,0))=0,"n/a",((INDEX(Historical!$C$7:$C$1044,MATCH(B62,Historical!$B$7:$B$1044,0))/INDEX(Historical!$M$7:$M$1044,MATCH(B62,Historical!$B$7:$B$1044,0)))^(1/10)-1)*100) -> 12.068872 | W62: =IF(OR(U62<=0,U62="n/a",V62<=0,V62="n/a"),"n/a",U62/V62) -> 0.98125915 | X62: =IF(OR(AJ62<=0,AJ62="n/a",U62<=0,U62="n/a"),"n/a",U62/AJ62) -> 1.4896467 | Z62: =IF(OR(AC62<0.01,AC62="n/a"),"n/a",M62/AC62*100) -> 84.955752 | AA62: =IF(OR(AC62<0.01,AC62="n/a"),"n/a",I62/AC62) -> 39.761062 | AB62: 12 | AC62: 1.13 | AD62: 3.13 | AE62: 6.11 | AF62: 12.93 | AG62: 33.85 | AH62: 13.5 | AI62: 10.34 | AJ62: 7.95 | AK62: 10.5 | AL62: 51580 | AM62: 0.2 | AN62: 0.11 | AO62: =IF(U62="n/a","n/a",IF(AA62<0,"n/a",IF(AA62="n/a","n/a",J62+U62-AA62))) -> -25.781713 | AP62: =IF(U62="n/a","n/a",J62+U62) -> 13.979348 | AQ62: =IF(OR(AC62<0.01,AC62="n/a",AF62="n/a"),"n/a",(I62/SQRT(22.5*AC62*(I62/AF62))-1)*100) -> 378.01001 | AR62: =INDEX(Historical!$C$7:$C$1045,MATCH(B62,Historical!$B$7:$B$1045,0))*IF(AH62="n/a",1.03,IF(AH62<0,1.01,IF(AH62>10,1.1,(1+AH62/100)))) -> 0.9625 | AS62: =IF($AI62="n/a",1.03*AR62,IF($AI62<0,1.01*AR62,IF($AI62>10,1.1*AR62,(1+$AI62/100)*AR62))) -> 1.05875 | AT62: =IF($AK62="n/a",1.03*AS62,IF($AK62<0,1.01*AS62,IF($AK62>10,1.1*AS62,(1+$AK62/100)*AS62))) -> 1.164625 | AU62: =IF($AK62="n/a",1.03*AT62,IF($AK62<0,1.01*AT62,IF($AK62>10,1.1*AT62,(1+$AK62/100)*AT62))) -> 1.2810875 | AV62: =IF($AK62="n/a",1.03*AU62,IF($AK62<0,1.01*AU62,IF($AK62>10,1.1*AU62,(1+$AK62/100)*AU62))) -> 1.4091963 | AW62: =SUM(AR62:AV62) -> 5.8761588 | AX62: =AW62/I62*100 -> 13.078475 | AY62: 0.74 | AZ62: 15.29 | BA62: -11.26 | BB62: -1.67 | BC62: 0.05 | BE62: 2000 | BF62: =IF(BE62>2020,0,IF(BE62>2008,1,IF(BE62>2001,2,IF(BE62>1990,3,IF(BE62>1980,4,IF(BE62>1973,5,IF(BE62>1970,6,IF(BE62>1960,7,IF(BE62>1958,8,IF(BE62>1953,9,10)))))))))) -> 3 | BG62: 25.79 | BH62: USD | BI62: Corp
A63: FactSet Research Systems Inc. | B63: FDS | C63: Financials | D63: Capital Markets | E63: 27 | F63: 136 | G63: - | H63: - | I63: 227.58 | J63: =(M63/I63)*100 -> 1.9333861 | K63: 1.1 | L63: 4 | M63: =K63*L63 -> 4.4 | N63: C20 | O63: 1.04 | P63: 45807 | Q63: 45826 | R63: =(K63-O63)/O63*100 -> 5.7692308 | S63: =IF(INDEX(Historical!$D$7:$D1265,MATCH(B63,Historical!$B$7:$B$1044,0))=0,"n/a",(INDEX(Historical!$C$7:$C$1044,MATCH(B63,Historical!$B$7:$B$1044,0))/INDEX(Historical!$D$7:$D$1044,MATCH(B63,Historical!$B$7:$B$1044,0))-1)*100) -> 5.8536585 | T63: =IF(INDEX(Historical!$F$7:$F$1044,MATCH(B63,Historical!$B$7:$B$1044,0))=0,"n/a",((INDEX(Historical!$C$7:$C$1044,MATCH(B63,Historical!$B$7:$B$1044,0))/INDEX(Historical!$F$7:$F$1044,MATCH(B63,Historical!$B$7:$B$1044,0)))^(1/3)-1)*100) -> 7.5362202 | U63: =IF(INDEX(Historical!$H$7:$H$1044,MATCH(B63,Historical!$B$7:$B$1044,0))=0,"n/a",((INDEX(Historical!$C$7:$C$1044,MATCH(B63,Historical!$B$7:$B$1044,0))/INDEX(Historical!$H$7:$H$1044,MATCH(B63,Historical!$B$7:$B$1044,0)))^(1/5)-1)*100) -> 7.4507423 | V63: =IF(INDEX(Historical!$M$7:$M$1044,MATCH(B63,Historical!$B$7:$B$1044,0))=0,"n/a",((INDEX(Historical!$C$7:$C$1044,MATCH(B63,Historical!$B$7:$B$1044,0))/INDEX(Historical!$M$7:$M$1044,MATCH(B63,Historical!$B$7:$B$1044,0)))^(1/10)-1)*100) -> 9.7613303 | W63: =IF(OR(U63<=0,U63="n/a",V63<=0,V63="n/a"),"n/a",U63/V63) -> 0.7632917 | X63: =IF(OR(AJ63<=0,AJ63="n/a",U63<=0,U63="n/a"),"n/a",U63/AJ63) -> 0.74358706 | Z63: =IF(OR(AC63<0.01,AC63="n/a"),"n/a",M63/AC63*100) -> 28.29582 | AA63: =IF(OR(AC63<0.01,AC63="n/a"),"n/a",I63/AC63) -> 14.63537 | AB63: 8 | AC63: 15.55 | AD63: 1.47 | AE63: 3.45 | AF63: 3.92 | AG63: 28.08 | AH63: 4.5 | AI63: 9.4 | AJ63: 10.02 | AK63: 7.98 | AL63: 8290 | AM63: 0.33 | AN63: 0.73 | AO63: =IF(U63="n/a","n/a",IF(AA63<0,"n/a",IF(AA63="n/a","n/a",J63+U63-AA63))) -> -5.2512414 | AP63: =IF(U63="n/a","n/a",J63+U63) -> 9.3841284 | AQ63: =IF(OR(AC63<0.01,AC63="n/a",AF63="n/a"),"n/a",(I63/SQRT(22.5*AC63*(I63/AF63))-1)*100) -> 59.68114 | AR63: =INDEX(Historical!$C$7:$C$1045,MATCH(B63,Historical!$B$7:$B$1045,0))*IF(AH63="n/a",1.03,IF(AH63<0,1.01,IF(AH63>10,1.1,(1+AH63/100)))) -> 4.5353 | AS63: =IF($AI63="n/a",1.03*AR63,IF($AI63<0,1.01*AR63,IF($AI63>10,1.1*AR63,(1+$AI63/100)*AR63))) -> 4.9616182 | AT63: =IF($AK63="n/a",1.03*AS63,IF($AK63<0,1.01*AS63,IF($AK63>10,1.1*AS63,(1+$AK63/100)*AS63))) -> 5.3575553 | AU63: =IF($AK63="n/a",1.03*AT63,IF($AK63<0,1.01*AT63,IF($AK63>10,1.1*AT63,(1+$AK63/100)*AT63))) -> 5.7850882 | AV63: =IF($AK63="n/a",1.03*AU63,IF($AK63<0,1.01*AU63,IF($AK63>10,1.1*AU63,(1+$AK63/100)*AU63))) -> 6.2467383 | AW63: =SUM(AR63:AV63) -> 26.8863 | AX63: =AW63/I63*100 -> 11.814 | AY63: 0.71 | AZ63: 23.02 | BA63: -52.07 | BB63: 4.98 | BC63: -20.13 | BE63: 1999 | BF63: =IF(BE63>2020,0,IF(BE63>2008,1,IF(BE63>2001,2,IF(BE63>1990,3,IF(BE63>1980,4,IF(BE63>1973,5,IF(BE63>1970,6,IF(BE63>1960,7,IF(BE63>1958,8,IF(BE63>1953,9,10)))))))))) -> 3 | BG63: 13.89 | BH63: USD | BI63: Corp
A64: Franklin Electric Co., Inc. | B64: FELE | C64: Industrials | D64: Machinery | E64: 34 | F64: 90 | G64: - | H64: - | I64: 100.19 | J64: =(M64/I64)*100 -> 1.117876 | K64: 0.28 | L64: 4 | M64: =K64*L64 -> 1.12 | N64: B17 | O64: 0.265 | P64: 46058 | Q64: 46072 | R64: =(K64-O64)/O64*100 -> 5.6603774 | S64: =IF(INDEX(Historical!$D$7:$D1267,MATCH(B64,Historical!$B$7:$B$1044,0))=0,"n/a",(INDEX(Historical!$C$7:$C$1044,MATCH(B64,Historical!$B$7:$B$1044,0))/INDEX(Historical!$D$7:$D$1044,MATCH(B64,Historical!$B$7:$B$1044,0))-1)*100) -> 6 | T64: =IF(INDEX(Historical!$F$7:$F$1044,MATCH(B64,Historical!$B$7:$B$1044,0))=0,"n/a",((INDEX(Historical!$C$7:$C$1044,MATCH(B64,Historical!$B$7:$B$1044,0))/INDEX(Historical!$F$7:$F$1044,MATCH(B64,Historical!$B$7:$B$1044,0)))^(1/3)-1)*100) -> 10.765307 | U64: =IF(INDEX(Historical!$H$7:$H$1044,MATCH(B64,Historical!$B$7:$B$1044,0))=0,"n/a",((INDEX(Historical!$C$7:$C$1044,MATCH(B64,Historical!$B$7:$B$1044,0))/INDEX(Historical!$H$7:$H$1044,MATCH(B64,Historical!$B$7:$B$1044,0)))^(1/5)-1)*100) -> 11.32247 | V64: =IF(INDEX(Historical!$M$7:$M$1044,MATCH(B64,Historical!$B$7:$B$1044,0))=0,"n/a",((INDEX(Historical!$C$7:$C$1044,MATCH(B64,Historical!$B$7:$B$1044,0))/INDEX(Historical!$M$7:$M$1044,MATCH(B64,Historical!$B$7:$B$1044,0)))^(1/10)-1)*100) -> 10.730546 | W64: =IF(OR(U64<=0,U64="n/a",V64<=0,V64="n/a"),"n/a",U64/V64) -> 1.0551625 | X64: =IF(OR(AJ64<=0,AJ64="n/a",U64<=0,U64="n/a"),"n/a",U64/AJ64) -> 1.3242655 | Z64: =IF(OR(AC64<0.01,AC64="n/a"),"n/a",M64/AC64*100) -> 33.836858 | AA64: =IF(OR(AC64<0.01,AC64="n/a"),"n/a",I64/AC64) -> 30.268882 | AB64: 12 | AC64: 3.31 | AD64: n/a | AE64: 2.03 | AF64: 3.3 | AG64: 11.36 | AH64: 10.87 | AI64: 11.55 | AJ64: 8.55 | AK64: n/a | AL64: 4420 | AM64: 7.29 | AN64: 0.22 | AO64: =IF(U64="n/a","n/a",IF(AA64<0,"n/a",IF(AA64="n/a","n/a",J64+U64-AA64))) -> -17.828536 | AP64: =IF(U64="n/a","n/a",J64+U64) -> 12.440346 | AQ64: =IF(OR(AC64<0.01,AC64="n/a",AF64="n/a"),"n/a",(I64/SQRT(22.5*AC64*(I64/AF64))-1)*100) -> 110.69969 | AR64: =INDEX(Historical!$C$7:$C$1045,MATCH(B64,Historical!$B$7:$B$1045,0))*IF(AH64="n/a",1.03,IF(AH64<0,1.01,IF(AH64>10,1.1,(1+AH64/100)))) -> 1.166 | AS64: =IF($AI64="n/a",1.03*AR64,IF($AI64<0,1.01*AR64,IF($AI64>10,1.1*AR64,(1+$AI64/100)*AR64))) -> 1.2826 | AT64: =IF($AK64="n/a",1.03*AS64,IF($AK64<0,1.01*AS64,IF($AK64>10,1.1*AS64,(1+$AK64/100)*AS64))) -> 1.321078 | AU64: =IF($AK64="n/a",1.03*AT64,IF($AK64<0,1.01*AT64,IF($AK64>10,1.1*AT64,(1+$AK64/100)*AT64))) -> 1.3607103 | AV64: =IF($AK64="n/a",1.03*AU64,IF($AK64<0,1.01*AU64,IF($AK64>10,1.1*AU64,(1+$AK64/100)*AU64))) -> 1.4015317 | AW64: =SUM(AR64:AV64) -> 6.53192 | AX64: =AW64/I64*100 -> 6.5195329 | AY64: 1.09 | AZ64: 21.77 | BA64: -10.17 | BB64: 3.48 | BC64: 3.7 | BE64: 1993 | BF64: =IF(BE64>2020,0,IF(BE64>2008,1,IF(BE64>2001,2,IF(BE64>1990,3,IF(BE64>1980,4,IF(BE64>1973,5,IF(BE64>1970,6,IF(BE64>1960,7,IF(BE64>1958,8,IF(BE64>1953,9,10)))))))))) -> 3 | BG64: 7.63 | BH64: USD | BI64: Corp
A65: First Farmers Financial Corporation | B65: FFMR | C65: Financials | D65: Banks | E65: 36 | F65: 83 | G65: - | H65: - | I65: 65.9 | J65: =(M65/I65)*100 -> 3.1562974 | K65: 0.52 | L65: 4 | M65: =K65*L65 -> 2.08 | N65: A13 | O65: 0.51 | P65: 46112 | Q65: 46127 | R65: =(K65-O65)/O65*100 -> 1.9607843 | S65: =IF(INDEX(Historical!$D$7:$D1269,MATCH(B65,Historical!$B$7:$B$1044,0))=0,"n/a",(INDEX(Historical!$C$7:$C$1044,MATCH(B65,Historical!$B$7:$B$1044,0))/INDEX(Historical!$D$7:$D$1044,MATCH(B65,Historical!$B$7:$B$1044,0))-1)*100) -> 3.125 | T65: =IF(INDEX(Historical!$F$7:$F$1044,MATCH(B65,Historical!$B$7:$B$1044,0))=0,"n/a",((INDEX(Historical!$C$7:$C$1044,MATCH(B65,Historical!$B$7:$B$1044,0))/INDEX(Historical!$F$7:$F$1044,MATCH(B65,Historical!$B$7:$B$1044,0)))^(1/3)-1)*100) -> 6.6987165 | U65: =IF(INDEX(Historical!$H$7:$H$1044,MATCH(B65,Historical!$B$7:$B$1044,0))=0,"n/a",((INDEX(Historical!$C$7:$C$1044,MATCH(B65,Historical!$B$7:$B$1044,0))/INDEX(Historical!$H$7:$H$1044,MATCH(B65,Historical!$B$7:$B$1044,0)))^(1/5)-1)*100) -> 9.116655 | V65: =IF(INDEX(Historical!$M$7:$M$1044,MATCH(B65,Historical!$B$7:$B$1044,0))=0,"n/a",((INDEX(Historical!$C$7:$C$1044,MATCH(B65,Historical!$B$7:$B$1044,0))/INDEX(Historical!$M$7:$M$1044,MATCH(B65,Historical!$B$7:$B$1044,0)))^(1/10)-1)*100) -> 12.966827 | W65: =IF(OR(U65<=0,U65="n/a",V65<=0,V65="n/a"),"n/a",U65/V65) -> 0.70307521 | X65: =IF(OR(AJ65<=0,AJ65="n/a",U65<=0,U65="n/a"),"n/a",U65/AJ65) -> n/a | Z65: =IF(OR(AC65<0.01,AC65="n/a"),"n/a",M65/AC65*100) -> n/a | AA65: =IF(OR(AC65<0.01,AC65="n/a"),"n/a",I65/AC65) -> n/a | AB65: 12 | AC65: n/a | AD65: n/a | AE65: n/a | AF65: n/a | AG65: n/a | AH65: n/a | AI65: n/a | AJ65: n/a | AK65: n/a | AL65: n/a | AM65: n/a | AN65: n/a | AO65: =IF(U65="n/a","n/a",IF(AA65<0,"n/a",IF(AA65="n/a","n/a",J65+U65-AA65))) -> n/a | AP65: =IF(U65="n/a","n/a",J65+U65) -> 12.272952 | AQ65: =IF(OR(AC65<0.01,AC65="n/a",AF65="n/a"),"n/a",(I65/SQRT(22.5*AC65*(I65/AF65))-1)*100) -> n/a | AR65: =INDEX(Historical!$C$7:$C$1045,MATCH(B65,Historical!$B$7:$B$1045,0))*IF(AH65="n/a",1.03,IF(AH65<0,1.01,IF(AH65>10,1.1,(1+AH65/100)))) -> 2.0394 | AS65: =IF($AI65="n/a",1.03*AR65,IF($AI65<0,1.01*AR65,IF($AI65>10,1.1*AR65,(1+$AI65/100)*AR65))) -> 2.100582 | AT65: =IF($AK65="n/a",1.03*AS65,IF($AK65<0,1.01*AS65,IF($AK65>10,1.1*AS65,(1+$AK65/100)*AS65))) -> 2.1635995 | AU65: =IF($AK65="n/a",1.03*AT65,IF($AK65<0,1.01*AT65,IF($AK65>10,1.1*AT65,(1+$AK65/100)*AT65))) -> 2.2285074 | AV65: =IF($AK65="n/a",1.03*AU65,IF($AK65<0,1.01*AU65,IF($AK65>10,1.1*AU65,(1+$AK65/100)*AU65))) -> 2.2953627 | AW65: =SUM(AR65:AV65) -> 10.827452 | AX65: =AW65/I65*100 -> 16.430124 | AY65: n/a | AZ65: n/a | BA65: n/a | BB65: n/a | BC65: n/a | BD65: OTC | BE65: 2008 | BF65: =IF(BE65>2020,0,IF(BE65>2008,1,IF(BE65>2001,2,IF(BE65>1990,3,IF(BE65>1980,4,IF(BE65>1973,5,IF(BE65>1970,6,IF(BE65>1960,7,IF(BE65>1958,8,IF(BE65>1953,9,10)))))))))) -> 2 | BG65: n/a | BH65: USD | BI65: Corp
A66: Farmers & Merchants Bancorp | B66: FMCB | C66: Financials | D66: Banks | E66: 63 | F66: 13 | G66: - | H66: - | I66: 1275 | J66: =(M66/I66)*100 -> 1.6 | K66: 5.1 | L66: 4 | M66: =K66*L66 -> 20.4 | N66: A1 | O66: 5.05 | P66: 46092 | Q66: 46113 | R66: =(K66-O66)/O66*100 -> 0.99009901 | S66: =IF(INDEX(Historical!$D$7:$D1276,MATCH(B66,Historical!$B$7:$B$1044,0))=0,"n/a",(INDEX(Historical!$C$7:$C$1044,MATCH(B66,Historical!$B$7:$B$1044,0))/INDEX(Historical!$D$7:$D$1044,MATCH(B66,Historical!$B$7:$B$1044,0))-1)*100) -> 5.6818182 | T66: =IF(INDEX(Historical!$F$7:$F$1044,MATCH(B66,Historical!$B$7:$B$1044,0))=0,"n/a",((INDEX(Historical!$C$7:$C$1044,MATCH(B66,Historical!$B$7:$B$1044,0))/INDEX(Historical!$F$7:$F$1044,MATCH(B66,Historical!$B$7:$B$1044,0)))^(1/3)-1)*100) -> 5.9252589 | U66: =IF(INDEX(Historical!$H$7:$H$1044,MATCH(B66,Historical!$B$7:$B$1044,0))=0,"n/a",((INDEX(Historical!$C$7:$C$1044,MATCH(B66,Historical!$B$7:$B$1044,0))/INDEX(Historical!$H$7:$H$1044,MATCH(B66,Historical!$B$7:$B$1044,0)))^(1/5)-1)*100) -> 5.2519354 | V66: =IF(INDEX(Historical!$M$7:$M$1044,MATCH(B66,Historical!$B$7:$B$1044,0))=0,"n/a",((INDEX(Historical!$C$7:$C$1044,MATCH(B66,Historical!$B$7:$B$1044,0))/INDEX(Historical!$M$7:$M$1044,MATCH(B66,Historical!$B$7:$B$1044,0)))^(1/10)-1)*100) -> 3.8078742 | W66: =IF(OR(U66<=0,U66="n/a",V66<=0,V66="n/a"),"n/a",U66/V66) -> 1.3792303 | X66: =IF(OR(AJ66<=0,AJ66="n/a",U66<=0,U66="n/a"),"n/a",U66/AJ66) -> n/a | Z66: =IF(OR(AC66<0.01,AC66="n/a"),"n/a",M66/AC66*100) -> n/a | AA66: =IF(OR(AC66<0.01,AC66="n/a"),"n/a",I66/AC66) -> n/a | AB66: 12 | AC66: n/a | AD66: n/a | AE66: n/a | AF66: n/a | AG66: n/a | AH66: n/a | AI66: n/a | AJ66: n/a | AK66: n/a | AL66: n/a | AM66: n/a | AN66: n/a | AO66: =IF(U66="n/a","n/a",IF(AA66<0,"n/a",IF(AA66="n/a","n/a",J66+U66-AA66))) -> n/a | AP66: =IF(U66="n/a","n/a",J66+U66) -> 6.8519354 | AQ66: =IF(OR(AC66<0.01,AC66="n/a",AF66="n/a"),"n/a",(I66/SQRT(22.5*AC66*(I66/AF66))-1)*100) -> n/a | AR66: =INDEX(Historical!$C$7:$C$1045,MATCH(B66,Historical!$B$7:$B$1045,0))*IF(AH66="n/a",1.03,IF(AH66<0,1.01,IF(AH66>10,1.1,(1+AH66/100)))) -> 19.158 | AS66: =IF($AI66="n/a",1.03*AR66,IF($AI66<0,1.01*AR66,IF($AI66>10,1.1*AR66,(1+$AI66/100)*AR66))) -> 19.73274 | AT66: =IF($AK66="n/a",1.03*AS66,IF($AK66<0,1.01*AS66,IF($AK66>10,1.1*AS66,(1+$AK66/100)*AS66))) -> 20.324722 | AU66: =IF($AK66="n/a",1.03*AT66,IF($AK66<0,1.01*AT66,IF($AK66>10,1.1*AT66,(1+$AK66/100)*AT66))) -> 20.934464 | AV66: =IF($AK66="n/a",1.03*AU66,IF($AK66<0,1.01*AU66,IF($AK66>10,1.1*AU66,(1+$AK66/100)*AU66))) -> 21.562498 | AW66: =SUM(AR66:AV66) -> 101.71242 | AX66: =AW66/I66*100 -> 7.977445 | AY66: n/a | AZ66: n/a | BA66: n/a | BB66: n/a | BC66: n/a | BD66: OTC | BE66: 1964 | BF66: =IF(BE66>2020,0,IF(BE66>2008,1,IF(BE66>2001,2,IF(BE66>1990,3,IF(BE66>1980,4,IF(BE66>1973,5,IF(BE66>1970,6,IF(BE66>1960,7,IF(BE66>1958,8,IF(BE66>1953,9,10)))))))))) -> 7 | BG66: n/a | BH66: USD | BI66: Corp
A67: Federal Realty Investment Trust | B67: FRT | C67: Real Estate | D67: Retail REITs | E67: 58 | F67: 23 | G67: N | H67: N | I67: 110.9 | J67: =(M67/I67)*100 -> 4.0757439 | K67: 1.13 | L67: 4 | M67: =K67*L67 -> 4.52 | N67: A16 | O67: 1.1 | P67: 45931 | Q67: 45945 | R67: =(K67-O67)/O67*100 -> 2.7272727 | S67: =IF(INDEX(Historical!$D$7:$D1283,MATCH(B67,Historical!$B$7:$B$1044,0))=0,"n/a",(INDEX(Historical!$C$7:$C$1044,MATCH(B67,Historical!$B$7:$B$1044,0))/INDEX(Historical!$D$7:$D$1044,MATCH(B67,Historical!$B$7:$B$1044,0))-1)*100) -> 1.3729977 | T67: =IF(INDEX(Historical!$F$7:$F$1044,MATCH(B67,Historical!$B$7:$B$1044,0))=0,"n/a",((INDEX(Historical!$C$7:$C$1044,MATCH(B67,Historical!$B$7:$B$1044,0))/INDEX(Historical!$F$7:$F$1044,MATCH(B67,Historical!$B$7:$B$1044,0)))^(1/3)-1)*100) -> 1.076178 | U67: =IF(INDEX(Historical!$H$7:$H$1044,MATCH(B67,Historical!$B$7:$B$1044,0))=0,"n/a",((INDEX(Historical!$C$7:$C$1044,MATCH(B67,Historical!$B$7:$B$1044,0))/INDEX(Historical!$H$7:$H$1044,MATCH(B67,Historical!$B$7:$B$1044,0)))^(1/5)-1)*100) -> 1.0239455 | V67: =IF(INDEX(Historical!$M$7:$M$1044,MATCH(B67,Historical!$B$7:$B$1044,0))=0,"n/a",((INDEX(Historical!$C$7:$C$1044,MATCH(B67,Historical!$B$7:$B$1044,0))/INDEX(Historical!$M$7:$M$1044,MATCH(B67,Historical!$B$7:$B$1044,0)))^(1/10)-1)*100) -> 2.2392223 | W67: =IF(OR(U67<=0,U67="n/a",V67<=0,V67="n/a"),"n/a",U67/V67) -> 0.4572773 | X67: =IF(OR(AJ67<=0,AJ67="n/a",U67<=0,U67="n/a"),"n/a",U67/AJ67) -> 0.043479641 | Z67: =IF(OR(AC67<0.01,AC67="n/a"),"n/a",M67/AC67*100) -> 96.788009 | AA67: =IF(OR(AC67<0.01,AC67="n/a"),"n/a",I67/AC67) -> 23.747323 | AB67: 12 | AC67: 4.67 | AD67: n/a | AE67: 7.54 | AF67: 3.1 | AG67: 12.76 | AH67: -38.29 | AI67: 5.88 | AJ67: 23.55 | AK67: -9.99 | AL67: 9640 | AM67: 0.94 | AN67: 1.61 | AO67: =IF(U67="n/a","n/a",IF(AA67<0,"n/a",IF(AA67="n/a","n/a",J67+U67-AA67))) -> -18.647634 | AP67: =IF(U67="n/a","n/a",J67+U67) -> 5.0996894 | AQ67: =IF(OR(AC67<0.01,AC67="n/a",AF67="n/a"),"n/a",(I67/SQRT(22.5*AC67*(I67/AF67))-1)*100) -> 80.882654 | AR67: =INDEX(Historical!$C$7:$C$1045,MATCH(B67,Historical!$B$7:$B$1045,0))*IF(AH67="n/a",1.03,IF(AH67<0,1.01,IF(AH67>10,1.1,(1+AH67/100)))) -> 4.4743 | AS67: =IF($AI67="n/a",1.03*AR67,IF($AI67<0,1.01*AR67,IF($AI67>10,1.1*AR67,(1+$AI67/100)*AR67))) -> 4.7373888 | AT67: =IF($AK67="n/a",1.03*AS67,IF($AK67<0,1.01*AS67,IF($AK67>10,1.1*AS67,(1+$AK67/100)*AS67))) -> 4.7847627 | AU67: =IF($AK67="n/a",1.03*AT67,IF($AK67<0,1.01*AT67,IF($AK67>10,1.1*AT67,(1+$AK67/100)*AT67))) -> 4.8326104 | AV67: =IF($AK67="n/a",1.03*AU67,IF($AK67<0,1.01*AU67,IF($AK67>10,1.1*AU67,(1+$AK67/100)*AU67))) -> 4.8809365 | AW67: =SUM(AR67:AV67) -> 23.709998 | AX67: =AW67/I67*100 -> 21.37962 | AY67: 0.94 | AZ67: 23.24 | BA67: -1.94 | BB67: 2.84 | BC67: 9.68 | BE67: 1968 | BF67: =IF(BE67>2020,0,IF(BE67>2008,1,IF(BE67>2001,2,IF(BE67>1990,3,IF(BE67>1980,4,IF(BE67>1973,5,IF(BE67>1970,6,IF(BE67>1960,7,IF(BE67>1958,8,IF(BE67>1953,9,10)))))))))) -> 7 | BG67: 4.64 | BH67: USD | BI67: REIT
A68: H.B. Fuller Company | B68: FUL | C68: Materials | D68: Chemicals | E68: 57 | F68: 26 | G68: Y | H68: Y | I68: 60.52 | J68: =(M68/I68)*100 -> 1.6192994 | K68: 0.245 | L68: 4 | M68: =K68*L68 -> 0.98 | N68: B10 | O68: 0.235 | P68: 46142 | Q68: 46156 | R68: =(K68-O68)/O68*100 -> 4.2553191 | S68: =IF(INDEX(Historical!$D$7:$D1287,MATCH(B68,Historical!$B$7:$B$1044,0))=0,"n/a",(INDEX(Historical!$C$7:$C$1044,MATCH(B68,Historical!$B$7:$B$1044,0))/INDEX(Historical!$D$7:$D$1044,MATCH(B68,Historical!$B$7:$B$1044,0))-1)*100) -> 6.3037249 | T68: =IF(INDEX(Historical!$F$7:$F$1044,MATCH(B68,Historical!$B$7:$B$1044,0))=0,"n/a",((INDEX(Historical!$C$7:$C$1044,MATCH(B68,Historical!$B$7:$B$1044,0))/INDEX(Historical!$F$7:$F$1044,MATCH(B68,Historical!$B$7:$B$1044,0)))^(1/3)-1)*100) -> 7.9403854 | U68: =IF(INDEX(Historical!$H$7:$H$1044,MATCH(B68,Historical!$B$7:$B$1044,0))=0,"n/a",((INDEX(Historical!$C$7:$C$1044,MATCH(B68,Historical!$B$7:$B$1044,0))/INDEX(Historical!$H$7:$H$1044,MATCH(B68,Historical!$B$7:$B$1044,0)))^(1/5)-1)*100) -> 7.4520806 | V68: =IF(INDEX(Historical!$M$7:$M$1044,MATCH(B68,Historical!$B$7:$B$1044,0))=0,"n/a",((INDEX(Historical!$C$7:$C$1044,MATCH(B68,Historical!$B$7:$B$1044,0))/INDEX(Historical!$M$7:$M$1044,MATCH(B68,Historical!$B$7:$B$1044,0)))^(1/10)-1)*100) -> 6.1632913 | W68: =IF(OR(U68<=0,U68="n/a",V68<=0,V68="n/a"),"n/a",U68/V68) -> 1.2091073 | X68: =IF(OR(AJ68<=0,AJ68="n/a",U68<=0,U68="n/a"),"n/a",U68/AJ68) -> 2.3961674 | Z68: =IF(OR(AC68<0.01,AC68="n/a"),"n/a",M68/AC68*100) -> 33.793103 | AA68: =IF(OR(AC68<0.01,AC68="n/a"),"n/a",I68/AC68) -> 20.868966 | AB68: 11 | AC68: 2.9 | AD68: 1.29 | AE68: 0.95 | AF68: 1.6 | AG68: 8.32 | AH68: 11.21 | AI68: 9.03 | AJ68: 3.11 | AK68: 9.13 | AL68: 3300 | AM68: 0.44 | AN68: 1.01 | AO68: =IF(U68="n/a","n/a",IF(AA68<0,"n/a",IF(AA68="n/a","n/a",J68+U68-AA68))) -> -11.797586 | AP68: =IF(U68="n/a","n/a",J68+U68) -> 9.07138 | AQ68: =IF(OR(AC68<0.01,AC68="n/a",AF68="n/a"),"n/a",(I68/SQRT(22.5*AC68*(I68/AF68))-1)*100) -> 21.820168 | AR68: =INDEX(Historical!$C$7:$C$1045,MATCH(B68,Historical!$B$7:$B$1045,0))*IF(AH68="n/a",1.03,IF(AH68<0,1.01,IF(AH68>10,1.1,(1+AH68/100)))) -> 1.02025 | AS68: =IF($AI68="n/a",1.03*AR68,IF($AI68<0,1.01*AR68,IF($AI68>10,1.1*AR68,(1+$AI68/100)*AR68))) -> 1.1123786 | AT68: =IF($AK68="n/a",1.03*AS68,IF($AK68<0,1.01*AS68,IF($AK68>10,1.1*AS68,(1+$AK68/100)*AS68))) -> 1.2139387 | AU68: =IF($AK68="n/a",1.03*AT68,IF($AK68<0,1.01*AT68,IF($AK68>10,1.1*AT68,(1+$AK68/100)*AT68))) -> 1.3247713 | AV68: =IF($AK68="n/a",1.03*AU68,IF($AK68<0,1.01*AU68,IF($AK68>10,1.1*AU68,(1+$AK68/100)*AU68))) -> 1.445723 | AW68: =SUM(AR68:AV68) -> 6.1170616 | AX68: =AW68/I68*100 -> 10.107504 | AY68: 0.96 | AZ68: 24.25 | BA68: -11.82 | BB68: 0.04 | BC68: 0.65 | BE68: 1970 | BF68: =IF(BE68>2020,0,IF(BE68>2008,1,IF(BE68>2001,2,IF(BE68>1990,3,IF(BE68>1980,4,IF(BE68>1973,5,IF(BE68>1970,6,IF(BE68>1960,7,IF(BE68>1958,8,IF(BE68>1953,9,10)))))))))) -> 7 | BG68: 3.14 | BH68: USD | BI68: Corp
A69: General Dynamics Corporation | B69: GD | C69: Industrials | D69: Aerospace & Defense | E69: 35 | F69: 85 | G69: - | H69: - | I69: 344.3 | J69: =(M69/I69)*100 -> 1.8472263 | K69: 1.59 | L69: 4 | M69: =K69*L69 -> 6.36 | N69: B11 | O69: 1.5 | P69: 46122 | Q69: 46150 | R69: =(K69-O69)/O69*100 -> 6 | S69: =IF(INDEX(Historical!$D$7:$D1295,MATCH(B69,Historical!$B$7:$B$1044,0))=0,"n/a",(INDEX(Historical!$C$7:$C$1044,MATCH(B69,Historical!$B$7:$B$1044,0))/INDEX(Historical!$D$7:$D$1044,MATCH(B69,Historical!$B$7:$B$1044,0))-1)*100) -> 6.09319 | T69: =IF(INDEX(Historical!$F$7:$F$1044,MATCH(B69,Historical!$B$7:$B$1044,0))=0,"n/a",((INDEX(Historical!$C$7:$C$1044,MATCH(B69,Historical!$B$7:$B$1044,0))/INDEX(Historical!$F$7:$F$1044,MATCH(B69,Historical!$B$7:$B$1044,0)))^(1/3)-1)*100) -> 6.0038827 | U69: =IF(INDEX(Historical!$H$7:$H$1044,MATCH(B69,Historical!$B$7:$B$1044,0))=0,"n/a",((INDEX(Historical!$C$7:$C$1044,MATCH(B69,Historical!$B$7:$B$1044,0))/INDEX(Historical!$H$7:$H$1044,MATCH(B69,Historical!$B$7:$B$1044,0)))^(1/5)-1)*100) -> 6.5044103 | V69: =IF(INDEX(Historical!$M$7:$M$1044,MATCH(B69,Historical!$B$7:$B$1044,0))=0,"n/a",((INDEX(Historical!$C$7:$C$1044,MATCH(B69,Historical!$B$7:$B$1044,0))/INDEX(Historical!$M$7:$M$1044,MATCH(B69,Historical!$B$7:$B$1044,0)))^(1/10)-1)*100) -> 8.2073952 | W69: =IF(OR(U69<=0,U69="n/a",V69<=0,V69="n/a"),"n/a",U69/V69) -> 0.79250604 | X69: =IF(OR(AJ69<=0,AJ69="n/a",U69<=0,U69="n/a"),"n/a",U69/AJ69) -> 0.92392191 | Z69: =IF(OR(AC69<0.01,AC69="n/a"),"n/a",M69/AC69*100) -> 40 | AA69: =IF(OR(AC69<0.01,AC69="n/a"),"n/a",I69/AC69) -> 21.654088 | AB69: 12 | AC69: 15.9 | AD69: 2.32 | AE69: 1.73 | AF69: 3.57 | AG69: 17.97 | AH69: 6.74 | AI69: 10 | AJ69: 7.04 | AK69: 8.17 | AL69: 93250 | AM69: 0.62 | AN69: 0.38 | AO69: =IF(U69="n/a","n/a",IF(AA69<0,"n/a",IF(AA69="n/a","n/a",J69+U69-AA69))) -> -13.302452 | AP69: =IF(U69="n/a","n/a",J69+U69) -> 8.3516365 | AQ69: =IF(OR(AC69<0.01,AC69="n/a",AF69="n/a"),"n/a",(I69/SQRT(22.5*AC69*(I69/AF69))-1)*100) -> 85.358625 | AR69: =INDEX(Historical!$C$7:$C$1045,MATCH(B69,Historical!$B$7:$B$1045,0))*IF(AH69="n/a",1.03,IF(AH69<0,1.01,IF(AH69>10,1.1,(1+AH69/100)))) -> 6.319008 | AS69: =IF($AI69="n/a",1.03*AR69,IF($AI69<0,1.01*AR69,IF($AI69>10,1.1*AR69,(1+$AI69/100)*AR69))) -> 6.9509088 | AT69: =IF($AK69="n/a",1.03*AS69,IF($AK69<0,1.01*AS69,IF($AK69>10,1.1*AS69,(1+$AK69/100)*AS69))) -> 7.518798 | AU69: =IF($AK69="n/a",1.03*AT69,IF($AK69<0,1.01*AT69,IF($AK69>10,1.1*AT69,(1+$AK69/100)*AT69))) -> 8.1330838 | AV69: =IF($AK69="n/a",1.03*AU69,IF($AK69<0,1.01*AU69,IF($AK69>10,1.1*AU69,(1+$AK69/100)*AU69))) -> 8.7975568 | AW69: =SUM(AR69:AV69) -> 37.719355 | AX69: =AW69/I69*100 -> 10.955375 | AY69: 0.34 | AZ69: 28.96 | BA69: -6.87 | BB69: -0.41 | BC69: 1.73 | BE69: 1992 | BF69: =IF(BE69>2020,0,IF(BE69>2008,1,IF(BE69>2001,2,IF(BE69>1990,3,IF(BE69>1980,4,IF(BE69>1973,5,IF(BE69>1970,6,IF(BE69>1960,7,IF(BE69>1958,8,IF(BE69>1953,9,10)))))))))) -> 3 | BG69: 7.51 | BH69: USD | BI69: Corp
A70: Graco Inc. | B70: GGG | C70: Industrials | D70: Machinery | E70: 29 | F70: 127 | G70: N | H70: N | I70: 80.27 | J70: =(M70/I70)*100 -> 1.4700386 | K70: 0.295 | L70: 4 | M70: =K70*L70 -> 1.18 | N70: B07 | O70: 0.275 | P70: 46041 | Q70: 46057 | R70: =(K70-O70)/O70*100 -> 7.2727273 | S70: =IF(INDEX(Historical!$D$7:$D1298,MATCH(B70,Historical!$B$7:$B$1044,0))=0,"n/a",(INDEX(Historical!$C$7:$C$1044,MATCH(B70,Historical!$B$7:$B$1044,0))/INDEX(Historical!$D$7:$D$1044,MATCH(B70,Historical!$B$7:$B$1044,0))-1)*100) -> 7.8431373 | T70: =IF(INDEX(Historical!$F$7:$F$1044,MATCH(B70,Historical!$B$7:$B$1044,0))=0,"n/a",((INDEX(Historical!$C$7:$C$1044,MATCH(B70,Historical!$B$7:$B$1044,0))/INDEX(Historical!$F$7:$F$1044,MATCH(B70,Historical!$B$7:$B$1044,0)))^(1/3)-1)*100) -> 9.4051585 | U70: =IF(INDEX(Historical!$H$7:$H$1044,MATCH(B70,Historical!$B$7:$B$1044,0))=0,"n/a",((INDEX(Historical!$C$7:$C$1044,MATCH(B70,Historical!$B$7:$B$1044,0))/INDEX(Historical!$H$7:$H$1044,MATCH(B70,Historical!$B$7:$B$1044,0)))^(1/5)-1)*100) -> 9.4608784 | V70: =IF(INDEX(Historical!$M$7:$M$1044,MATCH(B70,Historical!$B$7:$B$1044,0))=0,"n/a",((INDEX(Historical!$C$7:$C$1044,MATCH(B70,Historical!$B$7:$B$1044,0))/INDEX(Historical!$M$7:$M$1044,MATCH(B70,Historical!$B$7:$B$1044,0)))^(1/10)-1)*100) -> 10.645376 | W70: =IF(OR(U70<=0,U70="n/a",V70<=0,V70="n/a"),"n/a",U70/V70) -> 0.88873125 | X70: =IF(OR(AJ70<=0,AJ70="n/a",U70<=0,U70="n/a"),"n/a",U70/AJ70) -> 0.95275714 | Z70: =IF(OR(AC70<0.01,AC70="n/a"),"n/a",M70/AC70*100) -> 38.436482 | AA70: =IF(OR(AC70<0.01,AC70="n/a"),"n/a",I70/AC70) -> 26.14658 | AB70: 12 | AC70: 3.07 | AD70: 2.87 | AE70: 5.93 | AF70: 4.86 | AG70: 19.78 | AH70: 6.03 | AI70: 8.41 | AJ70: 9.93 | AK70: 8.26 | AL70: 13320 | AM70: 0.83 | AN70: 0.02 | AO70: =IF(U70="n/a","n/a",IF(AA70<0,"n/a",IF(AA70="n/a","n/a",J70+U70-AA70))) -> -15.215663 | AP70: =IF(U70="n/a","n/a",J70+U70) -> 10.930917 | AQ70: =IF(OR(AC70<0.01,AC70="n/a",AF70="n/a"),"n/a",(I70/SQRT(22.5*AC70*(I70/AF70))-1)*100) -> 137.64809 | AR70: =INDEX(Historical!$C$7:$C$1045,MATCH(B70,Historical!$B$7:$B$1045,0))*IF(AH70="n/a",1.03,IF(AH70<0,1.01,IF(AH70>10,1.1,(1+AH70/100)))) -> 1.16633 | AS70: =IF($AI70="n/a",1.03*AR70,IF($AI70<0,1.01*AR70,IF($AI70>10,1.1*AR70,(1+$AI70/100)*AR70))) -> 1.2644184 | AT70: =IF($AK70="n/a",1.03*AS70,IF($AK70<0,1.01*AS70,IF($AK70>10,1.1*AS70,(1+$AK70/100)*AS70))) -> 1.3688593 | AU70: =IF($AK70="n/a",1.03*AT70,IF($AK70<0,1.01*AT70,IF($AK70>10,1.1*AT70,(1+$AK70/100)*AT70))) -> 1.4819271 | AV70: =IF($AK70="n/a",1.03*AU70,IF($AK70<0,1.01*AU70,IF($AK70>10,1.1*AU70,(1+$AK70/100)*AU70))) -> 1.6043343 | AW70: =SUM(AR70:AV70) -> 6.885869 | AX70: =AW70/I70*100 -> 8.5783842 | AY70: 0.97 | AZ70: 1.78 | BA70: -16.11 | BB70: -7.74 | BC70: -5.82 | BE70: 1998 | BF70: =IF(BE70>2020,0,IF(BE70>2008,1,IF(BE70>2001,2,IF(BE70>1990,3,IF(BE70>1980,4,IF(BE70>1973,5,IF(BE70>1970,6,IF(BE70>1960,7,IF(BE70>1958,8,IF(BE70>1953,9,10)))))))))) -> 3 | BG70: 16.28 | BH70: USD | BI70: Corp
A71: Genuine Parts Company | B71: GPC | C71: Consumer Discretionary | D71: Distributors | E71: 70 | F71: 4 | G71: N | H71: N | I71: 107.23 | J71: =(M71/I71)*100 -> 3.9634431 | K71: 1.0625 | L71: 4 | M71: =K71*L71 -> 4.25 | N71: A02 | O71: 1.03 | P71: 46087 | Q71: 46114 | R71: =(K71-O71)/O71*100 -> 3.1553398 | S71: =IF(INDEX(Historical!$D$7:$D1306,MATCH(B71,Historical!$B$7:$B$1044,0))=0,"n/a",(INDEX(Historical!$C$7:$C$1044,MATCH(B71,Historical!$B$7:$B$1044,0))/INDEX(Historical!$D$7:$D$1044,MATCH(B71,Historical!$B$7:$B$1044,0))-1)*100) -> 3.5443038 | T71: =IF(INDEX(Historical!$F$7:$F$1044,MATCH(B71,Historical!$B$7:$B$1044,0))=0,"n/a",((INDEX(Historical!$C$7:$C$1044,MATCH(B71,Historical!$B$7:$B$1044,0))/INDEX(Historical!$F$7:$F$1044,MATCH(B71,Historical!$B$7:$B$1044,0)))^(1/3)-1)*100) -> 5.3299201 | U71: =IF(INDEX(Historical!$H$7:$H$1044,MATCH(B71,Historical!$B$7:$B$1044,0))=0,"n/a",((INDEX(Historical!$C$7:$C$1044,MATCH(B71,Historical!$B$7:$B$1044,0))/INDEX(Historical!$H$7:$H$1044,MATCH(B71,Historical!$B$7:$B$1044,0)))^(1/5)-1)*100) -> 5.4791073 | V71: =IF(INDEX(Historical!$M$7:$M$1044,MATCH(B71,Historical!$B$7:$B$1044,0))=0,"n/a",((INDEX(Historical!$C$7:$C$1044,MATCH(B71,Historical!$B$7:$B$1044,0))/INDEX(Historical!$M$7:$M$1044,MATCH(B71,Historical!$B$7:$B$1044,0)))^(1/10)-1)*100) -> 5.3879106 | W71: =IF(OR(U71<=0,U71="n/a",V71<=0,V71="n/a"),"n/a",U71/V71) -> 1.0169262 | X71: =IF(OR(AJ71<=0,AJ71="n/a",U71<=0,U71="n/a"),"n/a",U71/AJ71) -> n/a | Z71: =IF(OR(AC71<0.01,AC71="n/a"),"n/a",M71/AC71*100) -> 988.37209 | AA71: =IF(OR(AC71<0.01,AC71="n/a"),"n/a",I71/AC71) -> 249.37209 | AB71: 12 | AC71: 0.43 | AD71: 1.62 | AE71: 0.6 | AF71: 3.3 | AG71: 1.35 | AH71: 4.35 | AI71: 8.88 | AJ71: -18.81 | AK71: 7.91 | AL71: 14760 | AM71: 0.62 | AN71: 1.5 | AO71: =IF(U71="n/a","n/a",IF(AA71<0,"n/a",IF(AA71="n/a","n/a",J71+U71-AA71))) -> -239.92954 | AP71: =IF(U71="n/a","n/a",J71+U71) -> 9.4425504 | AQ71: =IF(OR(AC71<0.01,AC71="n/a",AF71="n/a"),"n/a",(I71/SQRT(22.5*AC71*(I71/AF71))-1)*100) -> 504.76916 | AR71: =INDEX(Historical!$C$7:$C$1045,MATCH(B71,Historical!$B$7:$B$1045,0))*IF(AH71="n/a",1.03,IF(AH71<0,1.01,IF(AH71>10,1.1,(1+AH71/100)))) -> 4.267915 | AS71: =IF($AI71="n/a",1.03*AR71,IF($AI71<0,1.01*AR71,IF($AI71>10,1.1*AR71,(1+$AI71/100)*AR71))) -> 4.6469059 | AT71: =IF($AK71="n/a",1.03*AS71,IF($AK71<0,1.01*AS71,IF($AK71>10,1.1*AS71,(1+$AK71/100)*AS71))) -> 5.0144761 | AU71: =IF($AK71="n/a",1.03*AT71,IF($AK71<0,1.01*AT71,IF($AK71>10,1.1*AT71,(1+$AK71/100)*AT71))) -> 5.4111212 | AV71: =IF($AK71="n/a",1.03*AU71,IF($AK71<0,1.01*AU71,IF($AK71>10,1.1*AU71,(1+$AK71/100)*AU71))) -> 5.8391408 | AW71: =SUM(AR71:AV71) -> 25.179559 | AX71: =AW71/I71*100 -> 23.481823 | AY71: 0.69 | AZ71: 11.6 | BA71: -29.25 | BB71: -1.81 | BC71: -15.7 | BE71: 1957 | BF71: =IF(BE71>2020,0,IF(BE71>2008,1,IF(BE71>2001,2,IF(BE71>1990,3,IF(BE71>1980,4,IF(BE71>1973,5,IF(BE71>1970,6,IF(BE71>1960,7,IF(BE71>1958,8,IF(BE71>1953,9,10)))))))))) -> 9 | BG71: 0.29 | BH71: USD | BI71: Corp
A72: The Gorman-Rupp Company | B72: GRC | C72: Industrials | D72: Machinery | E72: 53 | F72: 39 | G72: N | H72: N | I72: 75.74 | J72: =(M72/I72)*100 -> 1.0034328 | K72: 0.19 | L72: 4 | M72: =K72*L72 -> 0.76 | N72: C08 | O72: 0.185 | P72: 45975 | Q72: 46001 | R72: =(K72-O72)/O72*100 -> 2.7027027 | S72: =IF(INDEX(Historical!$D$7:$D1307,MATCH(B72,Historical!$B$7:$B$1044,0))=0,"n/a",(INDEX(Historical!$C$7:$C$1044,MATCH(B72,Historical!$B$7:$B$1044,0))/INDEX(Historical!$D$7:$D$1044,MATCH(B72,Historical!$B$7:$B$1044,0))-1)*100) -> 2.7586207 | T72: =IF(INDEX(Historical!$F$7:$F$1044,MATCH(B72,Historical!$B$7:$B$1044,0))=0,"n/a",((INDEX(Historical!$C$7:$C$1044,MATCH(B72,Historical!$B$7:$B$1044,0))/INDEX(Historical!$F$7:$F$1044,MATCH(B72,Historical!$B$7:$B$1044,0)))^(1/3)-1)*100) -> 2.8383817 | U72: =IF(INDEX(Historical!$H$7:$H$1044,MATCH(B72,Historical!$B$7:$B$1044,0))=0,"n/a",((INDEX(Historical!$C$7:$C$1044,MATCH(B72,Historical!$B$7:$B$1044,0))/INDEX(Historical!$H$7:$H$1044,MATCH(B72,Historical!$B$7:$B$1044,0)))^(1/5)-1)*100) -> 4.7757678 | V72: =IF(INDEX(Historical!$M$7:$M$1044,MATCH(B72,Historical!$B$7:$B$1044,0))=0,"n/a",((INDEX(Historical!$C$7:$C$1044,MATCH(B72,Historical!$B$7:$B$1044,0))/INDEX(Historical!$M$7:$M$1044,MATCH(B72,Historical!$B$7:$B$1044,0)))^(1/10)-1)*100) -> 6.2845468 | W72: =IF(OR(U72<=0,U72="n/a",V72<=0,V72="n/a"),"n/a",U72/V72) -> 0.7599224 | X72: =IF(OR(AJ72<=0,AJ72="n/a",U72<=0,U72="n/a"),"n/a",U72/AJ72) -> 0.30093055 | Z72: =IF(OR(AC72<0.01,AC72="n/a"),"n/a",M72/AC72*100) -> 34.080717 | AA72: =IF(OR(AC72<0.01,AC72="n/a"),"n/a",I72/AC72) -> 33.964126 | AB72: 12 | AC72: 2.23 | AD72: n/a | AE72: 2.88 | AF72: 4.7 | AG72: 14.54 | AH72: 20.72 | AI72: 14.39 | AJ72: 15.87 | AK72: n/a | AL72: 2000 | AM72: 21.42 | AN72: 0.69 | AO72: =IF(U72="n/a","n/a",IF(AA72<0,"n/a",IF(AA72="n/a","n/a",J72+U72-AA72))) -> -28.184925 | AP72: =IF(U72="n/a","n/a",J72+U72) -> 5.7792006 | AQ72: =IF(OR(AC72<0.01,AC72="n/a",AF72="n/a"),"n/a",(I72/SQRT(22.5*AC72*(I72/AF72))-1)*100) -> 166.35931 | AR72: =INDEX(Historical!$C$7:$C$1045,MATCH(B72,Historical!$B$7:$B$1045,0))*IF(AH72="n/a",1.03,IF(AH72<0,1.01,IF(AH72>10,1.1,(1+AH72/100)))) -> 0.8195 | AS72: =IF($AI72="n/a",1.03*AR72,IF($AI72<0,1.01*AR72,IF($AI72>10,1.1*AR72,(1+$AI72/100)*AR72))) -> 0.90145 | AT72: =IF($AK72="n/a",1.03*AS72,IF($AK72<0,1.01*AS72,IF($AK72>10,1.1*AS72,(1+$AK72/100)*AS72))) -> 0.9284935 | AU72: =IF($AK72="n/a",1.03*AT72,IF($AK72<0,1.01*AT72,IF($AK72>10,1.1*AT72,(1+$AK72/100)*AT72))) -> 0.95634831 | AV72: =IF($AK72="n/a",1.03*AU72,IF($AK72<0,1.01*AU72,IF($AK72>10,1.1*AU72,(1+$AK72/100)*AU72))) -> 0.98503875 | AW72: =SUM(AR72:AV72) -> 4.5908306 | AX72: =AW72/I72*100 -> 6.0613026 | AY72: 1.31 | AZ72: 116.65 | BA72: -3.52 | BB72: 15.99 | BC72: 46.79 | BE72: 1974 | BF72: =IF(BE72>2020,0,IF(BE72>2008,1,IF(BE72>2001,2,IF(BE72>1990,3,IF(BE72>1980,4,IF(BE72>1973,5,IF(BE72>1970,6,IF(BE72>1960,7,IF(BE72>1958,8,IF(BE72>1953,9,10)))))))))) -> 5 | BG72: 6.83 | BH72: USD | BI72: Corp
